Workbook
Name Conversion_Rate: Assumptions!$G$8

Sheet Cover
B14: Date: | F14: =NOW()
B15: Contact: | F15: nick@careerxl.com
B16: Website: | F16: careerxl.com
B19: PRIVATE - NOT FOR REDISTRIBUTION

Sheet Inputs ->

Sheet Assumptions
C3: Assumptions | K3: Formatting
C5: Company Name: | G5: Copart, Inc. (CPRT) | O5: R | P5: G | Q5: B
C6: Historicals Start Date | G6: =YEAR(G7)-3 | K6: Header | O6: 22 | P6: 57 | Q6: 91
C7: LTM Period | G7: 46234 | K7: Emphasis 1 | O7: 221 | P7: 221 | Q7: 221
C8: Conversion Rate | G8: 1 | K8: Emphasis 2 | O8: 191 | P8: 191 | Q8: 191
C9: Units | G9: ($ in millions) | K9: Emphasis 3 | O9: 255 | P9: 242 | Q9: 204
K11: Hardcoded | O11: 0 | P11: 0 | Q11: 252
K12: Formulas | O12: 0 | P12: 0 | Q12: 0
K13: Linked Outside of Sheet | O13: 0 | P13: 128 | Q13: 0
K14: Linked Inside of Sheet | O14: 128 | P14: 0 | Q14: 128
K15: Unique Entry / Formula | O15: 255 | P15: 0 | Q15: 0

Sheet Model Notes
C3: Model Notes - Copart, Inc. (CPRT) SHORT
C5: 1 | D5: Short CPRT at $27.36 (Sep 30, 2026), target $21.50 (-21%), 6-12 months. Copart is a toll road paid per car, and fewer cars are using the road. Target = 15x FY27E EPS of $1.44; DCF, comps and LBO are cross-checks. Printed case = memo base case (Support!D16 = 2); bear $16.84 / bull $33.90 sit on the switch; probability-weighted $23.45 is a note.
C6: =+C5+1 | D6: Three mechanisms, each a driver. (a) Structural claim decline: units -3% FY27E (Drivers row 192); insurance CPI +49% and repair CPI +57% since 2019, miles driven already 2% above 2019, AEB mandatory Sep 2029. (b) Share loss to IAA: 63.9% to 61.4%, ~167k cars, ~$166M service revenue, Progressive ~90% to IAA (Support rows 62-80). (c) Operating leverage the wrong way: Q4 facility cost per car +14.2% vs revenue per car +5.4%; margin to 33.0% (row 204); interest income $182M to $110M (row 207).
C7: =+C6+1 | D7: Margin path (what drops). Operating margin (Drivers row 204): 38.4% FY23A, 37.1%, 36.5%, 35.4% FY26A, 33.0% FY27E. FY23A-FY26A, -300bp of revenue: G&A +263bp, facility operations +206bp, D&A +98bp, less cost of vehicle sales -267bp. FY26A-FY27E, -242bp: facility operations +227bp, D&A +15bp; G&A and cost of vehicle sales held at FY26 rates. Cause: a growing cost base serves fewer cars. Q4 FY26 US facility cost rose 7.7% on 5.7% fewer US cars (+14.2% per car); management cites long-haul delivery ($17M of the increase), Title Express, wholesale yards and new capacity. Base FY27E: facility cost +$122M (+7.0%) on 3% fewer cars; cost per car +10.3% vs revenue per car +4.0%.
C8: =+C7+1 | D8: Margin path (why 33.0%, and why it holds). FY27E is not a new leg down: FY26A's 35.4% blends 36.5% for the first nine months with a 32.0% Q4 exit ($368.9M / $1,152.4M), so 33.0% sits 100bp above the exit rate. Held to FY36E (Drivers row 205 = 0): units grow only +0.5% a year from FY30E, so no volume re-absorbs yard cost. Management says it will cut cost per car but gives no guidance; no credit given. +100bp of FY27E margin = ~$47M EBIT, ~$0.04 EPS, ~$0.61 on the target; bull case 36.5% = FY25A level. Net margin falls more (31.8% to 28.5%) as interest income drops from $182M to $110M after the ACV payment.
C9: =+C8+1 | D9: Variant view: Street has FY27 EPS $1.75 (+11% per memo) and treats 17.6x vs a 34x ten-year median as a cyclical dip. Model FY27E EPS $1.44, 18% below; Street is a reference cell only (Support!D10). Unlike prior 30%+ drawdowns, trailing EPS is falling.
C10: =+C9+1 | D10: Falsifiers: cover if collision frequency is positive for two quarters; the lost-customer lap is already in the -3% unit assumption; catastrophe volume is excluded from the trend; stop reference $32.60 (above the 50-day and the 23.6% retracement). Short interest 4.6% of float is context, not an input.
C11: =+C10+1 | D11: Catalysts: Q1 FY27 on Nov 19, 2026 (Street $0.40 vs $0.41); RB Global Q3 in early Nov; ACV close by year-end 2026; monthly CCC / insurer claim prints.
C12: =+C11+1 | D12: Column map (no columns inserted): G = FY2023A (year ended July 31, 2023), H = FY2024A, I = FY2025A, J = FY2026A / LTM (July 31, 2026), K-T = FY2027E-FY2036E. Pitch window FY27E-FY31E; FY32E-FY36E fade (units +0.5%, revenue per unit to +1.5%, margin flat). DCF columns G-P = FY27E-FY36E. Units: $ millions except per share; shares in millions.
C13: =+C12+1 | D13: Definitions. Cash = cash, equivalents, restricted cash + held-to-maturity securities ($4,489.8M FY26). Debt = revolver + term loan = 0; finance leases are not split out on the balance sheet (immaterial) and sit in lease liabilities. Capex and buybacks are negative (template sign). Net income = attributable to Copart: NCI loss runs through Other (Income)/Expense, so template EBT = reported pre-tax income + NCI loss ($3.9M FY26). Facility operations and G&A include their SBC; D&A is the cash-flow-statement total, so template gross profit is before D&A (reported FY26 gross profit $2,083.9M = template $2,294.6M - $201.7M facility D&A - $9.1M).
C14: =+C13+1 | D14: Filing vs memo flags. ACV: 8-K says ~$1.9B equity value; memo ~$1.8B; model uses $1.9B. Revenue $4,666M (memo $4.67B), operating income $1,652.6M, EPS $1.55, buybacks $1,632.5M, interest income net $181.9M: all tie. EV/EBITDA on CFS D&A is 11.0x vs memo 11.1x. Street growth is +12.8% on $1.55, memo says +11%. Memo Exhibit 2 base target is $21.54 vs headline $21.50. Bull EPS computes to $1.67 vs memo $1.70 (see Support row 35). Unit levels are an index on the memo 4.0M base; Copart discloses growth rates only.
C15: =+C14+1 | D15: Template formula changes (logged, none to force a result): first forecast column rolls from J (FY26A) instead of I; EPS row on Multiples & Ratios was market cap / shares, now net income / shares; Summary FCF rows for interest, other and taxes now subtract; Financial Model H127:I127, Drivers G148:J148 (pointed at retained earnings) and L150:T150 reference fixes; LBO management rollover made non-circular; historical reconciling line (row 131) closes the derived cash-flow statement in FY23-FY26 only; DCF cost of debt and capital structure are inputs per brief; LBO cash is after ACV and row 83 excludes acquisitions; Comps stats wrapped in IFERROR.
C16: =+C15+1 | D16: Open items left blank and flagged, not invented: OPENLANE multiples and RBA / LKQ full comps lines as of Sep 30, 2026 (only memo forward P/Es loaded); ACV EV and profit measure (not in the 8-K); gross PP&E / accumulated depreciation split; FY23 unit KPIs; IAA unit forecast (KPI 3 forecast = n/a); 2-year weekly beta not re-estimated (1.0 per brief); 10-K cover share count. DCF vs target and LBO IRR: see Support rows 88-116.

Sheet Dashboard ->

Sheet Summary
C3: =Assumptions!G5
C4: Financial Summary | J4: FY26A / LTM
C5: =+Assumptions!G9 | G5: ='Historical Financials'!G5 | H5: ='Historical Financials'!H5 | I5: ='Historical Financials'!I5 | J5: ='Historical Financials'!J5 | K5: ='Financial Model'!K5 | L5: ='Financial Model'!L5 | M5: ='Financial Model'!M5 | N5: ='Financial Model'!N5 | O5: ='Financial Model'!O5 | P5: ='Financial Model'!P5 | Q5: ='Financial Model'!Q5 | R5: ='Financial Model'!R5 | ... T5: ='Financial Model'!T5
C7: ='Financial Model'!C9 | G7: ='Financial Model'!G9 | H7: ='Financial Model'!H9 | I7: ='Financial Model'!I9 | J7: ='Financial Model'!J9 | K7: ='Financial Model'!K9 | L7: ='Financial Model'!L9 | M7: ='Financial Model'!M9 | N7: ='Financial Model'!N9 | ... T7: ='Financial Model'!T9
C8: % Growth | G8: ='Financial Model'!$G$10 | H8: =+H7/G7-1 | I8: =+I7/H7-1 | J8: ='Financial Model'!$J$10 | K8: =+K7/J7-1 | L8: =+L7/K7-1 | M8: =+M7/L7-1 | N8: =+N7/M7-1 | O8: =+O7/N7-1 | P8: =+P7/O7-1 | Q8: =+Q7/P7-1 | R8: =+R7/Q7-1 | ... T8: =+T7/S7-1
C10: ='Financial Model'!C18 | G10: ='Financial Model'!G18 | H10: ='Financial Model'!H18 | I10: ='Financial Model'!I18 | J10: ='Financial Model'!J18 | K10: ='Financial Model'!K18 | L10: ='Financial Model'!L18 | M10: ='Financial Model'!M18 | N10: ='Financial Model'!N18 | ... T10: ='Financial Model'!T18
C11: % Gross Margin | G11: =+G10/G$7 | H11: =+H10/H$7 | I11: =+I10/I$7 | J11: =+J10/J$7 | K11: =+K10/K$7 | L11: =+L10/L$7 | M11: =+M10/M$7 | N11: =+N10/N$7 | ... T11: =+T10/T$7
C13: ='Financial Model'!C24 | G13: ='Financial Model'!G24 | H13: ='Financial Model'!H24 | I13: ='Financial Model'!I24 | J13: ='Financial Model'!J24 | K13: ='Financial Model'!K24 | L13: ='Financial Model'!L24 | M13: ='Financial Model'!M24 | N13: ='Financial Model'!N24 | ... T13: ='Financial Model'!T24
C14: ='Financial Model'!C25 | G14: =+G13/G$7 | H14: =+H13/H$7 | I14: =+I13/I$7 | J14: =+J13/J$7 | K14: =+K13/K$7 | L14: =+L13/L$7 | M14: =+M13/M$7 | N14: =+N13/N$7 | ... T14: =+T13/T$7
C16: ='Financial Model'!C27 | G16: ='Financial Model'!G27 | H16: ='Financial Model'!H27 | I16: ='Financial Model'!I27 | J16: ='Financial Model'!J27 | K16: ='Financial Model'!K27 | L16: ='Financial Model'!L27 | M16: ='Financial Model'!M27 | N16: ='Financial Model'!N27 | ... T16: ='Financial Model'!T27
C17: ='Financial Model'!C28 | G17: =+G16/G$7 | H17: =+H16/H$7 | I17: =+I16/I$7 | J17: =+J16/J$7 | K17: =+K16/K$7 | L17: =+L16/L$7 | M17: =+M16/M$7 | N17: =+N16/N$7 | ... T17: =+T16/T$7
C19: - Interest | G19: =-'Financial Model'!G34 | H19: =-'Financial Model'!H34 | I19: =-'Financial Model'!I34 | J19: =-'Financial Model'!J34 | K19: =-'Financial Model'!K34 | L19: =-'Financial Model'!L34 | M19: =-'Financial Model'!M34 | N19: =-'Financial Model'!N34 | ... T19: =-'Financial Model'!T34
C20: - Other Expenses | G20: =-'Financial Model'!G35 | H20: =-'Financial Model'!H35 | I20: =-'Financial Model'!I35 | J20: =-'Financial Model'!J35 | K20: =-'Financial Model'!K35 | L20: =-'Financial Model'!L35 | M20: =-'Financial Model'!M35 | N20: =-'Financial Model'!N35 | ... T20: =-'Financial Model'!T35
C21: - Taxes | G21: =-'Financial Model'!G38 | H21: =-'Financial Model'!H38 | I21: =-'Financial Model'!I38 | J21: =-'Financial Model'!J38 | K21: =-'Financial Model'!K38 | L21: =-'Financial Model'!L38 | M21: =-'Financial Model'!M38 | N21: =-'Financial Model'!N38 | ... T21: =-'Financial Model'!T38
C22: +/- ∆ Net Working Capital | G22: ='Financial Model'!G114 | H22: ='Financial Model'!H114 | I22: ='Financial Model'!I114 | J22: ='Financial Model'!J114 | K22: ='Financial Model'!K114 | L22: ='Financial Model'!L114 | M22: ='Financial Model'!M114 | N22: ='Financial Model'!N114 | ... T22: ='Financial Model'!T114
C23: - Capex | G23: ='Financial Model'!G118 | H23: ='Financial Model'!H118 | I23: ='Financial Model'!I118 | J23: ='Financial Model'!J118 | K23: ='Financial Model'!K118 | L23: ='Financial Model'!L118 | M23: ='Financial Model'!M118 | N23: ='Financial Model'!N118 | ... T23: ='Financial Model'!T118
C24: Free Cash Flow (FCF) | G24: =SUM(G19:G23)+G16 | H24: =SUM(H19:H23)+H16 | I24: =SUM(I19:I23)+I16 | J24: =SUM(J19:J23)+J16 | K24: =SUM(K19:K23)+K16 | L24: =SUM(L19:L23)+L16 | M24: =SUM(M19:M23)+M16 | N24: =SUM(N19:N23)+N16 | ... T24: =SUM(T19:T23)+T16
C25: % FCF Margin | G25: =+G24/G$7 | H25: =+H24/H$7 | I25: =+I24/I$7 | J25: =+J24/J$7 | K25: =+K24/K$7 | L25: =+L24/L$7 | M25: =+M24/M$7 | N25: =+N24/N$7 | ... T25: =+T24/T$7
C26: % FCF Growth | G26: n/a | H26: =+H24/G24-1 | I26: =+I24/H24-1 | J26: =+J24/I24-1 | K26: =+K24/J24-1 | L26: =+L24/K24-1 | M26: =+M24/L24-1 | N26: =+N24/M24-1 | O26: =+O24/N24-1 | ... T26: =+T24/S24-1
C28: Key Performance Indicators
C29: ='Multiples & Ratios'!C20 | G29: ='Multiples & Ratios'!G20 | H29: ='Multiples & Ratios'!H20 | I29: ='Multiples & Ratios'!I20 | J29: ='Multiples & Ratios'!J20 | K29: ='Multiples & Ratios'!K20 | L29: ='Multiples & Ratios'!L20 | M29: ='Multiples & Ratios'!M20 | N29: ='Multiples & Ratios'!N20 | ... T29: ='Multiples & Ratios'!T20
C30: ='Multiples & Ratios'!C21 | G30: ='Multiples & Ratios'!G21 | H30: ='Multiples & Ratios'!H21 | I30: ='Multiples & Ratios'!I21 | J30: ='Multiples & Ratios'!J21 | K30: ='Multiples & Ratios'!K21 | L30: ='Multiples & Ratios'!L21 | M30: ='Multiples & Ratios'!M21 | N30: ='Multiples & Ratios'!N21 | ... T30: ='Multiples & Ratios'!T21
C31: ='Multiples & Ratios'!C22 | G31: ='Multiples & Ratios'!G22 | H31: ='Multiples & Ratios'!H22 | I31: ='Multiples & Ratios'!I22 | J31: ='Multiples & Ratios'!J22 | K31: ='Multiples & Ratios'!K22 | L31: ='Multiples & Ratios'!L22 | M31: ='Multiples & Ratios'!M22 | N31: ='Multiples & Ratios'!N22 | ... T31: ='Multiples & Ratios'!T22
C33: Efficiency Ratios
C34: ='Multiples & Ratios'!C25 | G34: ='Multiples & Ratios'!G25 | H34: ='Multiples & Ratios'!H25 | I34: ='Multiples & Ratios'!I25 | J34: ='Multiples & Ratios'!J25 | K34: ='Multiples & Ratios'!K25 | L34: ='Multiples & Ratios'!L25 | M34: ='Multiples & Ratios'!M25 | N34: ='Multiples & Ratios'!N25 | ... T34: ='Multiples & Ratios'!T25
C35: ='Multiples & Ratios'!C26 | G35: ='Multiples & Ratios'!G26 | H35: ='Multiples & Ratios'!H26 | I35: ='Multiples & Ratios'!I26 | J35: ='Multiples & Ratios'!J26 | K35: ='Multiples & Ratios'!K26 | L35: ='Multiples & Ratios'!L26 | M35: ='Multiples & Ratios'!M26 | N35: ='Multiples & Ratios'!N26 | ... T35: ='Multiples & Ratios'!T26
C36: ='Multiples & Ratios'!C27 | G36: ='Multiples & Ratios'!G27 | H36: ='Multiples & Ratios'!H27 | I36: ='Multiples & Ratios'!I27 | J36: ='Multiples & Ratios'!J27 | K36: ='Multiples & Ratios'!K27 | L36: ='Multiples & Ratios'!L27 | M36: ='Multiples & Ratios'!M27 | N36: ='Multiples & Ratios'!N27 | ... T36: ='Multiples & Ratios'!T27
C37: ='Multiples & Ratios'!C28 | G37: ='Multiples & Ratios'!G28 | H37: ='Multiples & Ratios'!H28 | I37: ='Multiples & Ratios'!I28 | J37: ='Multiples & Ratios'!J28 | K37: ='Multiples & Ratios'!K28 | L37: ='Multiples & Ratios'!L28 | M37: ='Multiples & Ratios'!M28 | N37: ='Multiples & Ratios'!N28 | ... T37: ='Multiples & Ratios'!T28
C39: Valuation Multiples
C40: ='Multiples & Ratios'!C8 | G40: ='Multiples & Ratios'!G8 | H40: ='Multiples & Ratios'!H8 | I40: ='Multiples & Ratios'!I8 | J40: ='Multiples & Ratios'!J8 | K40: ='Multiples & Ratios'!K8 | L40: ='Multiples & Ratios'!L8 | M40: ='Multiples & Ratios'!M8 | N40: ='Multiples & Ratios'!N8 | ... T40: ='Multiples & Ratios'!T8
C41: ='Multiples & Ratios'!C9 | G41: ='Multiples & Ratios'!G9 | H41: ='Multiples & Ratios'!H9 | I41: ='Multiples & Ratios'!I9 | J41: ='Multiples & Ratios'!J9 | K41: ='Multiples & Ratios'!K9 | L41: ='Multiples & Ratios'!L9 | M41: ='Multiples & Ratios'!M9 | N41: ='Multiples & Ratios'!N9 | ... T41: ='Multiples & Ratios'!T9
C42: ='Multiples & Ratios'!C10 | G42: ='Multiples & Ratios'!G10 | H42: ='Multiples & Ratios'!H10 | I42: ='Multiples & Ratios'!I10 | J42: ='Multiples & Ratios'!J10 | K42: ='Multiples & Ratios'!K10 | L42: ='Multiples & Ratios'!L10 | M42: ='Multiples & Ratios'!M10 | N42: ='Multiples & Ratios'!N10 | ... T42: ='Multiples & Ratios'!T10
C43: ='Multiples & Ratios'!C11 | G43: ='Multiples & Ratios'!G11 | H43: ='Multiples & Ratios'!H11 | I43: ='Multiples & Ratios'!I11 | J43: ='Multiples & Ratios'!J11 | K43: ='Multiples & Ratios'!K11 | L43: ='Multiples & Ratios'!L11 | M43: ='Multiples & Ratios'!M11 | N43: ='Multiples & Ratios'!N11 | ... T43: ='Multiples & Ratios'!T11

Sheet Summary Charts
O33: =Summary!G5 | P33: =Summary!H5 | Q33: =Summary!I5 | R33: =Summary!J5 | S33: =Summary!K5 | T33: =Summary!L5 | U33: =Summary!M5
L35: Revenue Growth | O35: =Summary!G8 | P35: =Summary!H8 | Q35: =Summary!I8 | R35: =Summary!J8 | S35: =Summary!K8 | T35: =Summary!L8 | U35: =Summary!M8
L36: Gross Margin | O36: =Summary!G11 | P36: =Summary!H11 | Q36: =Summary!I11 | R36: =Summary!J11 | S36: =Summary!K11 | T36: =Summary!L11 | U36: =Summary!M11
L37: Opex (% of Revenue) | O37: =Summary!G14 | P37: =Summary!H14 | Q37: =Summary!I14 | R37: =Summary!J14 | S37: =Summary!K14 | T37: =Summary!L14 | U37: =Summary!M14
L38: FCF Margin | O38: =Summary!G25 | P38: =Summary!H25 | Q38: =Summary!I25 | R38: =Summary!J25 | S38: =Summary!K25 | T38: =Summary!L25 | U38: =Summary!M25
L39: FCF Growth | O39: =Summary!G26 | P39: =Summary!H26 | Q39: =Summary!I26 | R39: =Summary!J26 | S39: =Summary!K26 | T39: =Summary!L26 | U39: =Summary!M26
L41: =Summary!C29 | O41: =Summary!G29 | P41: =Summary!H29 | Q41: =Summary!I29 | R41: =Summary!J29 | S41: =Summary!K29 | T41: =Summary!L29 | U41: =Summary!M29
L42: =Summary!C30 | O42: =Summary!G30 | P42: =Summary!H30 | Q42: =Summary!I30 | R42: =Summary!J30 | S42: =Summary!K30 | T42: =Summary!L30 | U42: =Summary!M30
L43: =Summary!C31 | O43: =Summary!G31 | P43: =Summary!H31 | Q43: =Summary!I31 | R43: =Summary!J31 | S43: =Summary!K31 | T43: =Summary!L31 | U43: =Summary!M31
L45: ROE | O45: =Summary!G34 | P45: =Summary!H34 | Q45: =Summary!I34 | R45: =Summary!J34 | S45: =Summary!K34 | T45: =Summary!L34 | U45: =Summary!M34
L46: ROA | O46: =Summary!G35 | P46: =Summary!H35 | Q46: =Summary!I35 | R46: =Summary!J35 | S46: =Summary!K35 | T46: =Summary!L35 | U46: =Summary!M35
L47: ROIC | O47: =Summary!G36 | P47: =Summary!H36 | Q47: =Summary!I36 | R47: =Summary!J36 | S47: =Summary!K36 | T47: =Summary!L36 | U47: =Summary!M36
L48: EPS | O48: =Summary!G37 | P48: =Summary!H37 | Q48: =Summary!I37 | R48: =Summary!J37 | S48: =Summary!K37 | T48: =Summary!L37 | U48: =Summary!M37

Sheet Financials ->

Sheet Historical Financials
G1: =Assumptions!$G$6 | H1: =+G1+1 | I1: =+H1+1 | J1: =Assumptions!G7 | M1: X
M2: X
C3: =Assumptions!G5&" - Financial Inputs Tab" | M3: X
J4: FY26A / LTM
G5: ="FY"&G1&"A" | H5: ="FY"&H1&"A" | I5: ="FY"&I1&"A" | J5: ="FY"&YEAR(J1)&"A" | M5: X
M6: X
C7: Income Statement | M7: X
M8: X
C9: Service revenues | G9: 3198.128 | H9: 3561.002 | I9: 3968.662 | J9: 3969.52 | M9: X
C10: Vehicle sales | G10: 671.39 | H10: 675.821 | I10: 678.296 | J10: 696.689 | M10: X
C11: Total Revenue | G11: =SUM(G9:G10) | H11: =SUM(H9:H10) | I11: =SUM(I9:I10) | J11: =SUM(J9:J10) | M11: X
M12: X
C13: Facility operations (incl. facility SBC; ex-D&A) | G13: =1369.006+6.926-(159.684-142.097-17.381) | H13: =1532.484+6.95-(190.256-170.65-19.111) | I13: =1744.436+8.107-(217.784-191.775-24.074) | J13: =1755.747+8.472-(238.466-201.669-27.704) | M13: X
C14: Cost of vehicle sales | G14: 614.498 | H14: 619.487 | I14: 602.997 | J14: 616.463 | M14: X
C15: Total COGS | G15: =SUM(G13:G14) | H15: =SUM(H13:H14) | I15: =SUM(I13:I14) | J15: =SUM(J13:J14) | M15: X
C16: % of Revenue | G16: =+G15/G11 | H16: =+H15/H11 | I16: =+I15/I11 | J16: =+J15/J11 | M16: X
M17: X
C18: Gross Profit | G18: =+G11-G15 | H18: =+H11-H15 | I18: =+I11-I15 | J18: =+J11-J15 | M18: X
C19: % Gross Margin | G19: =+G18/G11 | H19: =+H18/H11 | I19: =+I18/I11 | J19: =+J18/J11 | M19: X
M20: X
C21: General & Administrative | G21: =200.294+32.747 | H21: =287.834+28.284 | I21: =348.958+29.897 | J21: =373.218+30.346 | M21: X
C22: Sales & Marketing | G22: 0 | H22: 0 | I22: 0 | J22: 0 | M22: X
C23: Research & Development | G23: 0 | H23: 0 | I23: 0 | J23: 0 | M23: X
C24: Total Operating Expenses | G24: =SUM(G23,G22,G21) | H24: =SUM(H23,H22,H21) | I24: =SUM(I23,I22,I21) | J24: =SUM(J23,J22,J21) | M24: X
C25: % of Revenue | G25: =+G24/G$11 | H25: =+H24/H$11 | I25: =+I24/I$11 | J25: =+J24/J$11 | M25: X
M26: X
C27: EBITDA | G27: =+G18-G24 | H27: =+H18-H24 | I27: =+I18-I24 | J27: =+J18-J24 | M27: X
C28: % EBITDA Margin | G28: =+G27/G$11 | H28: =+H27/H$11 | I28: =+I27/I$11 | J28: =+J27/J$11 | M28: X
M29: X
C30: Depreciation | G30: 159.684 | H30: 190.256 | I30: 217.784 | J30: 238.466 | M30: X
C31: Amortization | G31: 0 | H31: 0 | I31: 0 | J31: 0 | M31: X
M32: X
C33: EBIT | G33: =+G27-SUM(G30:G31) | H33: =+H27-SUM(H30:H31) | I33: =+I27-SUM(I30:I31) | J33: =+J27-SUM(J30:J31) | M33: X
C34: % EBIT Margin | G34: =+G33/G$11 | H34: =+H33/H$11 | I34: =+I33/I$11 | J34: =+J33/J$11 | M34: X
M35: X
C36: Interest Expense | G36: 2.614 | H36: 3.127 | I36: 2.019 | J36: 1.866 | M36: X
M37: X
C38: Interest income, gross (= -(Interest income, net + interest paid)) | G38: =-(65.928+2.614) | H38: =-(145.673+3.127) | I38: =-(178.909+2.019) | J38: =-(181.923+1.866) | M38: X
C39: Other (income) expense, net | G39: -1.831 | H39: 3.095 | I39: -19.958 | J39: -0.464 | M39: X
C40: Net loss attributable to noncontrolling interest | G40: 0 | H40: -0.673 | I40: -4.086 | J40: -3.873 | M40: X
C41: Other (Income) Expenses | G41: =SUM(G38:G40) | H41: =SUM(H38:H40) | I41: =SUM(I38:I40) | J41: =SUM(J38:J40) | M41: X
C42: % of Revenue | G42: =+G41/G$11 | H42: =+H41/H$11 | I42: =+I41/I$11 | J42: =+J41/J$11 | M42: X
M43: X
C44: EBT | G44: =+G33-SUM(G41,G36) | H44: =+H33-SUM(H41,H36) | I44: =+I33-SUM(I41,I36) | J44: =+J33-SUM(J41,J36) | M44: X
C45: % EBIT Margin | G45: =+G44/G$11 | H45: =+H44/H$11 | I45: =+I44/I$11 | J45: =+J44/J$11 | M45: X
M46: X
C47: Taxes | G47: 316.587 | H47: 352.254 | I47: 347.218 | J47: 354.58 | M47: X
M48: X
C49: Net Income | G49: =+G44-G47 | H49: =+H44-H47 | I49: =+I44-I47 | J49: =+J44-J47 | M49: X
C50: % Profit Margin | G50: =+G49/G$11 | H50: =+H49/H$11 | I50: =+I49/I$11 | J50: =+J49/J$11 | M50: X
M51: X
C52: Company Reported Net Income | G52: 1237.741 | H52: 1363.02 | I52: 1552.449 | J52: 1484.27 | M52: X
C53: Check | G53: =+G49-G52 | H53: =+H49-H52 | I53: =+I49-I52 | J53: =+J49-J52 | M53: X
M54: X
A55: X | C55: Balance Sheet | M55: X
M56: X
C57: Assets | M57: X
M58: X
C59: Cash, equivalents, restricted cash + HTM securities | G59: =957.395+1406.589 | H59: =1514.111+1908.047 | I59: =2780.531+2008.539 | J59: =1907.901+2581.901 | M59: X
C60: Accounts Receivable | G60: 702.038 | H60: 785.877 | I60: 762.811 | J60: 809.247 | M60: X
C61: Prepaid Expenses | G61: 26.31 | H61: 33.872 | I61: 46.361 | J61: 44.959 | M61: X
C62: Inventories | G62: 39.973 | H62: 43.639 | I62: 39.661 | J62: 51.382 | M62: X
C63: Vehicle pooling costs + income taxes receivable | G63: =123.725+6.574 | H63: =132.638+0 | I63: =116.145+0.58 | J63: =122.948+49.856 | M63: X
C64: Total Current Assets | G64: =SUM(G59:G63) | H64: =SUM(H59:H63) | I64: =SUM(I59:I63) | J64: =SUM(J59:J63) | M64: X
M65: X
C66: PP&E, net (gross/accumulated split not loaded) | G66: 2844.339 | H66: 3175.838 | I66: 3598.093 | J66: 3733.22 | M66: X
C67: (Accumulated Depreciation) | G67: 0 | H67: 0 | I67: 0 | J67: 0 | M67: X
C68: Net PPE | G68: =SUM(G66:G67) | H68: =SUM(H66:H67) | I68: =SUM(I66:I67) | J68: =SUM(J66:J67) | M68: X
M69: X
M70: X
C71: Goodwill + intangibles, net | G71: =394.289+62.702 | H71: =513.909+74.088 | I71: =517.779+62.832 | J71: =511.297+50.477 | M71: X
C72: (Accumulated Amortization) | G72: 0 | H72: 0 | I72: 0 | J72: 0 | M72: X
C73: Net Goodwill & Intangibles | G73: =SUM(G71:G72) | H73: =SUM(H71:H72) | I73: =SUM(I71:I72) | J73: =SUM(J71:J72) | M73: X
M74: X
M75: X
C76: Operating lease ROU assets + other assets | G76: =108.139+65.806 | H76: =116.301+129.444 | I76: =99.708+57.862 | J76: =83.728+80.894 | M76: X
M77: X
C78: Total Assets | G78: =SUM(G76,G73,G68,G64) | H78: =SUM(H76,H73,H68,H64) | I78: =SUM(I76,I73,I68,I64) | J78: =SUM(J76,J73,J68,J64) | M78: X
M79: X
A80: X | C80: Liabilities | M80: X
M81: X
C82: Accounts Payable | G82: 440.81 | H82: 518.148 | I82: 591.831 | J82: 634.675 | M82: X
C83: Accrued Expenses | G83: 0 | H83: 0 | I83: 0 | J83: 0 | M83: X
C84: Deferred Revenue | G84: 26.117 | H84: 28.121 | I84: 30.44 | J84: 32.466 | M84: X
C85: Income taxes payable (current) + current lease liabilities | G85: =4.374+21.468 | H85: =60.994+21.304 | I85: =41.141+19.869 | J85: =21.437+15.163 | M85: X
C86: Total Current Liabilities | G86: =SUM(G82:G85) | H86: =SUM(H82:H85) | I86: =SUM(I82:I85) | J86: =SUM(J82:J85) | M86: X
M87: X
C88: Revolver | G88: 10.903 | H88: 0 | I88: 0 | J88: 0 | M88: X
C89: Term Loan | G89: 0 | H89: 0 | I89: 0 | J89: 0 | M89: X
C90: Deferred taxes, LT taxes payable, non-current leases, redeemable NCI | G90: =89.492+69.193+88.082 | H90: =93.653+59.56+97.429+24.544 | I90: =80.625+35.635+83.87+20.458 | J90: =127.918+9.067+73.204+16.585 | M90: X
C91: Total Liabilities | G91: =SUM(G88:G90,G86) | H91: =SUM(H88:H90,H86) | I91: =SUM(I88:I90,I86) | J91: =SUM(J88:J90,J86) | M91: X
M92: X
A93: X | C93: Equity | M93: X
M94: X
C95: Retained Earnings | G95: 5189.44 | H95: 6545.902 | I95: 8093.069 | J95: 7980.626 | M95: X
C96: Common stock + APIC | G96: =0.096+938.91 | H96: =0.096+1120.985 | I96: =0.097+1214.15 | J96: =0.093+1226.354 | M96: X
C97: Accumulated other comprehensive loss | G97: -141.006 | H97: -142.972 | I97: -120.283 | J97: -109.778 | M97: X
C98: Total Equity | G98: =SUM(G95:G97) | H98: =SUM(H95:H97) | I98: =SUM(I95:I97) | J98: =SUM(J95:J97) | M98: X
M99: X
C100: Total Liabilities & Equity | G100: =SUM(G98,G91) | H100: =SUM(H98,H91) | I100: =SUM(I98,I91) | J100: =SUM(J98,J91) | M100: X
...

Sheet Financial Model
K1: =YEAR('Historical Financials'!J1)+1 | L1: =K1+1 | M1: =L1+1 | N1: =M1+1 | O1: =N1+1 | P1: =O1+1 | Q1: =P1+1 | R1: =Q1+1 | S1: =R1+1 | T1: =S1+1
C3: =Assumptions!G5
A4: X | C4: Income Statement | J4: FY26A / LTM
C5: =Assumptions!$G$9 | G5: ='Historical Financials'!G5 | H5: ='Historical Financials'!H5 | I5: ='Historical Financials'!I5 | J5: ='Historical Financials'!J5 | K5: ="FY"&K$1&"E" | L5: ="FY"&L$1&"E" | M5: ="FY"&M$1&"E" | N5: ="FY"&N$1&"E" | O5: ="FY"&O$1&"E" | P5: ="FY"&P$1&"E" | Q5: ="FY"&Q$1&"E" | R5: ="FY"&R$1&"E" | ... T5: ="FY"&T$1&"E"
C7: =+'Historical Financials'!C9 | G7: =+'Historical Financials'!G9/Conversion_Rate | H7: =+'Historical Financials'!H9/Conversion_Rate | I7: =+'Historical Financials'!I9/Conversion_Rate | J7: =+'Historical Financials'!J9/Conversion_Rate | K7: =+Drivers!K8 | L7: =+Drivers!L8 | M7: =+Drivers!M8 | N7: =+Drivers!N8 | O7: =+Drivers!O8 | P7: =+Drivers!P8 | Q7: =+Drivers!Q8 | R7: =+Drivers!R8 | ... T7: =+Drivers!T8
C8: =+'Historical Financials'!C10 | G8: =+'Historical Financials'!G10/Conversion_Rate | H8: =+'Historical Financials'!H10/Conversion_Rate | I8: =+'Historical Financials'!I10/Conversion_Rate | J8: =+'Historical Financials'!J10/Conversion_Rate | K8: =+Drivers!K13 | L8: =+Drivers!L13 | M8: =+Drivers!M13 | N8: =+Drivers!N13 | O8: =+Drivers!O13 | P8: =+Drivers!P13 | Q8: =+Drivers!Q13 | R8: =+Drivers!R13 | ... T8: =+Drivers!T13
C9: Revenue | G9: =SUM(G7:G8) | H9: =SUM(H7:H8) | I9: =SUM(I7:I8) | J9: =SUM(J7:J8) | K9: =SUM(K7:K8) | L9: =SUM(L7:L8) | M9: =SUM(M7:M8) | N9: =SUM(N7:N8) | ... T9: =SUM(T7:T8)
C10: Growth | G10: =G9/3500.921-1 | H10: =H9/G9-1 | I10: =I9/H9-1 | J10: =J9/I9-1 | K10: =K9/J9-1 | L10: =L9/K9-1 | M10: =M9/L9-1 | N10: =N9/M9-1 | O10: =O9/N9-1 | ... T10: =T9/S9-1
C12: ='Historical Financials'!C13 | G12: ='Historical Financials'!G13/Conversion_Rate | H12: ='Historical Financials'!H13/Conversion_Rate | I12: ='Historical Financials'!I13/Conversion_Rate | J12: ='Historical Financials'!J13/Conversion_Rate | K12: =+Drivers!K19 | L12: =+Drivers!L19 | M12: =+Drivers!M19 | N12: =+Drivers!N19 | O12: =+Drivers!O19 | P12: =+Drivers!P19 | Q12: =+Drivers!Q19 | R12: =+Drivers!R19 | ... T12: =+Drivers!T19
C13: ='Historical Financials'!C14 | G13: ='Historical Financials'!G14/Conversion_Rate | H13: ='Historical Financials'!H14/Conversion_Rate | I13: ='Historical Financials'!I14/Conversion_Rate | J13: ='Historical Financials'!J14/Conversion_Rate | K13: =+Drivers!K24 | L13: =+Drivers!L24 | M13: =+Drivers!M24 | N13: =+Drivers!N24 | O13: =+Drivers!O24 | P13: =+Drivers!P24 | Q13: =+Drivers!Q24 | R13: =+Drivers!R24 | ... T13: =+Drivers!T24
C14: Cost of Goods Sold | G14: =SUM(G12:G13) | H14: =SUM(H12:H13) | I14: =SUM(I12:I13) | J14: =SUM(J12:J13) | K14: =SUM(K12:K13) | L14: =SUM(L12:L13) | M14: =SUM(M12:M13) | N14: =SUM(N12:N13) | ... T14: =SUM(T12:T13)
C16: Gross Profit 1 | G16: =+G7-G12 | H16: =+H7-H12 | I16: =+I7-I12 | J16: =+J7-J12 | K16: =+K7-K12 | L16: =+L7-L12 | M16: =+M7-M12 | N16: =+N7-N12 | ... T16: =+T7-T12
C17: Gross Profit 2 | G17: =+G8-G13 | H17: =+H8-H13 | I17: =+I8-I13 | J17: =+J8-J13 | K17: =+K8-K13 | L17: =+L8-L13 | M17: =+M8-M13 | N17: =+N8-N13 | ... T17: =+T8-T13
C18: Gross Profit | G18: =G9-G14 | H18: =H9-H14 | I18: =I9-I14 | J18: =J9-J14 | K18: =K9-K14 | L18: =L9-L14 | M18: =M9-M14 | N18: =N9-N14 | ... T18: =T9-T14
C19: Gross Margin | G19: =G18/G$9 | H19: =H18/H$9 | I19: =I18/I$9 | J19: =J18/J$9 | K19: =K18/K$9 | L19: =L18/L$9 | M19: =M18/M$9 | N19: =N18/N$9 | ... T19: =T18/T$9
C21: ='Historical Financials'!C21 | G21: ='Historical Financials'!G21/Conversion_Rate | H21: ='Historical Financials'!H21/Conversion_Rate | I21: ='Historical Financials'!I21/Conversion_Rate | J21: ='Historical Financials'!J21/Conversion_Rate | K21: =+Drivers!K30 | L21: =+Drivers!L30 | M21: =+Drivers!M30 | N21: =+Drivers!N30 | O21: =+Drivers!O30 | P21: =+Drivers!P30 | Q21: =+Drivers!Q30 | R21: =+Drivers!R30 | ... T21: =+Drivers!T30
C22: ='Historical Financials'!C22 | G22: ='Historical Financials'!G22/Conversion_Rate | H22: ='Historical Financials'!H22/Conversion_Rate | I22: ='Historical Financials'!I22/Conversion_Rate | J22: ='Historical Financials'!J22/Conversion_Rate | K22: =+Drivers!K35 | L22: =+Drivers!L35 | M22: =+Drivers!M35 | N22: =+Drivers!N35 | O22: =+Drivers!O35 | P22: =+Drivers!P35 | Q22: =+Drivers!Q35 | R22: =+Drivers!R35 | ... T22: =+Drivers!T35
C23: ='Historical Financials'!C23 | G23: ='Historical Financials'!G23/Conversion_Rate | H23: ='Historical Financials'!H23/Conversion_Rate | I23: ='Historical Financials'!I23/Conversion_Rate | J23: ='Historical Financials'!J23/Conversion_Rate | K23: =+Drivers!K40 | L23: =+Drivers!L40 | M23: =+Drivers!M40 | N23: =+Drivers!N40 | O23: =+Drivers!O40 | P23: =+Drivers!P40 | Q23: =+Drivers!Q40 | R23: =+Drivers!R40 | ... T23: =+Drivers!T40
C24: Opex | G24: =SUM(G21:G23) | H24: =SUM(H21:H23) | I24: =SUM(I21:I23) | J24: =SUM(J21:J23) | K24: =SUM(K21:K23) | L24: =SUM(L21:L23) | M24: =SUM(M21:M23) | N24: =SUM(N21:N23) | ... T24: =SUM(T21:T23)
C25: % of Revenue | G25: =G24/G$9 | H25: =H24/H$9 | I25: =I24/I$9 | J25: =J24/J$9 | K25: =K24/K$9 | L25: =L24/L$9 | M25: =M24/M$9 | N25: =N24/N$9 | ... T25: =T24/T$9
C27: EBITDA | G27: =G18-G24 | H27: =H18-H24 | I27: =I18-I24 | J27: =J18-J24 | K27: =K18-K24 | L27: =L18-L24 | M27: =M18-M24 | N27: =N18-N24 | ... T27: =T18-T24
C28: EBITDA Margin | G28: =G27/G$9 | H28: =H27/H$9 | I28: =I27/I$9 | J28: =J27/J$9 | K28: =K27/K$9 | L28: =L27/L$9 | M28: =M27/M$9 | N28: =N27/N$9 | ... T28: =T27/T$9
C30: ='Historical Financials'!$C$30 | G30: ='Historical Financials'!G30/Conversion_Rate | H30: ='Historical Financials'!H30/Conversion_Rate | I30: ='Historical Financials'!I30/Conversion_Rate | J30: ='Historical Financials'!J30/Conversion_Rate | K30: =+Drivers!K46 | L30: =+Drivers!L46 | M30: =+Drivers!M46 | N30: =+Drivers!N46 | O30: =+Drivers!O46 | P30: =+Drivers!P46 | Q30: =+Drivers!Q46 | R30: =+Drivers!R46 | ... T30: =+Drivers!T46
C31: ='Historical Financials'!$C$31 | G31: ='Historical Financials'!G31/Conversion_Rate | H31: ='Historical Financials'!H31/Conversion_Rate | I31: ='Historical Financials'!I31/Conversion_Rate | J31: ='Historical Financials'!J31/Conversion_Rate | K31: =+Drivers!K51 | L31: =+Drivers!L51 | M31: =+Drivers!M51 | N31: =+Drivers!N51 | O31: =+Drivers!O51 | P31: =+Drivers!P51 | Q31: =+Drivers!Q51 | R31: =+Drivers!R51 | ... T31: =+Drivers!T51
C32: EBIT | G32: =+G27-SUM(G30:G31) | H32: =+H27-SUM(H30:H31) | I32: =+I27-SUM(I30:I31) | J32: =+J27-SUM(J30:J31) | K32: =+K27-SUM(K30:K31) | L32: =+L27-SUM(L30:L31) | M32: =+M27-SUM(M30:M31) | N32: =+N27-SUM(N30:N31) | ... T32: =+T27-SUM(T30:T31)
C34: ='Historical Financials'!$C$36 | G34: ='Historical Financials'!G36/Conversion_Rate | H34: ='Historical Financials'!H36/Conversion_Rate | I34: ='Historical Financials'!I36/Conversion_Rate | J34: ='Historical Financials'!J36/Conversion_Rate | K34: =SUM(Drivers!K57,Drivers!K62) | L34: =SUM(Drivers!L57,Drivers!L62) | M34: =SUM(Drivers!M57,Drivers!M62) | N34: =SUM(Drivers!N57,Drivers!N62) | O34: =SUM(Drivers!O57,Drivers!O62) | P34: =SUM(Drivers!P57,Drivers!P62) | Q34: =SUM(Drivers!Q57,Drivers!Q62) | R34: =SUM(Drivers!R57,Drivers!R62) | ... T34: =SUM(Drivers!T57,Drivers!T62)
C35: ='Historical Financials'!$C$41 | G35: ='Historical Financials'!G41/Conversion_Rate | H35: ='Historical Financials'!H41/Conversion_Rate | I35: ='Historical Financials'!I41/Conversion_Rate | J35: ='Historical Financials'!J41/Conversion_Rate | K35: =+Drivers!K67 | L35: =+Drivers!L67 | M35: =+Drivers!M67 | N35: =+Drivers!N67 | O35: =+Drivers!O67 | P35: =+Drivers!P67 | Q35: =+Drivers!Q67 | R35: =+Drivers!R67 | ... T35: =+Drivers!T67
C36: Earnings Before Taxes | G36: =+G32-SUM(G34:G35) | H36: =+H32-SUM(H34:H35) | I36: =+I32-SUM(I34:I35) | J36: =+J32-SUM(J34:J35) | K36: =+K32-SUM(K34:K35) | L36: =+L32-SUM(L34:L35) | M36: =+M32-SUM(M34:M35) | N36: =+N32-SUM(N34:N35) | ... T36: =+T32-SUM(T34:T35)
C38: ='Historical Financials'!$C$47 | G38: ='Historical Financials'!G47/Conversion_Rate | H38: ='Historical Financials'!H47/Conversion_Rate | I38: ='Historical Financials'!I47/Conversion_Rate | J38: ='Historical Financials'!J47/Conversion_Rate | K38: =+Drivers!K72 | L38: =+Drivers!L72 | M38: =+Drivers!M72 | N38: =+Drivers!N72 | O38: =+Drivers!O72 | P38: =+Drivers!P72 | Q38: =+Drivers!Q72 | R38: =+Drivers!R72 | ... T38: =+Drivers!T72
C39: Tax Rate | G39: =+G38/G36 | H39: =+H38/H36 | I39: =+I38/I36 | J39: =+J38/J36 | K39: =+K38/K36 | L39: =+L38/L36 | M39: =+M38/M36 | N39: =+N38/N36 | ... T39: =+T38/T36
C41: Net Income | G41: =G36-G38 | H41: =H36-H38 | I41: =I36-I38 | J41: =J36-J38 | K41: =K36-K38 | L41: =L36-L38 | M41: =M36-M38 | N41: =N36-N38 | ... T41: =T36-T38
C42: Profit Margin | G42: =G41/G$9 | H42: =H41/H$9 | I42: =I41/I$9 | J42: =J41/J$9 | K42: =K41/K$9 | L42: =L41/L$9 | M42: =M41/M$9 | N42: =N41/N$9 | ... T42: =T41/T$9
C46: =Assumptions!G$5
A47: X | C47: Balance Sheet | J47: FY26A / LTM
C48: =Assumptions!$G$9 | G48: ='Historical Financials'!G5 | H48: ='Historical Financials'!H5 | I48: ='Historical Financials'!I5 | J48: ='Historical Financials'!J5 | K48: ="FY"&K$1&"E" | L48: ="FY"&L$1&"E" | M48: ="FY"&M$1&"E" | N48: ="FY"&N$1&"E" | O48: ="FY"&O$1&"E" | P48: ="FY"&P$1&"E" | Q48: ="FY"&Q$1&"E" | R48: ="FY"&R$1&"E" | ... T48: ="FY"&T$1&"E"
C50: ='Historical Financials'!$C$59 | G50: =+G136 | H50: =+H136 | I50: =+I136 | J50: =+J136 | K50: =+K136 | L50: =+L136 | M50: =+M136 | N50: =+N136 | ... T50: =+T136
C51: ='Historical Financials'!$C$60 | G51: ='Historical Financials'!G60/Conversion_Rate | H51: ='Historical Financials'!H60/Conversion_Rate | I51: ='Historical Financials'!I60/Conversion_Rate | J51: ='Historical Financials'!J60/Conversion_Rate | K51: =+Drivers!K83 | L51: =+Drivers!L83 | M51: =+Drivers!M83 | N51: =+Drivers!N83 | O51: =+Drivers!O83 | P51: =+Drivers!P83 | Q51: =+Drivers!Q83 | R51: =+Drivers!R83 | ... T51: =+Drivers!T83
C52: ='Historical Financials'!$C$61 | G52: ='Historical Financials'!G61/Conversion_Rate | H52: ='Historical Financials'!H61/Conversion_Rate | I52: ='Historical Financials'!I61/Conversion_Rate | J52: ='Historical Financials'!J61/Conversion_Rate | K52: =+Drivers!K88 | L52: =+Drivers!L88 | M52: =+Drivers!M88 | N52: =+Drivers!N88 | O52: =+Drivers!O88 | P52: =+Drivers!P88 | Q52: =+Drivers!Q88 | R52: =+Drivers!R88 | ... T52: =+Drivers!T88
C53: ='Historical Financials'!$C$62 | G53: ='Historical Financials'!G62/Conversion_Rate | H53: ='Historical Financials'!H62/Conversion_Rate | I53: ='Historical Financials'!I62/Conversion_Rate | J53: ='Historical Financials'!J62/Conversion_Rate | K53: =Drivers!K93 | L53: =Drivers!L93 | M53: =Drivers!M93 | N53: =Drivers!N93 | O53: =Drivers!O93 | P53: =Drivers!P93 | Q53: =Drivers!Q93 | R53: =Drivers!R93 | ... T53: =Drivers!T93
C54: ='Historical Financials'!$C$63 | G54: ='Historical Financials'!G63/Conversion_Rate | H54: ='Historical Financials'!H63/Conversion_Rate | I54: ='Historical Financials'!I63/Conversion_Rate | J54: ='Historical Financials'!J63/Conversion_Rate | K54: =+Drivers!K98 | L54: =+Drivers!L98 | M54: =+Drivers!M98 | N54: =+Drivers!N98 | O54: =+Drivers!O98 | P54: =+Drivers!P98 | Q54: =+Drivers!Q98 | R54: =+Drivers!R98 | ... T54: =+Drivers!T98
C55: Total Current Assets | G55: =SUM(G50:G54) | H55: =SUM(H50:H54) | I55: =SUM(I50:I54) | J55: =SUM(J50:J54) | K55: =SUM(K50:K54) | L55: =SUM(L50:L54) | M55: =SUM(M50:M54) | N55: =SUM(N50:N54) | ... T55: =SUM(T50:T54)
C57: ='Historical Financials'!C66 | G57: ='Historical Financials'!G66/Conversion_Rate | H57: ='Historical Financials'!H66/Conversion_Rate | I57: ='Historical Financials'!I66/Conversion_Rate | J57: ='Historical Financials'!J66/Conversion_Rate | K57: =+J57-K118 | L57: =+K57-L118 | M57: =+L57-M118 | N57: =+M57-N118 | O57: =+N57-O118 | P57: =+O57-P118 | Q57: =+P57-Q118 | R57: =+Q57-R118 | ... T57: =+S57-T118
C58: ='Historical Financials'!C67 | G58: ='Historical Financials'!G67/Conversion_Rate | H58: ='Historical Financials'!H67/Conversion_Rate | I58: ='Historical Financials'!I67/Conversion_Rate | J58: ='Historical Financials'!J67/Conversion_Rate | K58: =+J58-K30 | L58: =+K58-L30 | M58: =+L58-M30 | N58: =+M58-N30 | O58: =+N58-O30 | P58: =+O58-P30 | Q58: =+P58-Q30 | R58: =+Q58-R30 | ... T58: =+S58-T30
C59: ='Historical Financials'!C68 | G59: =SUM(G57:G58) | H59: =SUM(H57:H58) | I59: =SUM(I57:I58) | J59: =SUM(J57:J58) | K59: =SUM(K57:K58) | L59: =SUM(L57:L58) | M59: =SUM(M57:M58) | N59: =SUM(N57:N58) | ... T59: =SUM(T57:T58)
C61: ='Historical Financials'!C71 | G61: ='Historical Financials'!G71/Conversion_Rate | H61: ='Historical Financials'!H71/Conversion_Rate | I61: ='Historical Financials'!I71/Conversion_Rate | J61: ='Historical Financials'!J71/Conversion_Rate | K61: =+J61-K119 | L61: =+K61-L119 | M61: =+L61-M119 | N61: =+M61-N119 | O61: =+N61-O119 | P61: =+O61-P119 | Q61: =+P61-Q119 | R61: =+Q61-R119 | ... T61: =+S61-T119
C62: ='Historical Financials'!C72 | G62: ='Historical Financials'!G72/Conversion_Rate | H62: ='Historical Financials'!H72/Conversion_Rate | I62: ='Historical Financials'!I72/Conversion_Rate | J62: ='Historical Financials'!J72/Conversion_Rate | K62: =+J62-K31 | L62: =+K62-L31 | M62: =+L62-M31 | N62: =+M62-N31 | O62: =+N62-O31 | P62: =+O62-P31 | Q62: =+P62-Q31 | R62: =+Q62-R31 | ... T62: =+S62-T31
C63: ='Historical Financials'!C73 | G63: =SUM(G61:G62) | H63: =SUM(H61:H62) | I63: =SUM(I61:I62) | J63: =SUM(J61:J62) | K63: =SUM(K61:K62) | L63: =SUM(L61:L62) | M63: =SUM(M61:M62) | N63: =SUM(N61:N62) | ... T63: =SUM(T61:T62)
C65: ='Historical Financials'!$C$76 | G65: ='Historical Financials'!G76/Conversion_Rate | H65: ='Historical Financials'!H76/Conversion_Rate | I65: ='Historical Financials'!I76/Conversion_Rate | J65: ='Historical Financials'!J76/Conversion_Rate | K65: =+Drivers!K103 | L65: =+Drivers!L103 | M65: =+Drivers!M103 | N65: =+Drivers!N103 | O65: =+Drivers!O103 | P65: =+Drivers!P103 | Q65: =+Drivers!Q103 | R65: =+Drivers!R103 | ... T65: =+Drivers!T103
C67: Total Assets | G67: =SUM(G65,G59,G55,G63) | H67: =SUM(H65,H59,H55,H63) | I67: =SUM(I65,I59,I55,I63) | J67: =SUM(J65,J59,J55,J63) | K67: =SUM(K65,K59,K55,K63) | L67: =SUM(L65,L59,L55,L63) | M67: =SUM(M65,M59,M55,M63) | N67: =SUM(N65,N59,N55,N63) | ... T67: =SUM(T65,T59,T55,T63)
C69: ='Historical Financials'!$C$82 | G69: ='Historical Financials'!G82/Conversion_Rate | H69: ='Historical Financials'!H82/Conversion_Rate | I69: ='Historical Financials'!I82/Conversion_Rate | J69: ='Historical Financials'!J82/Conversion_Rate | K69: =+Drivers!K109 | L69: =+Drivers!L109 | M69: =+Drivers!M109 | N69: =+Drivers!N109 | O69: =+Drivers!O109 | P69: =+Drivers!P109 | Q69: =+Drivers!Q109 | R69: =+Drivers!R109 | ... T69: =+Drivers!T109
C70: ='Historical Financials'!$C$83 | G70: ='Historical Financials'!G83/Conversion_Rate | H70: ='Historical Financials'!H83/Conversion_Rate | I70: ='Historical Financials'!I83/Conversion_Rate | J70: ='Historical Financials'!J83/Conversion_Rate | K70: =+Drivers!K114 | L70: =+Drivers!L114 | M70: =+Drivers!M114 | N70: =+Drivers!N114 | O70: =+Drivers!O114 | P70: =+Drivers!P114 | Q70: =+Drivers!Q114 | R70: =+Drivers!R114 | ... T70: =+Drivers!T114
C71: ='Historical Financials'!$C$84 | G71: ='Historical Financials'!G84/Conversion_Rate | H71: ='Historical Financials'!H84/Conversion_Rate | I71: ='Historical Financials'!I84/Conversion_Rate | J71: ='Historical Financials'!J84/Conversion_Rate | K71: =+Drivers!K119 | L71: =+Drivers!L119 | M71: =+Drivers!M119 | N71: =+Drivers!N119 | O71: =+Drivers!O119 | P71: =+Drivers!P119 | Q71: =+Drivers!Q119 | R71: =+Drivers!R119 | ... T71: =+Drivers!T119
C72: ='Historical Financials'!$C$85 | G72: ='Historical Financials'!G85/Conversion_Rate | H72: ='Historical Financials'!H85/Conversion_Rate | I72: ='Historical Financials'!I85/Conversion_Rate | J72: ='Historical Financials'!J85/Conversion_Rate | K72: =+Drivers!K124 | L72: =+Drivers!L124 | M72: =+Drivers!M124 | N72: =+Drivers!N124 | O72: =+Drivers!O124 | P72: =+Drivers!P124 | Q72: =+Drivers!Q124 | R72: =+Drivers!R124 | ... T72: =+Drivers!T124
C73: Total Current Liabilities | G73: =SUM(G69:G72) | H73: =SUM(H69:H72) | I73: =SUM(I69:I72) | J73: =SUM(J69:J72) | K73: =SUM(K69:K72) | L73: =SUM(L69:L72) | M73: =SUM(M69:M72) | N73: =SUM(N69:N72) | ... T73: =SUM(T69:T72)
C75: ='Historical Financials'!$C$88 | G75: ='Historical Financials'!G88/Conversion_Rate | H75: ='Historical Financials'!H88/Conversion_Rate | I75: ='Historical Financials'!I88/Conversion_Rate | J75: ='Historical Financials'!J88/Conversion_Rate | K75: =+Drivers!K135 | L75: =+Drivers!L135 | M75: =+Drivers!M135 | N75: =+Drivers!N135 | O75: =+Drivers!O135 | P75: =+Drivers!P135 | Q75: =+Drivers!Q135 | R75: =+Drivers!R135 | ... T75: =+Drivers!T135
C76: ='Historical Financials'!$C$89 | G76: ='Historical Financials'!G89/Conversion_Rate | H76: ='Historical Financials'!H89/Conversion_Rate | I76: ='Historical Financials'!I89/Conversion_Rate | J76: ='Historical Financials'!J89/Conversion_Rate | K76: =+Drivers!K140 | L76: =+Drivers!L140 | M76: =+Drivers!M140 | N76: =+Drivers!N140 | O76: =+Drivers!O140 | P76: =+Drivers!P140 | Q76: =+Drivers!Q140 | R76: =+Drivers!R140 | ... T76: =+Drivers!T140
C77: ='Historical Financials'!$C$90 | G77: ='Historical Financials'!G90/Conversion_Rate | H77: ='Historical Financials'!H90/Conversion_Rate | I77: ='Historical Financials'!I90/Conversion_Rate | J77: ='Historical Financials'!J90/Conversion_Rate | K77: =+Drivers!K129 | L77: =+Drivers!L129 | M77: =+Drivers!M129 | N77: =+Drivers!N129 | O77: =+Drivers!O129 | P77: =+Drivers!P129 | Q77: =+Drivers!Q129 | R77: =+Drivers!R129 | ... T77: =+Drivers!T129
C79: Total Liabilities | G79: =SUM(G73:G78) | H79: =SUM(H73:H78) | I79: =SUM(I73:I78) | J79: =SUM(J73:J78) | K79: =SUM(K73:K78) | L79: =SUM(L73:L78) | M79: =SUM(M73:M78) | N79: =SUM(N73:N78) | ... T79: =SUM(T73:T78)
C81: ='Historical Financials'!$C$95 | G81: ='Historical Financials'!G95/Conversion_Rate | H81: ='Historical Financials'!H95/Conversion_Rate | I81: ='Historical Financials'!I95/Conversion_Rate | J81: ='Historical Financials'!J95/Conversion_Rate | K81: =+J81+K41+K126 | L81: =+K81+L41+L126 | M81: =+L81+M41+M126 | N81: =+M81+N41+N126 | O81: =+N81+O41+O126 | P81: =+O81+P41+P126 | Q81: =+P81+Q41+Q126 | R81: =+Q81+R41+R126 | ... T81: =+S81+T41+T126
C82: ='Historical Financials'!$C$96 | G82: ='Historical Financials'!G96/Conversion_Rate | H82: ='Historical Financials'!H96/Conversion_Rate | I82: ='Historical Financials'!I96/Conversion_Rate | J82: ='Historical Financials'!J96/Conversion_Rate | K82: =+J82+K125+K101+K102 | L82: =+K82+L125+L101+L102 | M82: =+L82+M125+M101+M102 | N82: =+M82+N125+N101+N102 | O82: =+N82+O125+O101+O102 | P82: =+O82+P125+P101+P102 | Q82: =+P82+Q125+Q101+Q102 | R82: =+Q82+R125+R101+R102 | ... T82: =+S82+T125+T101+T102
C83: ='Historical Financials'!$C$97 | G83: ='Historical Financials'!G97/Conversion_Rate | H83: ='Historical Financials'!H97/Conversion_Rate | I83: ='Historical Financials'!I97/Conversion_Rate | J83: ='Historical Financials'!J97/Conversion_Rate | K83: =+Drivers!K148 | L83: =+Drivers!L148 | M83: =+Drivers!M148 | N83: =+Drivers!N148 | O83: =+Drivers!O148 | P83: =+Drivers!P148 | Q83: =+Drivers!Q148 | R83: =+Drivers!R148 | ... T83: =+Drivers!T148
C84: Shareholder's Equity | G84: =SUM(G81:G83) | H84: =SUM(H81:H83) | I84: =SUM(I81:I83) | J84: =SUM(J81:J83) | K84: =SUM(K81:K83) | L84: =SUM(L81:L83) | M84: =SUM(M81:M83) | N84: =SUM(N81:N83) | ... T84: =SUM(T81:T83)
C86: Liabilities & Shareholder's Equity | G86: =SUM(G84,G79) | H86: =SUM(H84,H79) | I86: =SUM(I84,I79) | J86: =SUM(J84,J79) | K86: =SUM(K84,K79) | L86: =SUM(L84,L79) | M86: =SUM(M84,M79) | N86: =SUM(N84,N79) | ... T86: =SUM(T84,T79)
C88: Note: You can always hardcode / plug historical data, but not projected data. | M88: =M90-L90 | N88: =N90-M90 | O88: =O90-N90 | P88: =P90-O90 | Q88: =Q90-P90 | R88: =R90-Q90 | S88: =S90-R90 | T88: =T90-S90
C89: Check | G89: =+G67-G86 | H89: =+H67-H86 | I89: =+I67-I86 | J89: =0-(+J67-J86) | K89: =0-(+K67-K86) | L89: =0-(+L67-L86) | M89: =0-(+M67-M86) | N89: =0-(+N67-N86) | O89: =0-(+O67-O86) | P89: =0-(+P67-P86) | Q89: =0-(+Q67-Q86) | ... T89: =0-(+T67-T86)
L90: =L89-K89 | M90: =M89-L89 | N90: =N89-M89 | O90: =O89-N89 | P90: =P89-O89 | Q90: =Q89-P89 | R90: =R89-Q89 | S90: =S89-R89 | T90: =T89-S89
C92: =Assumptions!G$5
A93: X | C93: Cash Flow Statement | J93: FY26A / LTM
C94: =Assumptions!$G$9 | G94: ='Historical Financials'!G5 | H94: ='Historical Financials'!H5 | I94: ='Historical Financials'!I5 | J94: ='Historical Financials'!J5 | K94: ="FY"&K$1&"E" | L94: ="FY"&L$1&"E" | M94: ="FY"&M$1&"E" | N94: ="FY"&N$1&"E" | O94: ="FY"&O$1&"E" | P94: ="FY"&P$1&"E" | Q94: ="FY"&Q$1&"E" | R94: ="FY"&R$1&"E" | ... T94: ="FY"&T$1&"E"
C96: Net Income | G96: =+G41 | H96: =+H41 | I96: =+I41 | J96: =+J41 | K96: =+K41 | L96: =+L41 | M96: =+M41 | N96: =+N41 | ... T96: =+T41
C98: Non-Cash Expenses
C99: =+C30 | G99: =+G30 | H99: =+H30 | I99: =+I30 | J99: =+J30 | K99: =+K30 | L99: =+L30 | M99: =+M30 | N99: =+N30 | ... T99: =+T30
C100: =+C31 | G100: =+G31 | H100: =+H31 | I100: =+I31 | J100: =+J31 | K100: =+K31 | L100: =+L31 | M100: =+M31 | N100: =+N31 | ... T100: =+T31
C101: ='Historical Financials'!$C$106 | G101: ='Historical Financials'!G106/Conversion_Rate | H101: ='Historical Financials'!H106/Conversion_Rate | I101: ='Historical Financials'!I106/Conversion_Rate | J101: ='Historical Financials'!J106/Conversion_Rate | K101: =+Drivers!K159 | L101: =+Drivers!L159 | M101: =+Drivers!M159 | N101: =+Drivers!N159 | O101: =+Drivers!O159 | P101: =+Drivers!P159 | Q101: =+Drivers!Q159 | R101: =+Drivers!R159 | ... T101: =+Drivers!T159
C102: Other Non-Cash (credit losses, equity-method, PP&E gains, deferred taxes) | G102: =1.946+5.347-1.846+9.946 | H102: =3.914-4.058+2.241-2.386-0.847 | I102: =0.354-0.149-13.726-13.44 | J102: =5.599+0.326+1.13+47.359 | K102: 0 | L102: 0 | M102: 0 | N102: 0 | O102: 0 | P102: 0 | Q102: 0 | R102: 0 | S102: 0 | T102: 0
C104: ∆ Net Working Capital
C105: ="∆ "&C51 | G105: =578.573-702.038 | H105: =+G51-H51 | I105: =+H51-I51 | J105: =+I51-J51 | K105: =+J51-K51 | L105: =+K51-L51 | M105: =+L51-M51 | N105: =+M51-N51 | O105: =+N51-O51 | ... T105: =+S51-T51
C106: ="∆ "&C52 | G106: =18.731-26.31 | H106: =+G52-H52 | I106: =+H52-I52 | J106: =+I52-J52 | K106: =+J52-K52 | L106: =+K52-L52 | M106: =+L52-M52 | N106: =+M52-N52 | O106: =+N52-O52 | ... T106: =+S52-T52
C107: ="∆ "&C53 | G107: =58.791-39.973 | H107: =+G53-H53 | I107: =+H53-I53 | J107: =+I53-J53 | K107: =+J53-K53 | L107: =+K53-L53 | M107: =+L53-M53 | N107: =+M53-N53 | O107: =+N53-O53 | ... T107: =+S53-T53
C108: ="∆ "&C54 | G108: =(112.242+49.882)-G54 | H108: =+G54-H54 | I108: =+H54-I54 | J108: =+I54-J54 | K108: =+J54-K54 | L108: =+K54-L54 | M108: =+L54-M54 | N108: =+M54-N54 | O108: =+N54-O54 | ... T108: =+S54-T54
C110: ="∆ "&C69 | G110: =440.81-399.034 | H110: =+H69-G69 | I110: =+I69-H69 | J110: =+J69-I69 | K110: =+K69-J69 | L110: =+L69-K69 | M110: =+M69-L69 | N110: =+N69-M69 | O110: =+O69-N69 | ... T110: =+T69-S69
C111: ="∆ "&C70 | G111: 0 | H111: =+H70-G70 | I111: =+I70-H70 | J111: =+J70-I70 | K111: =+K70-J70 | L111: =+L70-K70 | M111: =+M70-L70 | N111: =+N70-M70 | O111: =+O70-N70 | ... T111: =+T70-S70
C112: ="∆ "&C71 | G112: =26.117-20.061 | H112: =+H71-G71 | I112: =+I71-H71 | J112: =+J71-I71 | K112: =+K71-J71 | L112: =+L71-K71 | M112: =+M71-L71 | N112: =+N71-M71 | O112: =+O71-N71 | ... T112: =+T71-S71
C113: ="∆ "&C72 | G113: =G72-(0+21.794) | H113: =+H72-G72 | I113: =+I72-H72 | J113: =+J72-I72 | K113: =+K72-J72 | L113: =+L72-K72 | M113: =+M72-L72 | N113: =+N72-M72 | O113: =+O72-N72 | ... T113: =+T72-S72
C114: Change in NWC | G114: =SUM(G105:G113) | H114: =SUM(H105:H113) | I114: =SUM(I105:I113) | J114: =SUM(J105:J113) | K114: =SUM(K105:K113) | L114: =SUM(L105:L113) | M114: =SUM(M105:M113) | N114: =SUM(N105:N113) | ... T114: =SUM(T105:T113)
C116: Cash Flow from Operations | G116: =SUM(G114,G99:G102,G96) | H116: =SUM(H114,H99:H102,H96) | I116: =SUM(I114,I99:I102,I96) | J116: =SUM(J114,J99:J102,J96) | K116: =SUM(K114,K99:K102,K96) | L116: =SUM(L114,L99:L102,L96) | M116: =SUM(M114,M99:M102,M96) | N116: =SUM(N114,N99:N102,N96) | ... T116: =SUM(T114,T99:T102,T96)
C118: ='Historical Financials'!C112 | G118: ='Historical Financials'!G112/Conversion_Rate | H118: ='Historical Financials'!H112/Conversion_Rate | I118: ='Historical Financials'!I112/Conversion_Rate | J118: ='Historical Financials'!J112/Conversion_Rate | K118: =+Drivers!K166 | L118: =+Drivers!L166 | M118: =+Drivers!M166 | N118: =+Drivers!N166 | O118: =+Drivers!O166 | P118: =+Drivers!P166 | Q118: =+Drivers!Q166 | R118: =+Drivers!R166 | ... T118: =+Drivers!T166
C119: ='Historical Financials'!$C$118 | G119: ='Historical Financials'!G118/Conversion_Rate | H119: ='Historical Financials'!H118/Conversion_Rate | I119: ='Historical Financials'!I118/Conversion_Rate | J119: ='Historical Financials'!J118/Conversion_Rate | K119: =+Drivers!K171 | L119: =+Drivers!L171 | M119: =+Drivers!M171 | N119: =+Drivers!N171 | O119: =+Drivers!O171 | P119: =+Drivers!P171 | Q119: =+Drivers!Q171 | R119: =+Drivers!R171 | ... T119: =+Drivers!T171
C120: =C65 | G120: =(116.303+47.708)-G65 | H120: =+G65-H65 | I120: =+H65-I65 | J120: =+I65-J65 | K120: =+J65-K65 | L120: =+K65-L65 | M120: =+L65-M65 | N120: =+M65-N65 | O120: =+N65-O65 | ... T120: =+S65-T65
C121: Cash Flow from Investing | G121: =SUM(G118:G120) | H121: =SUM(H118:H120) | I121: =SUM(I118:I120) | J121: =SUM(J118:J120) | K121: =SUM(K118:K120) | L121: =SUM(L118:L120) | M121: =SUM(M118:M120) | N121: =SUM(N118:N120) | ... T121: =SUM(T118:T120)
C123: Cash Flow Available to Service Debt | G123: =SUM(G121,G116) | H123: =SUM(H121,H116) | I123: =SUM(I121,I116) | J123: =SUM(J121,J116) | K123: =SUM(K121,K116) | L123: =SUM(L121,L116) | M123: =SUM(M121,M116) | N123: =SUM(N121,N116) | ... T123: =SUM(T121,T116)
C125: ='Historical Financials'!C120 | G125: ='Historical Financials'!G120/Conversion_Rate | H125: ='Historical Financials'!H120/Conversion_Rate | I125: ='Historical Financials'!I120/Conversion_Rate | J125: ='Historical Financials'!J120/Conversion_Rate | K125: =+Drivers!K175 | L125: =+Drivers!L175 | M125: =+Drivers!M175 | N125: =+Drivers!N175 | O125: =+Drivers!O175 | P125: =+Drivers!P175 | Q125: =+Drivers!Q175 | R125: =+Drivers!R175 | ... T125: =+Drivers!T175
C126: ='Historical Financials'!C122 | G126: ='Historical Financials'!G122/Conversion_Rate | H126: ='Historical Financials'!H122/Conversion_Rate | I126: ='Historical Financials'!I122/Conversion_Rate | J126: ='Historical Financials'!J122/Conversion_Rate | K126: =+Drivers!K180 | L126: =+Drivers!L180 | M126: =+Drivers!M180 | N126: =+Drivers!N180 | O126: =+Drivers!O180 | P126: =+Drivers!P180 | Q126: =+Drivers!Q180 | R126: =+Drivers!R180 | ... T126: =+Drivers!T180
C127: ="∆ "&C83 | G127: =G83-(-169.365) | H127: =H83-G83 | I127: =I83-H83 | J127: =J83-I83 | K127: =K83-J83 | L127: =L83-K83 | M127: =M83-L83 | N127: =N83-M83 | O127: =O83-N83 | ... T127: =T83-S83
C128: ="∆ "&C75 | G128: =10.903-1.996 | H128: =+H75-G75 | I128: =+I75-H75 | J128: =+J75-I75 | K128: =+K75-J75 | L128: =+L75-K75 | M128: =+M75-L75 | N128: =+N75-M75 | O128: =+O75-N75 | ... T128: =+T75-S75
C129: ="∆ "&C76 | G129: 0 | H129: =+H76-G76 | I129: =+I76-H76 | J129: =+J76-I76 | K129: =+K76-J76 | L129: =+L76-K76 | M129: =+M76-L76 | N129: =+N76-M76 | O129: =+O76-N76 | ... T129: =+T76-S76
C130: ="∆ "&C77 | G130: =G77-(80.06+64.637+95.683) | H130: =+H77-G77 | I130: =+I77-H77 | J130: =+J77-I77 | K130: =+K77-J77 | L130: =+L77-K77 | M130: =+M77-L77 | N130: =+N77-M77 | O130: =+O77-N77 | ... T130: =+T77-S77
C131: Historical reconciling items (FX, option/ESPP proceeds, non-cash PP&E & intangible movements) - historical only | G131: ='Historical Financials'!G59/Conversion_Rate-G135-SUM(G116,G121,G125:G130) | H131: ='Historical Financials'!H59/Conversion_Rate-H135-SUM(H116,H121,H125:H130) | I131: ='Historical Financials'!I59/Conversion_Rate-I135-SUM(I116,I121,I125:I130) | J131: ='Historical Financials'!J59/Conversion_Rate-J135-SUM(J116,J121,J125:J130)
C132: Cash Flow from Financing Activities | G132: =SUM(G125:G131) | H132: =SUM(H125:H131) | I132: =SUM(I125:I131) | J132: =SUM(J125:J131) | K132: =SUM(K125:K131) | L132: =SUM(L125:L131) | M132: =SUM(M125:M131) | N132: =SUM(N125:N131) | ... T132: =SUM(T125:T131)
C134: Change in Cash | G134: =SUM(G132,G121,G116) | H134: =SUM(H132,H121,H116) | I134: =SUM(I132,I121,I116) | J134: =SUM(J132,J121,J116) | K134: =SUM(K132,K121,K116) | L134: =SUM(L132,L121,L116) | M134: =SUM(M132,M121,M116) | N134: =SUM(N132,N121,N116) | ... T134: =SUM(T132,T121,T116)
...

Sheet Drivers
V3: Notes
C4: =Assumptions!G5
A5: X | C5: Income Statement Drivers | J5: FY26A / LTM
C6: =Assumptions!$G$9 | G6: ='Historical Financials'!G5 | H6: ='Historical Financials'!H5 | I6: ='Historical Financials'!I5 | J6: ='Historical Financials'!J5 | K6: ="FY"&'Financial Model'!K$1&"E" | L6: ="FY"&'Financial Model'!L$1&"E" | M6: ="FY"&'Financial Model'!M$1&"E" | N6: ="FY"&'Financial Model'!N$1&"E" | O6: ="FY"&'Financial Model'!O$1&"E" | P6: ="FY"&'Financial Model'!P$1&"E" | Q6: ="FY"&'Financial Model'!Q$1&"E" | R6: ="FY"&'Financial Model'!R$1&"E" | ... T6: ="FY"&'Financial Model'!T$1&"E"
C8: =+'Financial Model'!C7 | G8: =+'Financial Model'!G7 | H8: =+'Financial Model'!H7 | I8: =+'Financial Model'!I7 | J8: =+'Financial Model'!J7 | K8: =+K10*K11 | L8: =+L10*L11 | M8: =+M10*M11 | N8: =+N10*N11 | O8: =+O10*O11 | P8: =+P10*P11 | Q8: =+Q10*Q11 | R8: =+R10*R11 | ... T8: =+T10*T11
C10: Units sold (millions) - indexed to memo 4.0M FY26 anchor | G10: =H10/(1+H192) | H10: =I10/(1+I192) | I10: =J10/(1+J192) | J10: =Support!$D$68 | K10: =J10*(1+K192) | L10: =K10*(1+L192) | M10: =L10*(1+M192) | N10: =M10*(1+N192) | O10: =N10*(1+O192) | P10: =O10*(1+P192) | Q10: =P10*(1+Q192) | R10: =Q10*(1+R192) | ... T10: =S10*(1+T192) | V10: Units = prior x (1+total unit growth, row 192). Levels are an index anchored on the memo 4.0M FY26 base; only growth rates are company-disclosed.
C11: Service revenue per unit ($) | G11: =G8/G10 | H11: =H8/H10 | I11: =I8/I10 | J11: =J8/J10 | K11: =J11*(1+K203) | L11: =K11*(1+L203) | M11: =L11*(1+M203) | N11: =M11*(1+N203) | O11: =N11*(1+O203) | P11: =O11*(1+P203) | Q11: =P11*(1+Q203) | R11: =Q11*(1+R203) | ... T11: =S11*(1+T203) | V11: Service revenue per unit = prior x (1+RPU growth, row 203).
C13: =+'Financial Model'!C8 | G13: =+'Financial Model'!G8 | H13: =+'Financial Model'!H8 | I13: =+'Financial Model'!I8 | J13: =+'Financial Model'!J8 | K13: =+K15*K16 | L13: =+L15*L16 | M13: =+M15*M16 | N13: =+N15*N16 | O13: =+O15*O16 | P13: =+P15*P16 | Q13: =+Q15*Q16 | R13: =+R15*R16 | ... T13: =+T15*T16
C15: Prior-year vehicle sales ($) | G15: 647.881 | H15: =G13 | I15: =H13 | J15: =I13 | K15: =J13 | L15: =K13 | M15: =L13 | N15: =M13 | O15: =N13 | ... T15: =S13
C16: Growth factor (units x price, same as service revenue) | G16: =G13/G15 | H16: =H13/H15 | I16: =I13/I15 | J16: =J13/J15 | K16: =(1+K192)*(1+K203) | L16: =(1+L192)*(1+L203) | M16: =(1+M192)*(1+M203) | N16: =(1+N192)*(1+N203) | O16: =(1+O192)*(1+O203) | P16: =(1+P192)*(1+P203) | Q16: =(1+Q192)*(1+Q203) | R16: =(1+R192)*(1+R203) | ... T16: =(1+T192)*(1+T203)
C19: =+'Financial Model'!C12 | G19: =+'Financial Model'!G12 | H19: =+'Financial Model'!H12 | I19: =+'Financial Model'!I12 | J19: =+'Financial Model'!J12 | K19: =+K21*K22 | L19: =+L21*L22 | M19: =+M21*M22 | N19: =+N21*N22 | O19: =+O21*O22 | P19: =+P21*P22 | Q19: =+Q21*Q22 | R19: =+R21*R22 | ... T19: =+T21*T22
C21: =+C8 | G21: =+G8 | H21: =+H8 | I21: =+I8 | J21: =+J8 | K21: =+K8 | L21: =+L8 | M21: =+M8 | N21: =+N8 | ... T21: =+T8
C22: % of Revenue 1 | G22: =+G19/G21 | H22: =+H19/H21 | I22: =+I19/I21 | J22: =+J19/J21 | K22: =('Financial Model'!K9*(1-K204)-'Financial Model'!K13-'Financial Model'!K24-SUM('Financial Model'!K30:K31)-K206)/K21 | L22: =('Financial Model'!L9*(1-L204)-'Financial Model'!L13-'Financial Model'!L24-SUM('Financial Model'!L30:L31)-L206)/L21 | M22: =('Financial Model'!M9*(1-M204)-'Financial Model'!M13-'Financial Model'!M24-SUM('Financial Model'!M30:M31)-M206)/M21 | N22: =('Financial Model'!N9*(1-N204)-'Financial Model'!N13-'Financial Model'!N24-SUM('Financial Model'!N30:N31)-N206)/N21 | O22: =('Financial Model'!O9*(1-O204)-'Financial Model'!O13-'Financial Model'!O24-SUM('Financial Model'!O30:O31)-O206)/O21 | P22: =('Financial Model'!P9*(1-P204)-'Financial Model'!P13-'Financial Model'!P24-SUM('Financial Model'!P30:P31)-P206)/P21 | Q22: =('Financial Model'!Q9*(1-Q204)-'Financial Model'!Q13-'Financial Model'!Q24-SUM('Financial Model'!Q30:Q31)-Q206)/Q21 | R22: =('Financial Model'!R9*(1-R204)-'Financial Model'!R13-'Financial Model'!R24-SUM('Financial Model'!R30:R31)-R206)/R21 | ... T22: =('Financial Model'!T9*(1-T204)-'Financial Model'!T13-'Financial Model'!T24-SUM('Financial Model'!T30:T31)-T206)/T21 | V22: This row carries the margin drop: 44.2% to 46.9% of service revenue in FY27E. It is the residual that delivers row 204. Base case: facility cost +$122M (+7.0%) on 3% fewer cars; per car, cost +10.3% vs revenue +4.0% (Q4 FY26 US: +14.2%).
C24: =+'Financial Model'!C13 | G24: =+'Financial Model'!G13 | H24: =+'Financial Model'!H13 | I24: =+'Financial Model'!I13 | J24: =+'Financial Model'!J13 | K24: =+K26*K27 | L24: =+L26*L27 | M24: =+M26*M27 | N24: =+N26*N27 | O24: =+O26*O27 | P24: =+P26*P27 | Q24: =+Q26*Q27 | R24: =+R26*R27 | ... T24: =+T26*T27
C26: =+C13 | G26: =+G13 | H26: =+H13 | I26: =+I13 | J26: =+J13 | K26: =+K13 | L26: =+L13 | M26: =+M13 | N26: =+N13 | ... T26: =+T13
C27: % of Revenue 2 | G27: =+G24/G26 | H27: =+H24/H26 | I27: =+I24/I26 | J27: =+J24/J26 | K27: =$J$27 | L27: =$J$27 | M27: =$J$27 | N27: =$J$27 | O27: =$J$27 | P27: =$J$27 | Q27: =$J$27 | R27: =$J$27 | ... T27: =$J$27 | V27: Held at FY26 (88.5% of vehicle sales): not a source of the margin drop.
C30: =+'Financial Model'!C21 | G30: =+'Financial Model'!G21 | H30: =+'Financial Model'!H21 | I30: =+'Financial Model'!I21 | J30: =+'Financial Model'!J21 | K30: =+K32*K33 | L30: =+L32*L33 | M30: =+M32*M33 | N30: =+N32*N33 | O30: =+O32*O33 | P30: =+P32*P33 | Q30: =+Q32*Q33 | R30: =+R32*R33 | ... T30: =+T32*T33
C32: Total Revenue | G32: =+'Financial Model'!G$9 | H32: =+'Financial Model'!H$9 | I32: =+'Financial Model'!I$9 | J32: =+'Financial Model'!J$9 | K32: =+'Financial Model'!K$9 | L32: =+'Financial Model'!L$9 | M32: =+'Financial Model'!M$9 | N32: =+'Financial Model'!N$9 | ... T32: =+'Financial Model'!T$9
C33: % of Total Revenue | G33: =+G30/G32 | H33: =+H30/H32 | I33: =+I30/I32 | J33: =+J30/J32 | K33: =$J$33 | L33: =$J$33 | M33: =$J$33 | N33: =$J$33 | O33: =$J$33 | P33: =$J$33 | Q33: =$J$33 | R33: =$J$33 | ... T33: =$J$33 | V33: Held at FY26 (8.6% of revenue): not a source of the FY27E drop. G&A took 263bp of margin FY23A-FY26A (6.0% to 8.6%).
C35: =+'Financial Model'!C22 | G35: =+'Financial Model'!G22 | H35: =+'Financial Model'!H22 | I35: =+'Financial Model'!I22 | J35: =+'Financial Model'!J22 | K35: =+K37*K38 | L35: =+L37*L38 | M35: =+M37*M38 | N35: =+N37*N38 | O35: =+O37*O38 | P35: =+P37*P38 | Q35: =+Q37*Q38 | R35: =+R37*R38 | ... T35: =+T37*T38
C37: Total Revenue | G37: =+'Financial Model'!G$9 | H37: =+'Financial Model'!H$9 | I37: =+'Financial Model'!I$9 | J37: =+'Financial Model'!J$9 | K37: =+'Financial Model'!K$9 | L37: =+'Financial Model'!L$9 | M37: =+'Financial Model'!M$9 | N37: =+'Financial Model'!N$9 | ... T37: =+'Financial Model'!T$9
C38: % of Total Revenue | G38: =+G35/G37 | H38: =+H35/H37 | I38: =+I35/I37 | J38: =+J35/J37 | K38: 0 | L38: 0 | M38: 0 | N38: 0 | O38: 0 | P38: 0 | Q38: 0 | R38: 0 | S38: 0 | T38: 0
C40: =+'Financial Model'!C23 | G40: =+'Financial Model'!G23 | H40: =+'Financial Model'!H23 | I40: =+'Financial Model'!I23 | J40: =+'Financial Model'!J23 | K40: =+K42*K43 | L40: =+L42*L43 | M40: =+M42*M43 | N40: =+N42*N43 | O40: =+O42*O43 | P40: =+P42*P43 | Q40: =+Q42*Q43 | R40: =+R42*R43 | ... T40: =+T42*T43
C42: Total Revenue | G42: =+'Financial Model'!G$9 | H42: =+'Financial Model'!H$9 | I42: =+'Financial Model'!I$9 | J42: =+'Financial Model'!J$9 | K42: =+'Financial Model'!K$9 | L42: =+'Financial Model'!L$9 | M42: =+'Financial Model'!M$9 | N42: =+'Financial Model'!N$9 | ... T42: =+'Financial Model'!T$9
C43: % of Total Revenue | G43: =+G40/G42 | H43: =+H40/H42 | I43: =+I40/I42 | J43: =+J40/J42 | K43: 0 | L43: 0 | M43: 0 | N43: 0 | O43: 0 | P43: 0 | Q43: 0 | R43: 0 | S43: 0 | T43: 0
C46: Depreciation | G46: =+'Financial Model'!G30 | H46: =+'Financial Model'!H30 | I46: =+'Financial Model'!I30 | J46: =+'Financial Model'!J30 | K46: =+K48*K49 | L46: =+L48*L49 | M46: =+M48*M49 | N46: =+N48*N49 | O46: =+O48*O49 | P46: =+P48*P49 | Q46: =+Q48*Q49 | R46: =+R48*R49 | ... T46: =+T48*T49
C48: Total Revenue | G48: =+'Financial Model'!G$9 | H48: =+'Financial Model'!H$9 | I48: =+'Financial Model'!I$9 | J48: =+'Financial Model'!J$9 | K48: =+'Financial Model'!K$9 | L48: =+'Financial Model'!L$9 | M48: =+'Financial Model'!M$9 | N48: =+'Financial Model'!N$9 | ... T48: =+'Financial Model'!T$9
C49: % of Total Revenue | G49: =+G46/G48 | H49: =+H46/H48 | I49: =+I46/I48 | J49: =+J46/J48 | K49: =($J$46/'Financial Model'!$I$59)*'Financial Model'!J59/K48 | L49: =($J$46/'Financial Model'!$I$59)*'Financial Model'!K59/L48 | M49: =($J$46/'Financial Model'!$I$59)*'Financial Model'!L59/M48 | N49: =($J$46/'Financial Model'!$I$59)*'Financial Model'!M59/N48 | O49: =($J$46/'Financial Model'!$I$59)*'Financial Model'!N59/O48 | P49: =($J$46/'Financial Model'!$I$59)*'Financial Model'!O59/P48 | Q49: =($J$46/'Financial Model'!$I$59)*'Financial Model'!P59/Q48 | R49: =($J$46/'Financial Model'!$I$59)*'Financial Model'!Q59/R48 | ... T49: =($J$46/'Financial Model'!$I$59)*'Financial Model'!S59/T48 | V49: D&A at FY26 rate on opening net PP&E (yards do not shrink with units). Rises from 5.1% to 5.8% of revenue by FY30E, absorbed inside the flat operating margin.
C51: Amortization | G51: =+'Financial Model'!G31 | H51: =+'Financial Model'!H31 | I51: =+'Financial Model'!I31 | J51: =+'Financial Model'!J31 | K51: =+K53*K54 | L51: =+L53*L54 | M51: =+M53*M54 | N51: =+N53*N54 | O51: =+O53*O54 | P51: =+P53*P54 | Q51: =+Q53*Q54 | R51: =+R53*R54 | ... T51: =+T53*T54
C53: Total Revenue | G53: =+'Financial Model'!G$9 | H53: =+'Financial Model'!H$9 | I53: =+'Financial Model'!I$9 | J53: =+'Financial Model'!J$9 | K53: =+'Financial Model'!K$9 | L53: =+'Financial Model'!L$9 | M53: =+'Financial Model'!M$9 | N53: =+'Financial Model'!N$9 | ... T53: =+'Financial Model'!T$9
C54: % of Total Revenue | G54: =+G51/G53 | H54: =+H51/H53 | I54: =+I51/I53 | J54: =+J51/J53 | K54: 0 | L54: 0 | M54: 0 | N54: 0 | O54: 0 | P54: 0 | Q54: 0 | R54: 0 | S54: 0 | T54: 0
C57: Revolver Interest | K57: =+K59*K60 | L57: =+L59*L60 | M57: =+M59*M60 | N57: =+N59*N60 | O57: =+O59*O60 | P57: =+P59*P60 | Q57: =+Q59*Q60 | R57: =+R59*R60 | ... T57: =+T59*T60
C59: Average Outstanding Balance | K59: =AVERAGE(K135,J135) | L59: =AVERAGE(K135:L135) | M59: =AVERAGE(L135:M135) | N59: =AVERAGE(M135:N135) | O59: =AVERAGE(N135:O135) | P59: =AVERAGE(O135:P135) | Q59: =AVERAGE(P135:Q135) | R59: =AVERAGE(Q135:R135) | S59: =AVERAGE(R135:S135) | T59: =AVERAGE(S135:T135) | V59: - This is subject to changed based on debt balance below
C60: Interest Rate | K60: 0 | L60: 0 | M60: 0 | N60: 0 | O60: 0 | P60: 0 | Q60: 0 | R60: 0 | S60: 0 | T60: 0
C62: Term Loan Interest | K62: =+K64*K65 | L62: =+L64*L65 | M62: =+M64*M65 | N62: =+N64*N65 | O62: =+O64*O65 | P62: =+P64*P65 | Q62: =+Q64*Q65 | R62: =+R64*R65 | ... T62: =+T64*T65
C64: Average Outstanding Balance | K64: =AVERAGE(K140,J140) | L64: =AVERAGE(K140:L140) | M64: =AVERAGE(L140:M140) | N64: =AVERAGE(M140:N140) | O64: =AVERAGE(N140:O140) | P64: =AVERAGE(O140:P140) | Q64: =AVERAGE(P140:Q140) | R64: =AVERAGE(Q140:R140) | S64: =AVERAGE(R140:S140) | T64: =AVERAGE(S140:T140) | V64: - This is subject to changed based on debt balance below
C65: Interest Rate | K65: 0 | L65: 0 | M65: 0 | N65: 0 | O65: 0 | P65: 0 | Q65: 0 | R65: 0 | S65: 0 | T65: 0
C67: =+'Financial Model'!C35 | G67: =+'Financial Model'!G35 | H67: =+'Financial Model'!H35 | I67: =+'Financial Model'!I35 | J67: =+'Financial Model'!J35 | K67: =+K69*K70 | L67: =+L69*L70 | M67: =+M69*M70 | N67: =+N69*N70 | O67: =+O69*O70 | P67: =+P69*P70 | Q67: =+Q69*Q70 | R67: =+R69*R70 | ... T67: =+T69*T70
C69: Total Revenue | G69: =+'Financial Model'!G$9 | H69: =+'Financial Model'!H$9 | I69: =+'Financial Model'!I$9 | J69: =+'Financial Model'!J$9 | K69: =+'Financial Model'!K$9 | L69: =+'Financial Model'!L$9 | M69: =+'Financial Model'!M$9 | N69: =+'Financial Model'!N$9 | ... T69: =+'Financial Model'!T$9
C70: % of Total Revenue | G70: =+G67/G69 | H70: =+H67/H69 | I70: =+I67/I69 | J70: =+J67/J69 | K70: =-K207/K69 | L70: =-L207/L69 | M70: =-M207/M69 | N70: =-N207/N69 | O70: =-O207/O69 | P70: =-P207/P69 | Q70: =-Q207/Q69 | R70: =-R207/R69 | ... T70: =-T207/T69 | V70: Other income per row 207 (memo $110M FY27E; then FY26 yield x opening cash).
C72: =+'Financial Model'!C38 | G72: =+'Financial Model'!G38 | H72: =+'Financial Model'!H38 | I72: =+'Financial Model'!I38 | J72: =+'Financial Model'!J38 | K72: =+K74*K75 | L72: =+L74*L75 | M72: =+M74*M75 | N72: =+N74*N75 | O72: =+O74*O75 | P72: =+P74*P75 | Q72: =+Q74*Q75 | R72: =+R74*R75 | ... T72: =+T74*T75
C74: =+'Financial Model'!C36 | G74: =+'Financial Model'!G$36 | H74: =+'Financial Model'!H$36 | I74: =+'Financial Model'!I$36 | J74: =+'Financial Model'!J$36 | K74: =+'Financial Model'!K$36 | L74: =+'Financial Model'!L$36 | M74: =+'Financial Model'!M$36 | N74: =+'Financial Model'!N$36 | ... T74: =+'Financial Model'!T$36
C75: Tax Rate | G75: =+G72/G74 | H75: =+H72/H74 | I75: =+I72/I74 | J75: =+J72/J74 | K75: =AVERAGE($H$75:$J$75) | L75: =AVERAGE($H$75:$J$75) | M75: =AVERAGE($H$75:$J$75) | N75: =AVERAGE($H$75:$J$75) | O75: =AVERAGE($H$75:$J$75) | P75: =AVERAGE($H$75:$J$75) | Q75: =AVERAGE($H$75:$J$75) | R75: =AVERAGE($H$75:$J$75) | ... T75: =AVERAGE($H$75:$J$75) | V75: FY24-FY26 average effective rate.
V78: Notes
C79: =Assumptions!G$5
A80: X | C80: Balance Sheet Drivers | J80: FY26A / LTM
C81: =Assumptions!$G$9 | G81: ='Historical Financials'!G5 | H81: ='Historical Financials'!H5 | I81: ='Historical Financials'!I5 | J81: ='Historical Financials'!J5 | K81: ="FY"&'Financial Model'!K$1&"E" | L81: ="FY"&'Financial Model'!L$1&"E" | M81: ="FY"&'Financial Model'!M$1&"E" | N81: ="FY"&'Financial Model'!N$1&"E" | O81: ="FY"&'Financial Model'!O$1&"E" | P81: ="FY"&'Financial Model'!P$1&"E" | Q81: ="FY"&'Financial Model'!Q$1&"E" | R81: ="FY"&'Financial Model'!R$1&"E" | ... T81: ="FY"&'Financial Model'!T$1&"E"
C83: ='Financial Model'!C51 | G83: ='Financial Model'!G51 | H83: ='Financial Model'!H51 | I83: ='Financial Model'!I51 | J83: ='Financial Model'!J51 | K83: =+K85*K86/365 | L83: =+L85*L86/365 | M83: =+M85*M86/365 | N83: =+N85*N86/365 | O83: =+O85*O86/365 | P83: =+P85*P86/365 | Q83: =+Q85*Q86/365 | R83: =+R85*R86/365 | ... T83: =+T85*T86/365
C85: Total Revenue | G85: =+'Financial Model'!G$9 | H85: =+'Financial Model'!H$9 | I85: =+'Financial Model'!I$9 | J85: =+'Financial Model'!J$9 | K85: =+'Financial Model'!K$9 | L85: =+'Financial Model'!L$9 | M85: =+'Financial Model'!M$9 | N85: =+'Financial Model'!N$9 | ... T85: =+'Financial Model'!T$9
C86: Days Sales Outstanding (DSO) | G86: =G83/G85*365 | H86: =H83/H85*365 | I86: =I83/I85*365 | J86: =J83/J85*365 | K86: =$J$86 | L86: =$J$86 | M86: =$J$86 | N86: =$J$86 | O86: =$J$86 | P86: =$J$86 | Q86: =$J$86 | R86: =$J$86 | ... T86: =$J$86
C88: ='Financial Model'!C52 | G88: ='Financial Model'!G52 | H88: ='Financial Model'!H52 | I88: ='Financial Model'!I52 | J88: ='Financial Model'!J52 | K88: =+K90*K91 | L88: =+L90*L91 | M88: =+M90*M91 | N88: =+N90*N91 | O88: =+O90*O91 | P88: =+P90*P91 | Q88: =+Q90*Q91 | R88: =+R90*R91 | ... T88: =+T90*T91
C90: =+'Financial Model'!C24 | G90: =+'Financial Model'!G24 | H90: =+'Financial Model'!H24 | I90: =+'Financial Model'!I24 | J90: =+'Financial Model'!J24 | K90: =+'Financial Model'!K24 | L90: =+'Financial Model'!L24 | M90: =+'Financial Model'!M24 | N90: =+'Financial Model'!N24 | ... T90: =+'Financial Model'!T24
C91: % of Opex | G91: =+G88/G90 | H91: =+H88/H90 | I91: =+I88/I90 | J91: =+J88/J90 | K91: =$J$91 | L91: =$J$91 | M91: =$J$91 | N91: =$J$91 | O91: =$J$91 | P91: =$J$91 | Q91: =$J$91 | R91: =$J$91 | ... T91: =$J$91
C93: ='Financial Model'!C53 | G93: ='Financial Model'!G53 | H93: ='Financial Model'!H53 | I93: ='Financial Model'!I53 | J93: ='Financial Model'!J53 | K93: =+K95*K96/365 | L93: =+L95*L96/365 | M93: =+M95*M96/365 | N93: =+N95*N96/365 | O93: =+O95*O96/365 | P93: =+P95*P96/365 | Q93: =+Q95*Q96/365 | R93: =+R95*R96/365 | ... T93: =+T95*T96/365
C95: =+'Financial Model'!C14 | G95: =+'Financial Model'!G14 | H95: =+'Financial Model'!H14 | I95: =+'Financial Model'!I14 | J95: =+'Financial Model'!J14 | K95: =+'Financial Model'!K14 | L95: =+'Financial Model'!L14 | M95: =+'Financial Model'!M14 | N95: =+'Financial Model'!N14 | ... T95: =+'Financial Model'!T14
C96: Days in Inventory | G96: =+G93/G95*365 | H96: =+H93/H95*365 | I96: =+I93/I95*365 | J96: =+J93/J95*365 | K96: =$J$96 | L96: =$J$96 | M96: =$J$96 | N96: =$J$96 | O96: =$J$96 | P96: =$J$96 | Q96: =$J$96 | R96: =$J$96 | ... T96: =$J$96
C98: ='Financial Model'!C54 | G98: ='Financial Model'!G54 | H98: ='Financial Model'!H54 | I98: ='Financial Model'!I54 | J98: ='Financial Model'!J54 | K98: =+K100*K101 | L98: =+L100*L101 | M98: =+M100*M101 | N98: =+N100*N101 | O98: =+O100*O101 | P98: =+P100*P101 | Q98: =+Q100*Q101 | R98: =+R100*R101 | ... T98: =+T100*T101
C100: Total Revenue | G100: =+'Financial Model'!G$9 | H100: =+'Financial Model'!H$9 | I100: =+'Financial Model'!I$9 | J100: =+'Financial Model'!J$9 | K100: =+'Financial Model'!K$9 | L100: =+'Financial Model'!L$9 | M100: =+'Financial Model'!M$9 | N100: =+'Financial Model'!N$9 | ... T100: =+'Financial Model'!T$9
C101: % of Total Revenue | G101: =+G98/G100 | H101: =+H98/H100 | I101: =+I98/I100 | J101: =+J98/J100 | K101: =$J$101 | L101: =$J$101 | M101: =$J$101 | N101: =$J$101 | O101: =$J$101 | P101: =$J$101 | Q101: =$J$101 | R101: =$J$101 | ... T101: =$J$101
C103: =+'Financial Model'!C65 | G103: =+'Financial Model'!G65 | H103: =+'Financial Model'!H65 | I103: =+'Financial Model'!I65 | J103: =+'Financial Model'!J65 | K103: =+K105*K106 | L103: =+L105*L106 | M103: =+M105*M106 | N103: =+N105*N106 | O103: =+O105*O106 | P103: =+P105*P106 | Q103: =+Q105*Q106 | R103: =+R105*R106 | ... T103: =+T105*T106
C105: Total Revenue | G105: =+'Financial Model'!G$9 | H105: =+'Financial Model'!H$9 | I105: =+'Financial Model'!I$9 | J105: =+'Financial Model'!J$9 | K105: =+'Financial Model'!K$9 | L105: =+'Financial Model'!L$9 | M105: =+'Financial Model'!M$9 | N105: =+'Financial Model'!N$9 | ... T105: =+'Financial Model'!T$9
C106: % of Total Revenue | G106: =+G103/G105 | H106: =+H103/H105 | I106: =+I103/I105 | J106: =+J103/J105 | K106: =$J$106 | L106: =$J$106 | M106: =$J$106 | N106: =$J$106 | O106: =$J$106 | P106: =$J$106 | Q106: =$J$106 | R106: =$J$106 | ... T106: =$J$106
C109: ='Financial Model'!$C$69 | G109: =+'Financial Model'!G69 | H109: =+'Financial Model'!H69 | I109: =+'Financial Model'!I69 | J109: =+'Financial Model'!J69 | K109: =+K111*K112/365 | L109: =+L111*L112/365 | M109: =+M111*M112/365 | N109: =+N111*N112/365 | O109: =+O111*O112/365 | P109: =+P111*P112/365 | Q109: =+Q111*Q112/365 | R109: =+R111*R112/365 | ... T109: =+T111*T112/365
C111: Cost of Goods Sold | G111: =+'Financial Model'!G14 | H111: =+'Financial Model'!H14 | I111: =+'Financial Model'!I14 | J111: =+'Financial Model'!J14 | K111: =+'Financial Model'!K14 | L111: =+'Financial Model'!L14 | M111: =+'Financial Model'!M14 | N111: =+'Financial Model'!N14 | ... T111: =+'Financial Model'!T14
C112: Days Payable Outstanding (DPO) | G112: =+G109/G111*365 | H112: =+H109/H111*365 | I112: =+I109/I111*365 | J112: =+J109/J111*365 | K112: =$J$112 | L112: =$J$112 | M112: =$J$112 | N112: =$J$112 | O112: =$J$112 | P112: =$J$112 | Q112: =$J$112 | R112: =$J$112 | ... T112: =$J$112
C114: ='Financial Model'!$C$70 | G114: =+'Financial Model'!G70 | H114: =+'Financial Model'!H70 | I114: =+'Financial Model'!I70 | J114: =+'Financial Model'!J70 | K114: =+K116*K117 | L114: =+L116*L117 | M114: =+M116*M117 | N114: =+N116*N117 | O114: =+O116*O117 | P114: =+P116*P117 | Q114: =+Q116*Q117 | R114: =+R116*R117 | ... T114: =+T116*T117
C116: Operating Expenses | G116: =+'Financial Model'!G24 | H116: =+'Financial Model'!H24 | I116: =+'Financial Model'!I24 | J116: =+'Financial Model'!J24 | K116: =+'Financial Model'!K24 | L116: =+'Financial Model'!L24 | M116: =+'Financial Model'!M24 | N116: =+'Financial Model'!N24 | ... T116: =+'Financial Model'!T24
C117: % of Operating Expenses | G117: =+G114/G116 | H117: =+H114/H116 | I117: =+I114/I116 | J117: =+J114/J116 | K117: =$J$117 | L117: =$J$117 | M117: =$J$117 | N117: =$J$117 | O117: =$J$117 | P117: =$J$117 | Q117: =$J$117 | R117: =$J$117 | ... T117: =$J$117
C119: ='Financial Model'!$C$71 | G119: =+'Financial Model'!G71 | H119: =+'Financial Model'!H71 | I119: =+'Financial Model'!I71 | J119: =+'Financial Model'!J71 | K119: =+K121*K122 | L119: =+L121*L122 | M119: =+M121*M122 | N119: =+N121*N122 | O119: =+O121*O122 | P119: =+P121*P122 | Q119: =+Q121*Q122 | R119: =+R121*R122 | ... T119: =+T121*T122
C121: Total Revenue | G121: =+'Financial Model'!G$9 | H121: =+'Financial Model'!H$9 | I121: =+'Financial Model'!I$9 | J121: =+'Financial Model'!J$9 | K121: =+'Financial Model'!K$9 | L121: =+'Financial Model'!L$9 | M121: =+'Financial Model'!M$9 | N121: =+'Financial Model'!N$9 | ... T121: =+'Financial Model'!T$9
C122: % of Total Revenue | G122: =+G119/G121 | H122: =+H119/H121 | I122: =+I119/I121 | J122: =+J119/J121 | K122: =$J$122 | L122: =$J$122 | M122: =$J$122 | N122: =$J$122 | O122: =$J$122 | P122: =$J$122 | Q122: =$J$122 | R122: =$J$122 | ... T122: =$J$122
C124: ='Financial Model'!$C$72 | G124: =+'Financial Model'!G72 | H124: =+'Financial Model'!H72 | I124: =+'Financial Model'!I72 | J124: =+'Financial Model'!J72 | K124: =+K126*K127 | L124: =+L126*L127 | M124: =+M126*M127 | N124: =+N126*N127 | O124: =+O126*O127 | P124: =+P126*P127 | Q124: =+Q126*Q127 | R124: =+R126*R127 | ... T124: =+T126*T127
C126: Total Revenue | G126: =+'Financial Model'!G$9 | H126: =+'Financial Model'!H$9 | I126: =+'Financial Model'!I$9 | J126: =+'Financial Model'!J$9 | K126: =+'Financial Model'!K$9 | L126: =+'Financial Model'!L$9 | M126: =+'Financial Model'!M$9 | N126: =+'Financial Model'!N$9 | ... T126: =+'Financial Model'!T$9
C127: % of Total Revenue | G127: =+G124/G126 | H127: =+H124/H126 | I127: =+I124/I126 | J127: =+J124/J126 | K127: =$J$127 | L127: =$J$127 | M127: =$J$127 | N127: =$J$127 | O127: =$J$127 | P127: =$J$127 | Q127: =$J$127 | R127: =$J$127 | ... T127: =$J$127
C129: ='Financial Model'!$C$77 | G129: =+'Financial Model'!G77 | H129: =+'Financial Model'!H77 | I129: =+'Financial Model'!I77 | J129: =+'Financial Model'!J77 | K129: =+K131*K132 | L129: =+L131*L132 | M129: =+M131*M132 | N129: =+N131*N132 | O129: =+O131*O132 | P129: =+P131*P132 | Q129: =+Q131*Q132 | R129: =+R131*R132 | ... T129: =+T131*T132
C131: Total Revenue | G131: =+'Financial Model'!G$9 | H131: =+'Financial Model'!H$9 | I131: =+'Financial Model'!I$9 | J131: =+'Financial Model'!J$9 | K131: =+'Financial Model'!K$9 | L131: =+'Financial Model'!L$9 | M131: =+'Financial Model'!M$9 | N131: =+'Financial Model'!N$9 | ... T131: =+'Financial Model'!T$9
C132: % of Total Revenue | G132: =+G129/G131 | H132: =+H129/H131 | I132: =+I129/I131 | J132: =+J129/J131 | K132: =$J$132 | L132: =$J$132 | M132: =$J$132 | N132: =$J$132 | O132: =$J$132 | P132: =$J$132 | Q132: =$J$132 | R132: =$J$132 | ... T132: =$J$132
C135: ='Financial Model'!$C$75 | G135: =+'Financial Model'!G75 | H135: =+'Financial Model'!H75 | I135: =+'Financial Model'!I75 | J135: =+'Financial Model'!J75 | K135: =SUM(K137:K138) | L135: =SUM(L137:L138) | M135: =SUM(M137:M138) | N135: =SUM(N137:N138) | O135: =SUM(O137:O138) | P135: =SUM(P137:P138) | Q135: =SUM(Q137:Q138) | R135: =SUM(R137:R138) | ... T135: =SUM(T137:T138)
C137: Beginning Revolver Balance | K137: =+J135 | L137: =+K135 | M137: =+L135 | N137: =+M135 | O137: =+N135 | P137: =+O135 | Q137: =+P135 | R137: =+Q135 | ... T137: =+S135
C138: Borrowings (Paydowns) | K138: 0 | L138: 0 | M138: 0 | N138: 0 | O138: 0 | P138: 0 | Q138: 0 | R138: 0 | S138: 0 | T138: 0
C140: ='Financial Model'!$C$76 | G140: =+'Financial Model'!G76 | H140: =+'Financial Model'!H76 | I140: =+'Financial Model'!I76 | J140: =+'Financial Model'!J76 | K140: =SUM(K142:K145) | L140: =SUM(L142:L145) | M140: =SUM(M142:M145) | N140: =SUM(N142:N145) | O140: =SUM(O142:O145) | P140: =SUM(P142:P145) | Q140: =SUM(Q142:Q145) | R140: =SUM(R142:R145) | ... T140: =SUM(T142:T145)
C142: Beginning Term Loan Balance | K142: =+J140 | L142: =+K140 | M142: =+L140 | N142: =+M140 | O142: =+N140 | P142: =+O140 | Q142: =+P140 | R142: =+Q140 | ... T142: =+S140
C143: Additional Borrowings | K143: 0 | L143: 0 | M143: 0 | N143: 0 | O143: 0 | P143: 0 | Q143: 0 | R143: 0 | S143: 0 | T143: 0
C144: (Mandatory Amortization) | K144: 0 | L144: 0 | M144: 0 | N144: 0 | O144: 0 | P144: 0 | Q144: 0 | R144: 0 | S144: 0 | T144: 0
C145: (Prepayments) | K145: 0 | L145: 0 | M145: 0 | N145: 0 | O145: 0 | P145: 0 | Q145: 0 | R145: 0 | S145: 0 | T145: 0
C148: ='Financial Model'!$C$83 | G148: =+'Financial Model'!G83 | H148: =+'Financial Model'!H83 | I148: =+'Financial Model'!I83 | J148: =+'Financial Model'!J83 | K148: =SUM(K150:K151) | L148: =SUM(L150:L151) | M148: =SUM(M150:M151) | N148: =SUM(N150:N151) | O148: =SUM(O150:O151) | P148: =SUM(P150:P151) | Q148: =SUM(Q150:Q151) | R148: =SUM(R150:R151) | ... T148: =SUM(T150:T151)
C150: Beginning Other S/E | K150: =+J148 | L150: =+K148 | M150: =+L148 | N150: =+M148 | O150: =+N148 | P150: =+O148 | Q150: =+P148 | R150: =+Q148 | ... T150: =+S148
C151: New S/E | K151: 0 | L151: 0 | M151: 0 | N151: 0 | O151: 0 | P151: 0 | Q151: 0 | R151: 0 | S151: 0 | T151: 0
V154: Notes
C155: =Assumptions!G$5
A156: X | C156: Cash Flow Statement Drivers | J156: FY26A / LTM
C157: =Assumptions!$G$9 | G157: ='Historical Financials'!G5 | H157: ='Historical Financials'!H5 | I157: ='Historical Financials'!I5 | J157: ='Historical Financials'!J5 | K157: ="FY"&'Financial Model'!K$1&"E" | L157: ="FY"&'Financial Model'!L$1&"E" | M157: ="FY"&'Financial Model'!M$1&"E" | N157: ="FY"&'Financial Model'!N$1&"E" | O157: ="FY"&'Financial Model'!O$1&"E" | P157: ="FY"&'Financial Model'!P$1&"E" | Q157: ="FY"&'Financial Model'!Q$1&"E" | R157: ="FY"&'Financial Model'!R$1&"E" | ... T157: ="FY"&'Financial Model'!T$1&"E"
C159: =+'Financial Model'!C101 | G159: ='Financial Model'!G101 | H159: ='Financial Model'!H101 | I159: ='Financial Model'!I101 | J159: ='Financial Model'!J101 | K159: =+K161*K162 | L159: =+L161*L162 | M159: =+M161*M162 | N159: =+N161*N162 | O159: =+O161*O162 | P159: =+P161*P162 | Q159: =+Q161*Q162 | R159: =+R161*R162 | ... T159: =+T161*T162
C161: Total Revenue | G161: =+'Financial Model'!G9 | H161: =+'Financial Model'!H9 | I161: =+'Financial Model'!I9 | J161: =+'Financial Model'!J9 | K161: =+'Financial Model'!K9 | L161: =+'Financial Model'!L9 | M161: =+'Financial Model'!M9 | N161: =+'Financial Model'!N9 | ... T161: =+'Financial Model'!T9
C162: % of Total Revenue | G162: =+G159/G161 | H162: =+H159/H161 | I162: =+I159/I161 | J162: =+J159/J161 | K162: =$J$162 | L162: =$J$162 | M162: =$J$162 | N162: =$J$162 | O162: =$J$162 | P162: =$J$162 | Q162: =$J$162 | R162: =$J$162 | ... T162: =$J$162
C166: =+'Financial Model'!C118 | G166: =+'Financial Model'!G118 | H166: =+'Financial Model'!H118 | I166: =+'Financial Model'!I118 | J166: =+'Financial Model'!J118 | K166: =+K168*K169 | L166: =+L168*L169 | M166: =+M168*M169 | N166: =+N168*N169 | O166: =+O168*O169 | P166: =+P168*P169 | Q166: =+Q168*Q169 | R166: =+R168*R169 | ... T166: =+T168*T169
C168: Total Revenue | G168: =+'Financial Model'!G9 | H168: =+'Financial Model'!H9 | I168: =+'Financial Model'!I9 | J168: =+'Financial Model'!J9 | K168: =+'Financial Model'!K9 | L168: =+'Financial Model'!L9 | M168: =+'Financial Model'!M9 | N168: =+'Financial Model'!N9 | ... T168: =+'Financial Model'!T9
C169: % of Total Revenue | G169: =+G166/G168 | H169: =+H166/H168 | I169: =+I166/I168 | J169: =+J166/J168 | K169: =AVERAGE($H$169:$J$169) | L169: =AVERAGE($H$169:$J$169) | M169: =AVERAGE($H$169:$J$169) | N169: =AVERAGE(M169,$J$169) | O169: =$J$169 | P169: =$J$169 | Q169: =$J$169 | R169: =$J$169 | S169: =$J$169 | T169: =$J$169 | V169: Capex at FY24-FY26 average % of revenue for FY27E-FY29E; steps to FY26 % (near D&A + growth) by FY31E. Negative = outflow (template sign).
C171: =+'Financial Model'!C119 | G171: =+'Financial Model'!G119 | H171: =+'Financial Model'!H119 | I171: =+'Financial Model'!I119 | J171: =+'Financial Model'!J119 | K171: =-Support!$D$12 | L171: 0 | M171: 0 | N171: 0 | O171: 0 | P171: 0 | Q171: 0 | R171: 0 | S171: 0 | T171: 0 | V171: ACV: $1.9B cash (8-K, 9/10/2026) leaves at FY27E open; booked to goodwill & intangibles; no ACV P&L consolidated.
C175: ='Financial Model'!$C$125 | G175: =+'Financial Model'!G125 | H175: =+'Financial Model'!H125 | I175: =+'Financial Model'!I125 | J175: =+'Financial Model'!J125 | K175: =K177*K178 | L175: =L177*L178 | M175: =M177*M178 | N175: =N177*N178 | O175: =O177*O178 | P175: =P177*P178 | Q175: =Q177*Q178 | R175: =R177*R178 | ... T175: =T177*T178
...

Sheet Multiples & Ratios
K1: =YEAR('Historical Financials'!J1)+1 | L1: =K1+1 | M1: =L1+1 | N1: =M1+1 | O1: =N1+1 | P1: =O1+1 | Q1: =P1+1 | R1: =Q1+1 | S1: =R1+1 | T1: =S1+1
C3: =Assumptions!G5
A4: X | C4: Multiples & Ratios | J4: FY26A / LTM
C5: =Assumptions!$G$9 | G5: ='Historical Financials'!G5 | H5: ='Historical Financials'!H5 | I5: ='Historical Financials'!I5 | J5: ='Historical Financials'!J5 | K5: ="FY"&K$1&"E" | L5: ="FY"&L$1&"E" | M5: ="FY"&M$1&"E" | N5: ="FY"&N$1&"E" | O5: ="FY"&O$1&"E" | P5: ="FY"&P$1&"E" | Q5: ="FY"&Q$1&"E" | R5: ="FY"&R$1&"E" | ... T5: ="FY"&T$1&"E"
C7: Valuation
C8: EV / Sales | G8: =G55/G66 | H8: =H55/H66 | I8: =I55/I66 | J8: =J55/J66 | K8: =K55/K66 | L8: =L55/L66 | M8: =M55/M66 | N8: =N55/N66 | ... T8: =T55/T66
C9: EV / EBITDA | G9: =G55/G68 | H9: =H55/H68 | I9: =I55/I68 | J9: =J55/J68 | K9: =K55/K68 | L9: =L55/L68 | M9: =M55/M68 | N9: =N55/N68 | ... T9: =T55/T68
C10: EV / FCFF | G10: =G55/G71 | H10: =H55/H71 | I10: =I55/I71 | J10: =J55/J71 | K10: =K55/K71 | L10: =L55/L71 | M10: =M55/M71 | N10: =N55/N71 | ... T10: =T55/T71
C11: P / E | G11: =G52/G70 | H11: =H52/H70 | I11: =I52/I70 | J11: =J52/J70 | K11: =K52/K70 | L11: =L52/L70 | M11: =M52/M70 | N11: =N52/N70 | ... T11: =T52/T70
C13: Profitability
C14: ='Financial Model'!C19 | G14: ='Financial Model'!G19 | H14: ='Financial Model'!H19 | I14: ='Financial Model'!I19 | J14: ='Financial Model'!J19 | K14: ='Financial Model'!K19 | L14: ='Financial Model'!L19 | M14: ='Financial Model'!M19 | N14: ='Financial Model'!N19 | ... T14: ='Financial Model'!T19
C15: ='Financial Model'!C28 | G15: ='Financial Model'!G28 | H15: ='Financial Model'!H28 | I15: ='Financial Model'!I28 | J15: ='Financial Model'!J28 | K15: ='Financial Model'!K28 | L15: ='Financial Model'!L28 | M15: ='Financial Model'!M28 | N15: ='Financial Model'!N28 | ... T15: ='Financial Model'!T28
C16: ='Financial Model'!C42 | G16: ='Financial Model'!G42 | H16: ='Financial Model'!H42 | I16: ='Financial Model'!I42 | J16: ='Financial Model'!J42 | K16: ='Financial Model'!K42 | L16: ='Financial Model'!L42 | M16: ='Financial Model'!M42 | N16: ='Financial Model'!N42 | ... T16: ='Financial Model'!T42
C17: FCF Margin | G17: =Summary!G25 | H17: =Summary!H25 | I17: =Summary!I25 | J17: =Summary!J25 | K17: =Summary!K25 | L17: =Summary!L25 | M17: =Summary!M25 | N17: =Summary!N25 | ... T17: =Summary!T25
C19: KPIs
C20: US insurance unit growth | G20: n/a | H20: =Drivers!H194 | I20: =Drivers!I194 | J20: =Drivers!J194 | K20: =Drivers!K194 | L20: =Drivers!L194 | M20: =Drivers!M194 | N20: =Drivers!N194 | O20: =Drivers!O194 | ... T20: =Drivers!T194
C21: Revenue per unit growth | G21: n/a | H21: =Drivers!H203 | I21: =Drivers!I203 | J21: =Drivers!J203 | K21: =Drivers!K203 | L21: =Drivers!L203 | M21: =Drivers!M203 | N21: =Drivers!N203 | O21: =Drivers!O203 | ... T21: =Drivers!T203
C22: Copart share of Copart + IAA units | G22: n/a | H22: n/a | I22: =Drivers!I218 | J22: =Drivers!J218 | K22: n/a | L22: n/a | M22: n/a | N22: n/a | O22: n/a | P22: n/a | Q22: n/a | R22: n/a | S22: n/a | T22: n/a
C24: Investor Returns
C25: ROA | G25: =G70/G62 | H25: =H70/H62 | I25: =I70/I62 | J25: =J70/J62 | K25: =K70/K62 | L25: =L70/L62 | M25: =M70/M62 | N25: =N70/N62 | ... T25: =T70/T62
C26: ROE | G26: =G70/G64 | H26: =H70/H64 | I26: =I70/I64 | J26: =J70/J64 | K26: =K70/K64 | L26: =L70/L64 | M26: =M70/M64 | N26: =N70/N64 | ... T26: =T70/T64
C27: ROIC | G27: =G72/SUM(G64,G53) | H27: =H72/SUM(H64,H53) | I27: =I72/SUM(I64,I53) | J27: =J72/SUM(J64,J53) | K27: =K72/SUM(K64,K53) | L27: =L72/SUM(L64,L53) | M27: =M72/SUM(M64,M53) | N27: =N72/SUM(N64,N53) | ... T27: =T72/SUM(T64,T53)
C28: EPS | G28: =G70/G57 | H28: =H70/H57 | I28: =I70/I57 | J28: =J70/J57 | K28: =K70/K57 | L28: =L70/L57 | M28: =M70/M57 | N28: =N70/N57 | ... T28: =T70/T57
C30: Asset Efficiency
C31: Asset Turnover | G31: =G66/G62 | H31: =H66/H62 | I31: =I66/I62 | J31: =J66/J62 | K31: =K66/K62 | L31: =L66/L62 | M31: =M66/M62 | N31: =N66/N62 | ... T31: =T66/T62
C32: Inventory Turnover | G32: =G67/G60 | H32: =H67/H60 | I32: =I67/I60 | J32: =J67/J60 | K32: =K67/K60 | L32: =L67/L60 | M32: =M67/M60 | N32: =N67/N60 | ... T32: =T67/T60
C33: Receivables Turnover | G33: =G66/G59 | H33: =H66/H59 | I33: =I66/I59 | J33: =J66/J59 | K33: =K66/K59 | L33: =L66/L59 | M33: =M66/M59 | N33: =N66/N59 | ... T33: =T66/T59
C34: =Drivers!C86 | G34: =Drivers!G86 | H34: =Drivers!H86 | I34: =Drivers!I86 | J34: =Drivers!J86 | K34: =Drivers!K86 | L34: =Drivers!L86 | M34: =Drivers!M86 | N34: =Drivers!N86 | ... T34: =Drivers!T86
C35: =Drivers!C112 | G35: =Drivers!G112 | H35: =Drivers!H112 | I35: =Drivers!I112 | J35: =Drivers!J112 | K35: =Drivers!K112 | L35: =Drivers!L112 | M35: =Drivers!M112 | N35: =Drivers!N112 | ... T35: =Drivers!T112
C37: Leverage
C38: Debt / Assets | G38: =G53/G62 | H38: =H53/H62 | I38: =I53/I62 | J38: =J53/J62 | K38: =K53/K62 | L38: =L53/L62 | M38: =M53/M62 | N38: =N53/N62 | ... T38: =T53/T62
C39: Debt / Equity | G39: =G53/G52 | H39: =H53/H52 | I39: =I53/I52 | J39: =J53/J52 | K39: =K53/K52 | L39: =L53/L52 | M39: =M53/M52 | N39: =N53/N52 | ... T39: =T53/T52
C40: Debt / EBITDA | G40: =G53/G68 | H40: =H53/H68 | I40: =I53/I68 | J40: =J53/J68 | K40: =K53/K68 | L40: =L53/L68 | M40: =M53/M68 | N40: =N53/N68 | ... T40: =T53/T68
C41: Interest Coverage | G41: =IFERROR(G69/G74,"n/m") | H41: =IFERROR(H69/H74,"n/m") | I41: =IFERROR(I69/I74,"n/m") | J41: =IFERROR(J69/J74,"n/m") | K41: =IFERROR(K69/K74,"n/m") | L41: =IFERROR(L69/L74,"n/m") | M41: =IFERROR(M69/M74,"n/m") | N41: =IFERROR(N69/N74,"n/m") | ... T41: =IFERROR(T69/T74,"n/m")
C42: Debt Service Coverage | G42: =IFERROR(G69/G76,"n/m") | H42: =IFERROR(H69/H76,"n/m") | I42: =IFERROR(I69/I76,"n/m") | J42: =IFERROR(J69/J76,"n/m") | K42: =IFERROR(K69/K76,"n/m") | L42: =IFERROR(L69/L76,"n/m") | M42: =IFERROR(M69/M76,"n/m") | N42: =IFERROR(N69/N76,"n/m") | ... T42: =IFERROR(T69/T76,"n/m")
C44: Liquidity
C45: Current Ratio | G45: =G61/G63 | H45: =H61/H63 | I45: =I61/I63 | J45: =J61/J63 | K45: =K61/K63 | L45: =L61/L63 | M45: =M61/M63 | N45: =N61/N63 | ... T45: =T61/T63
C46: Acid-Test Ratio | G46: =(G61-G60)/G63 | H46: =(H61-H60)/H63 | I46: =(I61-I60)/I63 | J46: =(J61-J60)/J63 | K46: =(K61-K60)/K63 | L46: =(L61-L60)/L63 | M46: =(M61-M60)/M63 | N46: =(N61-N60)/N63 | ... T46: =(T61-T60)/T63
C47: Cash Ratio | G47: =G54/G63 | H47: =H54/H63 | I47: =I54/I63 | J47: =J54/J63 | K47: =K54/K63 | L47: =L54/L63 | M47: =M54/M63 | N47: =N54/N63 | ... T47: =T54/T63
C50: Supporting Information
C52: Market Value of Equity | G52: =Support!$D$5 | H52: =Support!$D$5 | I52: =Support!$D$5 | J52: =Support!$D$5 | K52: =Support!$D$5 | L52: =Support!$D$5 | M52: =Support!$D$5 | N52: =Support!$D$5 | ... T52: =Support!$D$5
C53: Debt | G53: =SUM('Financial Model'!G75:G76) | H53: =SUM('Financial Model'!H75:H76) | I53: =SUM('Financial Model'!I75:I76) | J53: =SUM('Financial Model'!J75:J76) | K53: =SUM('Financial Model'!K75:K76) | L53: =SUM('Financial Model'!L75:L76) | M53: =SUM('Financial Model'!M75:M76) | N53: =SUM('Financial Model'!N75:N76) | ... T53: =SUM('Financial Model'!T75:T76)
C54: ='Financial Model'!$C$50 | G54: ='Financial Model'!G50 | H54: ='Financial Model'!H50 | I54: ='Financial Model'!I50 | J54: ='Financial Model'!J50 | K54: ='Financial Model'!K50 | L54: ='Financial Model'!L50 | M54: ='Financial Model'!M50 | N54: ='Financial Model'!N50 | ... T54: ='Financial Model'!T50
C55: Enterprise Value | G55: =G52+G53-G54 | H55: =H52+H53-H54 | I55: =I52+I53-I54 | J55: =J52+J53-J54 | K55: =K52+K53-K54 | L55: =L52+L53-L54 | M55: =M52+M53-M54 | N55: =N52+N53-N54 | ... T55: =T52+T53-T54
C57: Fully-Diluted Shares Outstanding | G57: =Drivers!G215 | H57: =Drivers!H215 | I57: =Drivers!I215 | J57: =Drivers!J215 | K57: =Drivers!K215 | L57: =Drivers!L215 | M57: =Drivers!M215 | N57: =Drivers!N215 | ... T57: =Drivers!T215
C59: ='Financial Model'!C51 | G59: ='Financial Model'!G51 | H59: ='Financial Model'!H51 | I59: ='Financial Model'!I51 | J59: ='Financial Model'!J51 | K59: ='Financial Model'!K51 | L59: ='Financial Model'!L51 | M59: ='Financial Model'!M51 | N59: ='Financial Model'!N51 | ... T59: ='Financial Model'!T51
C60: ='Financial Model'!C53 | G60: ='Financial Model'!G53 | H60: ='Financial Model'!H53 | I60: ='Financial Model'!I53 | J60: ='Financial Model'!J53 | K60: ='Financial Model'!K53 | L60: ='Financial Model'!L53 | M60: ='Financial Model'!M53 | N60: ='Financial Model'!N53 | ... T60: ='Financial Model'!T53
C61: ='Financial Model'!C55 | G61: ='Financial Model'!G55 | H61: ='Financial Model'!H55 | I61: ='Financial Model'!I55 | J61: ='Financial Model'!J55 | K61: ='Financial Model'!K55 | L61: ='Financial Model'!L55 | M61: ='Financial Model'!M55 | N61: ='Financial Model'!N55 | ... T61: ='Financial Model'!T55
C62: ='Financial Model'!$C$67 | G62: ='Financial Model'!G67 | H62: ='Financial Model'!H67 | I62: ='Financial Model'!I67 | J62: ='Financial Model'!J67 | K62: ='Financial Model'!K67 | L62: ='Financial Model'!L67 | M62: ='Financial Model'!M67 | N62: ='Financial Model'!N67 | ... T62: ='Financial Model'!T67
C63: ='Financial Model'!C73 | G63: ='Financial Model'!G73 | H63: ='Financial Model'!H73 | I63: ='Financial Model'!I73 | J63: ='Financial Model'!J73 | K63: ='Financial Model'!K73 | L63: ='Financial Model'!L73 | M63: ='Financial Model'!M73 | N63: ='Financial Model'!N73 | ... T63: ='Financial Model'!T73
C64: ='Financial Model'!$C$84 | G64: ='Financial Model'!G84 | H64: ='Financial Model'!H84 | I64: ='Financial Model'!I84 | J64: ='Financial Model'!J84 | K64: ='Financial Model'!K84 | L64: ='Financial Model'!L84 | M64: ='Financial Model'!M84 | N64: ='Financial Model'!N84 | ... T64: ='Financial Model'!T84
C66: ='Financial Model'!C9 | G66: ='Financial Model'!G9 | H66: ='Financial Model'!H9 | I66: ='Financial Model'!I9 | J66: ='Financial Model'!J9 | K66: ='Financial Model'!K9 | L66: ='Financial Model'!L9 | M66: ='Financial Model'!M9 | N66: ='Financial Model'!N9 | ... T66: ='Financial Model'!T9
C67: ='Financial Model'!C14 | G67: ='Financial Model'!G14 | H67: ='Financial Model'!H14 | I67: ='Financial Model'!I14 | J67: ='Financial Model'!J14 | K67: ='Financial Model'!K14 | L67: ='Financial Model'!L14 | M67: ='Financial Model'!M14 | N67: ='Financial Model'!N14 | ... T67: ='Financial Model'!T14
C68: ='Financial Model'!C27 | G68: ='Financial Model'!G27 | H68: ='Financial Model'!H27 | I68: ='Financial Model'!I27 | J68: ='Financial Model'!J27 | K68: ='Financial Model'!K27 | L68: ='Financial Model'!L27 | M68: ='Financial Model'!M27 | N68: ='Financial Model'!N27 | ... T68: ='Financial Model'!T27
C69: ='Financial Model'!C32 | G69: ='Financial Model'!G32 | H69: ='Financial Model'!H32 | I69: ='Financial Model'!I32 | J69: ='Financial Model'!J32 | K69: ='Financial Model'!K32 | L69: ='Financial Model'!L32 | M69: ='Financial Model'!M32 | N69: ='Financial Model'!N32 | ... T69: ='Financial Model'!T32
C70: ='Financial Model'!C41 | G70: ='Financial Model'!G41 | H70: ='Financial Model'!H41 | I70: ='Financial Model'!I41 | J70: ='Financial Model'!J41 | K70: ='Financial Model'!K41 | L70: ='Financial Model'!L41 | M70: ='Financial Model'!M41 | N70: ='Financial Model'!N41 | ... T70: ='Financial Model'!T41
C71: =Summary!C24 | G71: =Summary!G24 | H71: =Summary!H24 | I71: =Summary!I24 | J71: =Summary!J24 | K71: =Summary!K24 | L71: =Summary!L24 | M71: =Summary!M24 | N71: =Summary!N24 | ... T71: =Summary!T24
C72: NOPAT | G72: ='Financial Model'!G32*(1-'Financial Model'!G39) | H72: ='Financial Model'!H32*(1-'Financial Model'!H39) | I72: ='Financial Model'!I32*(1-'Financial Model'!I39) | J72: ='Financial Model'!J32*(1-'Financial Model'!J39) | K72: ='Financial Model'!K32*(1-'Financial Model'!K39) | L72: ='Financial Model'!L32*(1-'Financial Model'!L39) | M72: ='Financial Model'!M32*(1-'Financial Model'!M39) | N72: ='Financial Model'!N32*(1-'Financial Model'!N39) | ... T72: ='Financial Model'!T32*(1-'Financial Model'!T39)
C74: ='Financial Model'!C34 | G74: ='Financial Model'!G34 | H74: ='Financial Model'!H34 | I74: ='Financial Model'!I34 | J74: ='Financial Model'!J34 | K74: ='Financial Model'!K34 | L74: ='Financial Model'!L34 | M74: ='Financial Model'!M34 | N74: ='Financial Model'!N34 | ... T74: ='Financial Model'!T34
C75: Principal Payments | G75: =SUMIF('Financial Model'!G128:G129,"<"&0,'Financial Model'!G128:G129) | H75: =SUMIF('Financial Model'!H128:H129,"<"&0,'Financial Model'!H128:H129) | I75: =SUMIF('Financial Model'!I128:I129,"<"&0,'Financial Model'!I128:I129) | J75: =SUMIF('Financial Model'!J128:J129,"<"&0,'Financial Model'!J128:J129) | K75: =SUMIF('Financial Model'!K128:K129,"<"&0,'Financial Model'!K128:K129) | L75: =SUMIF('Financial Model'!L128:L129,"<"&0,'Financial Model'!L128:L129) | M75: =SUMIF('Financial Model'!M128:M129,"<"&0,'Financial Model'!M128:M129) | N75: =SUMIF('Financial Model'!N128:N129,"<"&0,'Financial Model'!N128:N129) | ... T75: =SUMIF('Financial Model'!T128:T129,"<"&0,'Financial Model'!T128:T129)
C76: Total Debt Payments | G76: =SUM(G74:G75) | H76: =SUM(H74:H75) | I76: =SUM(I74:I75) | J76: =SUM(J74:J75) | K76: =SUM(K74:K75) | L76: =SUM(L74:L75) | M76: =SUM(M74:M75) | N76: =SUM(N74:N75) | ... T76: =SUM(T74:T75)

Sheet Valuation ->

Sheet DCF
C3: =Assumptions!$G$5
A4: X | C4: DCF Analysis | R4: X
C5: =Assumptions!$G$9 | G5: =Drivers!K6 | H5: =Drivers!L6 | I5: =Drivers!M6 | J5: =Drivers!N6 | K5: =Drivers!O6 | L5: =Drivers!P6 | M5: =Drivers!Q6 | N5: =Drivers!R6 | ... P5: =Drivers!T6 | R5: X
R6: X
C7: EBIT | G7: ='Financial Model'!K32 | H7: ='Financial Model'!L32 | I7: ='Financial Model'!M32 | J7: ='Financial Model'!N32 | K7: ='Financial Model'!O32 | L7: ='Financial Model'!P32 | M7: ='Financial Model'!Q32 | N7: ='Financial Model'!R32 | ... P7: ='Financial Model'!T32 | R7: X
C8: x (1 - Tax Rate) | G8: =1-'Financial Model'!K39 | H8: =1-'Financial Model'!L39 | I8: =1-'Financial Model'!M39 | J8: =1-'Financial Model'!N39 | K8: =1-'Financial Model'!O39 | L8: =1-'Financial Model'!P39 | M8: =1-'Financial Model'!Q39 | N8: =1-'Financial Model'!R39 | ... P8: =1-'Financial Model'!T39 | R8: X
C9: + Depreciation & Amortization | G9: =SUM('Financial Model'!K99:K100) | H9: =SUM('Financial Model'!L99:L100) | I9: =SUM('Financial Model'!M99:M100) | J9: =SUM('Financial Model'!N99:N100) | K9: =SUM('Financial Model'!O99:O100) | L9: =SUM('Financial Model'!P99:P100) | M9: =SUM('Financial Model'!Q99:Q100) | N9: =SUM('Financial Model'!R99:R100) | ... P9: =SUM('Financial Model'!T99:T100) | R9: X
C10: + Changes in Net Working Capital | G10: ='Financial Model'!K114 | H10: ='Financial Model'!L114 | I10: ='Financial Model'!M114 | J10: ='Financial Model'!N114 | K10: ='Financial Model'!O114 | L10: ='Financial Model'!P114 | M10: ='Financial Model'!Q114 | N10: ='Financial Model'!R114 | ... P10: ='Financial Model'!T114 | R10: X
C11: + Other Non-Cash | G11: ='Financial Model'!K102 | H11: ='Financial Model'!L102 | I11: ='Financial Model'!M102 | J11: ='Financial Model'!N102 | K11: ='Financial Model'!O102 | L11: ='Financial Model'!P102 | M11: ='Financial Model'!Q102 | N11: ='Financial Model'!R102 | ... P11: ='Financial Model'!T102 | R11: X
C12: - Capital Expenditures | G12: ='Financial Model'!K118 | H12: ='Financial Model'!L118 | I12: ='Financial Model'!M118 | J12: ='Financial Model'!N118 | K12: ='Financial Model'!O118 | L12: ='Financial Model'!P118 | M12: ='Financial Model'!Q118 | N12: ='Financial Model'!R118 | ... P12: ='Financial Model'!T118 | R12: X
C13: Unlevered Free Cash Flow (FCFF) | G13: =G7*G8+SUM(G9:G12) | H13: =H7*H8+SUM(H9:H12) | I13: =I7*I8+SUM(I9:I12) | J13: =J7*J8+SUM(J9:J12) | K13: =K7*K8+SUM(K9:K12) | L13: =L7*L8+SUM(L9:L12) | M13: =M7*M8+SUM(M9:M12) | N13: =N7*N8+SUM(N9:N12) | ... P13: =P7*P8+SUM(P9:P12) | R13: X
R14: X
C15: NPV of FCFF | P15: =NPV(P61,G13:P13) | R15: X
R16: X
C17: Final Year FCF | P17: =P13 | R17: X
C18: x 1 + Perpetual Growth Rate | P18: 1.02 | R18: g = 2.0%
C19: / (WACC - Perpetual Growth Rate) | P19: =+P61-(P18-1) | R19: X
C20: Terminal Value | P20: =+P17*P18/P19 | R20: X
R21: X
C22: NPV of Terminal Value | P22: =PV(P61,COUNTA(G13:P13),,-P20,0) | R22: X
R23: X
C24: Enterprise Value | P24: =SUM(P22,P15) | R24: Equity bridge, per-share value and implied exit EV/EBITDA: Support rows 88-97. Cross-check only.
R25: X
R26: X
R27: X
C28: =Assumptions!$G$5 | R28: X
A29: X | C29: Cost of Capital | R29: X
C30: =Assumptions!$G$9 | P30: ='Financial Model'!J5 | R30: X
R31: X
C32: Cost of Equity | R32: X
R33: X
C34: Expected Return (Rm) | P34: =P36+0.0423 | R34: ERP 4.23%: Damodaran implied ERP (Jan 2026 annual update; Sep-2026 monthly print not retrieved)
R35: X
C36: Risk-Free Rate (Rf) | P36: 0.0529 | R36: Rf: 10-yr Treasury CMT 5.29% on 9/30/2026 (FRED DGS10)
R37: X
C38: Risk Premium (Rm - Rf) | P38: =+P34-P36 | R38: X
C39: x Beta | P39: 1 | R39: Beta 1.0 per brief (2-yr weekly vs S&P 500 not re-estimated here - no price history loaded)
C40: + Risk-Free Rate (Rf) | P40: =+P36 | R40: X
C41: Cost of Equity (%) | P41: =+P38*P39+P40 | R41: X
R42: X
C43: Cost of Debt | R43: X
R44: X
C45: Interest Payments | P45: ='Financial Model'!$J$34 | R45: X
C46: / Total Debt | P46: =SUM('Financial Model'!J75:J76) | R46: X
C47: Average Yield on Debt | P47: 0.0597 | R47: Cost of debt: ICE BofA US Corporate Index effective yield 5.97% (FRED BAMLC0A0CMEY, 9/29/2026 print)
C48: x (1-Tax Rate) | P48: =1-'Financial Model'!$J$39 | R48: X
C49: After Tax Cost of Debt (%) | P49: =+P47*P48 | R49: X
R50: X
C51: Weighted Average Cost of Capital (WACC) | R51: X
R52: X
C53: Cost of Equity | P53: =+P41 | R53: X
C54: x % of Equity in Capital Structure | P54: 0.95 | R54: Target capital structure 95% equity / 5% debt (brief)
C55: Weighted Average Cost of Equity | P55: =+P54*P53 | R55: X
R56: X
C57: After Tax Cost of Debt | P57: =+P49 | R57: X
C58: x % of Debt in Capital Structure | P58: =1-P54 | R58: X
C59: Weighted Average Cost of Debt | P59: =+P58*P57 | R59: X
R60: X
C61: Weighted Average Cost of Capital (WACC) | P61: =SUM(P59,P55) | R61: X
R62: X
R63: X
A64: X | B64: X | C64: X | D64: X | E64: X | F64: X | G64: X | H64: X | P64: X | Q64: X | R64: X

Sheet Comps
C3: =Assumptions!$G$5
C4: Relative Valuation as of September 30, 2026 (memo date)
C5: =Assumptions!$G$9
A7: X | C7: Public Comparables | D7: Industry | E7: Country | F7: Valuation | H7: Financials ($MM's) | K7: Growth / Profitability (%) | N7: Valuation Multiples (x)
F8: EV | G8: Equity Value | H8: Revenue | I8: EBITDA | J8: Net Income | K8: Y/Y Growth | L8: EBITDA Margin | M8: Profit Margin | N8: EV / Revenue | O8: EV / EBITDA | P8: P/E | Q8: Fwd P/E (memo) | R8: Source
C9: RB Global (RBA; owns IAA) | D9: Marketplaces / salvage auctions | E9: Canada/US | L9: =IFERROR(I9/$H9,"n/m") | M9: =IFERROR(J9/$H9,"n/m") | N9: =IFERROR($F9/H9,"n/m") | O9: =IFERROR($F9/I9,"n/m") | P9: =IFERROR($G9/J9,"n/m") | Q9: 16.8 | R9: Memo: 16.8x forward P/E (Yahoo consensus, 9/30/2026)
C10: OPENLANE (KAR) | D10: Dealer wholesale auctions | E10: US | L10: =IFERROR(I10/$H10,"n/m") | M10: =IFERROR(J10/$H10,"n/m") | N10: =IFERROR($F10/H10,"n/m") | O10: =IFERROR($F10/I10,"n/m") | P10: =IFERROR($G10/J10,"n/m") | R10: Not sourced as of 9/30/2026 - left blank
C11: LKQ (floor reference only; excluded from median) | D11: Salvage-parts buyer | E11: US | L11: =IFERROR(I11/$H11,"n/m") | M11: =IFERROR(J11/$H11,"n/m") | N11: =IFERROR($F11/H11,"n/m") | O11: =IFERROR($F11/I11,"n/m") | P11: =IFERROR($G11/J11,"n/m") | Q11: 7.4 | R11: Memo: 7.4x forward P/E (Yahoo consensus, 9/30/2026)
C12: Copart (subject; from model, FY26A) | D12: Salvage auctions | E12: US | F12: =Support!$D$9 | G12: =Support!$D$5 | H12: ='Financial Model'!J9 | I12: ='Financial Model'!J27 | J12: ='Financial Model'!J41 | K12: ='Financial Model'!J10 | L12: =IFERROR(I12/$H12,"n/m") | M12: =IFERROR(J12/$H12,"n/m") | N12: =IFERROR($F12/H12,"n/m") | O12: =IFERROR($F12/I12,"n/m") | P12: =IFERROR($G12/J12,"n/m") | Q12: =Support!$D$101 | R12: P/E on $27.36 / FY26 EPS (memo 17.6x); EV/EBITDA 11.0x vs memo 11.1x
L13: =IFERROR(I13/$H13,"n/m") | M13: =IFERROR(J13/$H13,"n/m") | N13: =IFERROR($F13/H13,"n/m") | O13: =IFERROR($F13/I13,"n/m") | P13: =IFERROR($G13/J13,"n/m")
L14: =IFERROR(I14/$H14,"n/m") | M14: =IFERROR(J14/$H14,"n/m") | N14: =IFERROR($F14/H14,"n/m") | O14: =IFERROR($F14/I14,"n/m") | P14: =IFERROR($G14/J14,"n/m")
L15: =IFERROR(I15/$H15,"n/m") | M15: =IFERROR(J15/$H15,"n/m") | N15: =IFERROR($F15/H15,"n/m") | O15: =IFERROR($F15/I15,"n/m") | P15: =IFERROR($G15/J15,"n/m")
L16: =IFERROR(I16/$H16,"n/m") | M16: =IFERROR(J16/$H16,"n/m") | N16: =IFERROR($F16/H16,"n/m") | O16: =IFERROR($F16/I16,"n/m") | P16: =IFERROR($G16/J16,"n/m")
L17: =IFERROR(I17/$H17,"n/m") | M17: =IFERROR(J17/$H17,"n/m") | N17: =IFERROR($F17/H17,"n/m") | O17: =IFERROR($F17/I17,"n/m") | P17: =IFERROR($G17/J17,"n/m")
C19: Minimum | F19: =IFERROR(MIN(F9:F17),"n/m") | G19: =IFERROR(MIN(G9:G17),"n/m") | H19: =IFERROR(MIN(H9:H17),"n/m") | I19: =IFERROR(MIN(I9:I17),"n/m") | J19: =IFERROR(MIN(J9:J17),"n/m") | K19: =IFERROR(MIN(K9:K17),"n/m") | L19: =IFERROR(MIN(L9:L17),"n/m") | M19: =IFERROR(MIN(M9:M17),"n/m") | ... P19: =IFERROR(MIN(P9:P17),"n/m")
C20: Median | F20: =IFERROR(MEDIAN(F9:F17),"n/m") | G20: =IFERROR(MEDIAN(G9:G17),"n/m") | H20: =IFERROR(MEDIAN(H9:H17),"n/m") | I20: =IFERROR(MEDIAN(I9:I17),"n/m") | J20: =IFERROR(MEDIAN(J9:J17),"n/m") | K20: =IFERROR(MEDIAN(K9:K17),"n/m") | L20: =IFERROR(MEDIAN(L9:L17),"n/m") | M20: =IFERROR(MEDIAN(M9:M17),"n/m") | ... P20: =IFERROR(MEDIAN(P9:P17),"n/m") | Q20: =MEDIAN(Q9:Q10) | R20: Median used as target reference = RBA (OPENLANE blank); LKQ and Copart excluded. Stats in F:P reflect Copart row only.
C21: Mean | F21: =IFERROR(AVERAGE(F9:F17),"n/m") | G21: =IFERROR(AVERAGE(G9:G17),"n/m") | H21: =IFERROR(AVERAGE(H9:H17),"n/m") | I21: =IFERROR(AVERAGE(I9:I17),"n/m") | J21: =IFERROR(AVERAGE(J9:J17),"n/m") | K21: =IFERROR(AVERAGE(K9:K17),"n/m") | L21: =IFERROR(AVERAGE(L9:L17),"n/m") | M21: =IFERROR(AVERAGE(M9:M17),"n/m") | ... P21: =IFERROR(AVERAGE(P9:P17),"n/m")
C22: Max | F22: =IFERROR(MAX(F12:F17),"n/m") | G22: =IFERROR(MAX(G12:G17),"n/m") | H22: =IFERROR(MAX(H12:H17),"n/m") | I22: =IFERROR(MAX(I12:I17),"n/m") | J22: =IFERROR(MAX(J12:J17),"n/m") | K22: =IFERROR(MAX(K12:K17),"n/m") | L22: =IFERROR(MAX(L12:L17),"n/m") | M22: =IFERROR(MAX(M12:M17),"n/m") | ... P22: =IFERROR(MAX(P12:P17),"n/m")
A26: X | C26: Precedent Transactions | D26: Acquirer | E26: Close Date | F26: Valuation | H26: Financials ($MM's) | K26: Growth / Profitability (%) | N26: Valuation Multiples (x)
F27: EV | G27: Equity Value | H27: Revenue | I27: EBITDA | J27: Net Income | K27: Y/Y Growth | L27: EBITDA Margin | M27: Profit Margin | N27: EV / Revenue | O27: EV / EBITDA | P27: P/E
C28: IAA, Inc. | D28: Ritchie Bros. (RB Global) | E28: Mar 2023 (announced 11/7/2022) | F28: 7300 | G28: n/m | I28: =F28/13.6 | J28: n/m | K28: n/m | L28: =IFERROR(I28/$H28,"n/m") | M28: =IFERROR(J28/$H28,"n/m") | N28: =IFERROR($F28/H28,"n/m") | O28: =IFERROR($F28/I28,"n/m") | P28: n/m | R28: RBA 8-K 11/7/2022: ~$7.3B incl. $1.0B net debt; 13.6x LTM Adj. EBITDA. Revenue not loaded. https://www.sec.gov/Archives/edgar/data/1046102/000110465922115108/tm2229848d1_ex99-1.htm
C29: ACV Auctions | D29: Copart | E29: Pending (by CY-end 2026) | G29: 1900 | J29: n/m | K29: n/m | L29: =IFERROR(I29/$H29,"n/m") | M29: =IFERROR(J29/$H29,"n/m") | N29: =IFERROR($F29/H29,"n/m") | O29: =IFERROR($F29/I29,"n/m") | P29: n/m | R29: 8-K 9/10/2026: $10.50/sh cash, ~$1.9B equity value. EV and profit measure not disclosed - multiples left blank.
G30: n/m | J30: n/m | K30: n/m | L30: =IFERROR(I30/$H30,"n/m") | M30: =IFERROR(J30/$H30,"n/m") | N30: =IFERROR($F30/H30,"n/m") | O30: =IFERROR($F30/I30,"n/m") | P30: n/m
G31: n/m | J31: n/m | K31: n/m | L31: =IFERROR(I31/$H31,"n/m") | M31: =IFERROR(J31/$H31,"n/m") | N31: =IFERROR($F31/H31,"n/m") | O31: =IFERROR($F31/I31,"n/m") | P31: n/m
G32: n/m | J32: n/m | K32: n/m | L32: =IFERROR(I32/$H32,"n/m") | M32: =IFERROR(J32/$H32,"n/m") | N32: =IFERROR($F32/H32,"n/m") | O32: =IFERROR($F32/I32,"n/m") | P32: n/m
G33: n/m | J33: n/m | K33: n/m | L33: =IFERROR(I33/$H33,"n/m") | M33: =IFERROR(J33/$H33,"n/m") | N33: =IFERROR($F33/H33,"n/m") | O33: =IFERROR($F33/I33,"n/m") | P33: n/m
G34: n/m | J34: n/m | K34: n/m | L34: =IFERROR(I34/$H34,"n/m") | M34: =IFERROR(J34/$H34,"n/m") | N34: =IFERROR($F34/H34,"n/m") | O34: =IFERROR($F34/I34,"n/m") | P34: n/m
G35: n/m | J35: n/m | K35: n/m | L35: =IFERROR(I35/$H35,"n/m") | M35: =IFERROR(J35/$H35,"n/m") | N35: =IFERROR($F35/H35,"n/m") | O35: =IFERROR($F35/I35,"n/m") | P35: n/m
G36: n/m | J36: n/m | K36: n/m | L36: =IFERROR(I36/$H36,"n/m") | M36: =IFERROR(J36/$H36,"n/m") | N36: =IFERROR($F36/H36,"n/m") | O36: =IFERROR($F36/I36,"n/m") | P36: n/m
C38: Minimum | F38: =IFERROR(MIN(F28:F36),"n/m") | G38: n/m | H38: =IFERROR(MIN(H28:H36),"n/m") | I38: =IFERROR(MIN(I28:I36),"n/m") | J38: n/m | K38: n/m | L38: =IFERROR(MIN(L28:L36),"n/m") | M38: n/m | N38: =IFERROR(MIN(N28:N36),"n/m") | O38: =IFERROR(MIN(O28:O36),"n/m") | P38: n/m
C39: Median | F39: =IFERROR(MEDIAN(F28:F36),"n/m") | G39: n/m | H39: =IFERROR(MEDIAN(H28:H36),"n/m") | I39: =IFERROR(MEDIAN(I28:I36),"n/m") | J39: n/m | K39: n/m | L39: =IFERROR(MEDIAN(L28:L36),"n/m") | M39: n/m | N39: =IFERROR(MEDIAN(N28:N36),"n/m") | O39: =IFERROR(MEDIAN(O28:O36),"n/m") | P39: n/m
C40: Mean | F40: =IFERROR(AVERAGE(F28:F36),"n/m") | G40: n/m | H40: =IFERROR(AVERAGE(H28:H36),"n/m") | I40: =IFERROR(AVERAGE(I28:I36),"n/m") | J40: n/m | K40: n/m | L40: =IFERROR(AVERAGE(L28:L36),"n/m") | M40: n/m | N40: =IFERROR(AVERAGE(N28:N36),"n/m") | O40: =IFERROR(AVERAGE(O28:O36),"n/m") | P40: n/m
C41: Max | F41: =IFERROR(MAX(F31:F36),"n/m") | G41: n/m | H41: =IFERROR(MAX(H31:H36),"n/m") | I41: =IFERROR(MAX(I31:I36),"n/m") | J41: n/m | K41: n/m | L41: =IFERROR(MAX(L31:L36),"n/m") | M41: n/m | N41: =IFERROR(MAX(N31:N36),"n/m") | O41: =IFERROR(MAX(O31:O36),"n/m") | P41: n/m

Sheet LBO
J1: Exit Year Calc: | K1: 1 | L1: =K1+1 | M1: =L1+1 | N1: =M1+1 | O1: =N1+1 | P1: =O1+1
C3: ='Financial Model'!C3
A4: X | C4: LBO Assumptions
C5: ='Financial Model'!C5
C7: Transaction Assumptions | I7: Deal Financing | O7: Purchase Price
C9: Entry EBITDA Multiple | G9: =T27/K64 | K9: Funded | L9: Interest | M9: Annual | N9: CF Sweep | P9: Pricing Method | T9: Multiple | V9: Sponsor-bid floor: $27.36, 0% premium. Entry multiple is solved from that bid (Multiple and Premium builds give the same price). Cash is after the $1.9B ACV payment. Exit 11.1x = memo trading multiple. Not the price target.
C10: Transaction Fee | G10: 0.01 | K10: At Close | L10: Rate | M10: Amort. | N10: Priority
C11: Debt Issuance Fee | G11: 0.005 | I11: =C17 | K11: =G17*$K$64 | L11: 0.06 | M11: 0 | N11: 1 | P11: (a) Multiple-Based Build (Traditional LBO)
I12: =C18 | K12: =G18*$K$64 | L12: 0.08 | M12: 0.05 | N12: 2 | P12: Entry EBITDA Multiple | T12: =G9
C13: Minimum Cash to BS | G13: 500 | I13: =C19 | K13: =G19*$K$64 | L13: 0.12 | M13: 0.01 | N13: n/a | P13: x Closing LTM EBITDA | T13: =K64
C14: Existing Cash from BS | G14: ='Financial Model'!J136+Drivers!K171 | I14: =C21 | K14: =G21*(N36-G30-G31-G32-G33) | L14: n/a | M14: n/a | N14: n/a | P14: Enterprise Value (Multiple Method) | T14: =T12*T13
I15: Sponsor Equity | K15: =G35 | L15: n/a | M15: n/a | N15: n/a | P15: (-) Existing Debt | T15: =-SUM('Financial Model'!J75:J77)
C16: Total Leverage (x EBITDA) | G16: 3 | I16: Total / Wtd. | K16: =SUM(K11:K15) | L16: =IFERROR(SUMPRODUCT(K11:K13,L11:L13)/SUM(K11:K13),0) | M16: =IFERROR(SUMPRODUCT(K11:K13,M11:M13)/SUM(K11:K13),0) | P16: (+) Existing Cash | T16: ='Financial Model'!J136+Drivers!K171
C17: Revolver | G17: 1 | P17: Equity Purchase Price | T17: =SUM(T14:T16)
C18: Term Loan B | G18: 1
C19: Mezzanine | G19: =G16-SUM(G17:G18) | P19: (b) Purchase Premium Build (Take-Private)
P20: Unaffected Share Price ($) | T20: =Support!$D$4
C21: Management Rollover | G21: 0.05 | P21: x (1 + Purchase Premium) | T21: 0
P22: Offer Price Per Share | T22: =T20*(1+T21)
C23: Tax Rate | G23: =L76 | P23: x Fully-Diluted Shares O/S (mm) | T23: =Support!$D$6
P24: Equity Purchase Price | T24: =T22*T23
C25: Exit Multiple (x EBITDA) | G25: 11.1 | P25: (+) Existing Debt | T25: =SUM('Financial Model'!J75:J77)
C26: Exit Year (Hold Period) | G26: 5 | P26: (-) Existing Cash | T26: =-('Financial Model'!J50+Drivers!K171)
P27: Enterprise Value (Purchase Premium Build) | T27: =T24+SUM(T25:T26)
C28: Sources & Uses
P29: Active Equity Purchase Price | T29: =IF($T$9="Premium",T24,T17)
C30: =I11 | G30: =K11 | J30: Equity Purchase Price | N30: =T29 | P30: Active Enterprise Value | T30: =IF($T$9="Premium",T27,T14)
C31: =I12 | G31: =K12 | J31: Refinance Existing Debt | N31: =SUM('Financial Model'!J75:J76) | P31: Implied EV/EBITDA Multiple | T31: =T30/K64
C32: =I13 | G32: =K13 | J32: Transaction Fees | N32: =T34 | P32: (+) Debt Refinancing | T32: =N31
C33: =C14 | G33: =G14 | J33: Financing Fees | N33: =T33 | P33: (+) Transaction Fees | T33: =G10*T30
C34: =I14 | G34: =K14 | J34: Min. Cash to BS. | N34: =G13 | P34: (+) Financing Fees | T34: =G11*T30
C35: =I15 | G35: =G36-SUM(G30:G34) | P35: (+) Min. Cash to BS | T35: =G13
C36: Total Sources | G36: =N36 | J36: Total Uses | N36: =SUM(N30:N35) | P36: Total Investment | T36: =SUM(T33:T35,T30)
C40: ='Financial Model'!C3
A41: X | C41: LBO Model | J41: ='Financial Model'!J4
C42: ='Financial Model'!C5 | G42: ='Financial Model'!G5 | H42: ='Financial Model'!H5 | I42: ='Financial Model'!I5 | J42: ='Financial Model'!J5 | K42: ='Financial Model'!K5 | L42: ='Financial Model'!L5 | M42: ='Financial Model'!M5 | N42: ='Financial Model'!N5 | ... T42: ='Financial Model'!T5
C44: ='Financial Model'!C7 | G44: ='Financial Model'!G7 | H44: ='Financial Model'!H7 | I44: ='Financial Model'!I7 | J44: ='Financial Model'!J7 | K44: ='Financial Model'!K7 | L44: ='Financial Model'!L7 | M44: ='Financial Model'!M7 | N44: ='Financial Model'!N7 | ... T44: ='Financial Model'!T7
C45: ='Financial Model'!C8 | G45: ='Financial Model'!G8 | H45: ='Financial Model'!H8 | I45: ='Financial Model'!I8 | J45: ='Financial Model'!J8 | K45: ='Financial Model'!K8 | L45: ='Financial Model'!L8 | M45: ='Financial Model'!M8 | N45: ='Financial Model'!N8 | ... T45: ='Financial Model'!T8
C46: ='Financial Model'!C9 | G46: ='Financial Model'!G9 | H46: ='Financial Model'!H9 | I46: ='Financial Model'!I9 | J46: ='Financial Model'!J9 | K46: ='Financial Model'!K9 | L46: ='Financial Model'!L9 | M46: ='Financial Model'!M9 | N46: ='Financial Model'!N9 | ... T46: ='Financial Model'!T9
C47: ='Financial Model'!C10 | G47: ='Financial Model'!G10 | H47: ='Financial Model'!H10 | I47: ='Financial Model'!I10 | J47: ='Financial Model'!J10 | K47: ='Financial Model'!K10 | L47: ='Financial Model'!L10 | M47: ='Financial Model'!M10 | N47: ='Financial Model'!N10 | ... T47: ='Financial Model'!T10
C49: ='Financial Model'!C12 | G49: ='Financial Model'!G12 | H49: ='Financial Model'!H12 | I49: ='Financial Model'!I12 | J49: ='Financial Model'!J12 | K49: ='Financial Model'!K12 | L49: ='Financial Model'!L12 | M49: ='Financial Model'!M12 | N49: ='Financial Model'!N12 | ... T49: ='Financial Model'!T12
C50: ='Financial Model'!C13 | G50: ='Financial Model'!G13 | H50: ='Financial Model'!H13 | I50: ='Financial Model'!I13 | J50: ='Financial Model'!J13 | K50: ='Financial Model'!K13 | L50: ='Financial Model'!L13 | M50: ='Financial Model'!M13 | N50: ='Financial Model'!N13 | ... T50: ='Financial Model'!T13
C51: ='Financial Model'!C14 | G51: ='Financial Model'!G14 | H51: ='Financial Model'!H14 | I51: ='Financial Model'!I14 | J51: ='Financial Model'!J14 | K51: ='Financial Model'!K14 | L51: ='Financial Model'!L14 | M51: ='Financial Model'!M14 | N51: ='Financial Model'!N14 | ... T51: ='Financial Model'!T14
C53: ='Financial Model'!C16 | G53: ='Financial Model'!G16 | H53: ='Financial Model'!H16 | I53: ='Financial Model'!I16 | J53: ='Financial Model'!J16 | K53: ='Financial Model'!K16 | L53: ='Financial Model'!L16 | M53: ='Financial Model'!M16 | N53: ='Financial Model'!N16 | ... T53: ='Financial Model'!T16
C54: ='Financial Model'!C17 | G54: ='Financial Model'!G17 | H54: ='Financial Model'!H17 | I54: ='Financial Model'!I17 | J54: ='Financial Model'!J17 | K54: ='Financial Model'!K17 | L54: ='Financial Model'!L17 | M54: ='Financial Model'!M17 | N54: ='Financial Model'!N17 | ... T54: ='Financial Model'!T17
C55: ='Financial Model'!C18 | G55: ='Financial Model'!G18 | H55: ='Financial Model'!H18 | I55: ='Financial Model'!I18 | J55: ='Financial Model'!J18 | K55: ='Financial Model'!K18 | L55: ='Financial Model'!L18 | M55: ='Financial Model'!M18 | N55: ='Financial Model'!N18 | ... T55: ='Financial Model'!T18
C56: ='Financial Model'!C19 | G56: ='Financial Model'!G19 | H56: ='Financial Model'!H19 | I56: ='Financial Model'!I19 | J56: ='Financial Model'!J19 | K56: ='Financial Model'!K19 | L56: ='Financial Model'!L19 | M56: ='Financial Model'!M19 | N56: ='Financial Model'!N19 | ... T56: ='Financial Model'!T19
... C69: ='Financial Model'!C32 | G69: ='Financial Model'!G32 | H69: ='Financial Model'!H32 | I69: ='Financial Model'!I32 | J69: ='Financial Model'!J32 | K69: ='Financial Model'!K32 | L69: ='Financial Model'!L32 | M69: ='Financial Model'!M32 | N69: ='Financial Model'!N32 | ... T69: ='Financial Model'!T32
C71: ='Financial Model'!C34 | G71: ='Financial Model'!G34 | H71: ='Financial Model'!H34 | I71: ='Financial Model'!I34 | J71: ='Financial Model'!J34 | K71: =K129 | L71: =L129 | M71: =M129 | N71: =N129 | O71: =O129 | P71: =P129 | Q71: =Q129 | R71: =R129 | ... T71: =T129
C72: ='Financial Model'!C35 | G72: ='Financial Model'!G35 | H72: ='Financial Model'!H35 | I72: ='Financial Model'!I35 | J72: ='Financial Model'!J35 | K72: ='Financial Model'!K35 | L72: ='Financial Model'!L35 | M72: ='Financial Model'!M35 | N72: ='Financial Model'!N35 | ... T72: ='Financial Model'!T35
C73: ='Financial Model'!C36 | G73: ='Financial Model'!G36 | H73: ='Financial Model'!H36 | I73: ='Financial Model'!I36 | J73: ='Financial Model'!J36 | K73: =K69-SUM(K71:K72) | L73: =L69-SUM(L71:L72) | M73: =M69-SUM(M71:M72) | N73: =N69-SUM(N71:N72) | O73: =O69-SUM(O71:O72) | P73: =P69-SUM(P71:P72) | Q73: =Q69-SUM(Q71:Q72) | R73: =R69-SUM(R71:R72) | ... T73: =T69-SUM(T71:T72)
C75: ='Financial Model'!C38 | G75: ='Financial Model'!G38 | H75: ='Financial Model'!H38 | I75: ='Financial Model'!I38 | J75: ='Financial Model'!J38 | K75: =K76*K73 | L75: =L76*L73 | M75: =M76*M73 | N75: =N76*N73 | O75: =O76*O73 | P75: =P76*P73 | Q75: =Q76*Q73 | R75: =R76*R73 | ... T75: =T76*T73
C76: ='Financial Model'!C39 | G76: ='Financial Model'!G39 | H76: ='Financial Model'!H39 | I76: ='Financial Model'!I39 | J76: ='Financial Model'!J39 | K76: ='Financial Model'!K39 | L76: ='Financial Model'!L39 | M76: ='Financial Model'!M39 | N76: ='Financial Model'!N39 | ... T76: ='Financial Model'!T39
C78: ='Financial Model'!C41 | G78: ='Financial Model'!G41 | H78: ='Financial Model'!H41 | I78: ='Financial Model'!I41 | J78: ='Financial Model'!J41 | K78: =K73-K75 | L78: =L73-L75 | M78: =M73-M75 | N78: =N73-N75 | O78: =O73-O75 | P78: =P73-P75 | Q78: =Q73-Q75 | R78: =R73-R75 | ... T78: =T73-T75
C79: ='Financial Model'!C42 | G79: ='Financial Model'!G42 | H79: ='Financial Model'!H42 | I79: ='Financial Model'!I42 | J79: ='Financial Model'!J42 | K79: =K78/K46 | L79: =L78/L46 | M79: =M78/M46 | N79: =N78/N46 | O79: =O78/O46 | P79: =P78/P46 | Q79: =Q78/Q46 | R79: =R78/R46 | ... T79: =T78/T46
C81: (+) D&A | G81: =SUM(G67:G68) | H81: =SUM(H67:H68) | I81: =SUM(I67:I68) | J81: =SUM(J67:J68) | K81: =SUM(K67:K68) | L81: =SUM(L67:L68) | M81: =SUM(M67:M68) | N81: =SUM(N67:N68) | ... T81: =SUM(T67:T68)
C82: (-) Change in NWC | G82: ='Financial Model'!G114 | H82: ='Financial Model'!H114 | I82: ='Financial Model'!I114 | J82: ='Financial Model'!J114 | K82: ='Financial Model'!K114 | L82: ='Financial Model'!L114 | M82: ='Financial Model'!M114 | N82: ='Financial Model'!N114 | ... T82: ='Financial Model'!T114
C83: (-) Capex | G83: ='Financial Model'!G121 | H83: ='Financial Model'!H121 | I83: ='Financial Model'!I121 | J83: ='Financial Model'!J121 | K83: ='Financial Model'!K118+'Financial Model'!K120 | L83: ='Financial Model'!L118+'Financial Model'!L120 | M83: ='Financial Model'!M118+'Financial Model'!M120 | N83: ='Financial Model'!N118+'Financial Model'!N120 | O83: ='Financial Model'!O118+'Financial Model'!O120 | P83: ='Financial Model'!P118+'Financial Model'!P120 | Q83: ='Financial Model'!Q118+'Financial Model'!Q120 | R83: ='Financial Model'!R118+'Financial Model'!R120 | ... T83: ='Financial Model'!T118+'Financial Model'!T120
C84: Cash Flow Available for Debt Service | G84: =SUM(G81:G83) | H84: =SUM(H81:H83) | I84: =SUM(I81:I83) | J84: =SUM(J81:J83) | K84: =SUM(K81:K83) | L84: =SUM(L81:L83) | M84: =SUM(M81:M83) | N84: =SUM(N81:N83) | ... T84: =SUM(T81:T83)
C88: ='Financial Model'!C3
A89: X | C89: Debt Schedule | J89: ='Financial Model'!J4
C90: ='Financial Model'!C5 | G90: ='Financial Model'!G5 | H90: ='Financial Model'!H5 | I90: ='Financial Model'!I5 | J90: ='Financial Model'!J5 | K90: ='Financial Model'!K5 | L90: ='Financial Model'!L5 | M90: ='Financial Model'!M5 | N90: ='Financial Model'!N5 | ... T90: ='Financial Model'!T5
C92: =C84 | K92: =K84 | L92: =L84 | M92: =M84 | N92: =N84 | O92: =O84 | P92: =P84 | Q92: =Q84 | R92: =R84 | ... T92: =T84
C93: (-) Mandatory Amortization | K93: =K128 | L93: =L128 | M93: =M128 | N93: =N128 | O93: =O128 | P93: =P128 | Q93: =Q128 | R93: =R128 | ... T93: =T128
C94: Cash Flow Available for Sweep | K94: =SUM(K92:K93) | L94: =SUM(L92:L93) | M94: =SUM(M92:M93) | N94: =SUM(N92:N93) | O94: =SUM(O92:O93) | P94: =SUM(P92:P93) | Q94: =SUM(Q92:Q93) | R94: =SUM(R92:R93) | ... T94: =SUM(T92:T93)
C96: ="(-) Sweep to "&C105 | K96: =IF(K94>=0,-MIN(K94,K106),-K94) | L96: =IF(L94>=0,-MIN(L94,L106),-L94) | M96: =IF(M94>=0,-MIN(M94,M106),-M94) | N96: =IF(N94>=0,-MIN(N94,N106),-N94) | O96: =IF(O94>=0,-MIN(O94,O106),-O94) | P96: =IF(P94>=0,-MIN(P94,P106),-P94) | Q96: =IF(Q94>=0,-MIN(Q94,Q106),-Q94) | R96: =IF(R94>=0,-MIN(R94,R106),-R94) | ... T96: =IF(T94>=0,-MIN(T94,T106),-T94)
C97: ="Cash Remaining After "&C105 | K97: =SUM(K94:K96) | L97: =SUM(L94:L96) | M97: =SUM(M94:M96) | N97: =SUM(N94:N96) | O97: =SUM(O94:O96) | P97: =SUM(P94:P96) | Q97: =SUM(Q94:Q96) | R97: =SUM(R94:R96) | ... T97: =SUM(T94:T96)
C99: ="(-) Sweep to "&C111 | K99: =-MIN(K97,K112+K113) | L99: =-MIN(L97,L112+L113) | M99: =-MIN(M97,M112+M113) | N99: =-MIN(N97,N112+N113) | O99: =-MIN(O97,O112+O113) | P99: =-MIN(P97,P112+P113) | Q99: =-MIN(Q97,Q112+Q113) | R99: =-MIN(R97,R112+R113) | ... T99: =-MIN(T97,T112+T113)
C100: ="Cash Remaining After "&C111 | K100: =SUM(K97:K99) | L100: =SUM(L97:L99) | M100: =SUM(M97:M99) | N100: =SUM(N97:N99) | O100: =SUM(O97:O99) | P100: =SUM(P97:P99) | Q100: =SUM(Q97:Q99) | R100: =SUM(R97:R99) | ... T100: =SUM(T97:T99)
C102: ="(-) Sweep to "&C118 | K102: =-MIN(K100,K119+K120) | L102: =-MIN(L100,L119+L120) | M102: =-MIN(M100,M119+M120) | N102: =-MIN(N100,N119+N120) | O102: =-MIN(O100,O119+O120) | P102: =-MIN(P100,P119+P120) | Q102: =-MIN(Q100,Q119+Q120) | R102: =-MIN(R100,R119+R120) | ... T102: =-MIN(T100,T119+T120)
C103: Excess Cash to BS | K103: =SUM(K100:K102) | L103: =SUM(L100:L102) | M103: =SUM(M100:M102) | N103: =SUM(N100:N102) | O103: =SUM(O100:O102) | P103: =SUM(P100:P102) | Q103: =SUM(Q100:Q102) | R103: =SUM(R100:R102) | ... T103: =SUM(T100:T102)
C105: =I11
C106: Beginning Balance | K106: =K11 | L106: =K108 | M106: =L108 | N106: =M108 | O106: =N108 | P106: =O108 | Q106: =P108 | R106: =Q108 | S106: =R108 | T106: =S108
C107: (-) Cash Sweep / (+) Draw | K107: =K96 | L107: =L96 | M107: =M96 | N107: =N96 | O107: =O96 | P107: =P96 | Q107: =Q96 | R107: =R96 | ... T107: =T96
C108: Ending Balance | K108: =MAX(0,K106+K107) | L108: =MAX(0,L106+L107) | M108: =MAX(0,M106+M107) | N108: =MAX(0,N106+N107) | O108: =MAX(0,O106+O107) | P108: =MAX(0,P106+P107) | Q108: =MAX(0,Q106+Q107) | R108: =MAX(0,R106+R107) | ... T108: =MAX(0,T106+T107)
C109: =" "&C105&" Interest Expense" | K109: =AVERAGE(K106,K108)*$L$11 | L109: =AVERAGE(L106,L108)*$L$11 | M109: =AVERAGE(M106,M108)*$L$11 | N109: =AVERAGE(N106,N108)*$L$11 | O109: =AVERAGE(O106,O108)*$L$11 | P109: =AVERAGE(P106,P108)*$L$11 | Q109: =AVERAGE(Q106,Q108)*$L$11 | R109: =AVERAGE(R106,R108)*$L$11 | ... T109: =AVERAGE(T106,T108)*$L$11
C111: =I12
C112: Beginning Balance | K112: =K12 | L112: =K115 | M112: =L115 | N112: =M115 | O112: =N115 | P112: =O115 | Q112: =P115 | R112: =Q115 | S112: =R115 | T112: =S115
C113: (-) Mandatory Amortization | K113: =-MIN($K$12*$M$12,K112) | L113: =-MIN($K$12*$M$12,L112) | M113: =-MIN($K$12*$M$12,M112) | N113: =-MIN($K$12*$M$12,N112) | O113: =-MIN($K$12*$M$12,O112) | P113: =-MIN($K$12*$M$12,P112) | Q113: =-MIN($K$12*$M$12,Q112) | R113: =-MIN($K$12*$M$12,R112) | ... T113: =-MIN($K$12*$M$12,T112)
C114: (-) Cash Sweep | K114: =K99 | L114: =L99 | M114: =M99 | N114: =N99 | O114: =O99 | P114: =P99 | Q114: =Q99 | R114: =R99 | ... T114: =T99
C115: Ending Balance | K115: =SUM(K112:K114) | L115: =SUM(L112:L114) | M115: =SUM(M112:M114) | N115: =SUM(N112:N114) | O115: =SUM(O112:O114) | P115: =SUM(P112:P114) | Q115: =SUM(Q112:Q114) | R115: =SUM(R112:R114) | ... T115: =SUM(T112:T114)
C116: =" "&C111&" Interest Expense" | K116: =AVERAGE(K112,K115)*$L$12 | L116: =AVERAGE(L112,L115)*$L$12 | M116: =AVERAGE(M112,M115)*$L$12 | N116: =AVERAGE(N112,N115)*$L$12 | O116: =AVERAGE(O112,O115)*$L$12 | P116: =AVERAGE(P112,P115)*$L$12 | Q116: =AVERAGE(Q112,Q115)*$L$12 | R116: =AVERAGE(R112,R115)*$L$12 | ... T116: =AVERAGE(T112,T115)*$L$12
C118: =I13
C119: Beginning Balance | K119: =K13 | L119: =K122 | M119: =L122 | N119: =M122 | O119: =N122 | P119: =O122 | Q119: =P122 | R119: =Q122 | S119: =R122 | T119: =S122
C120: (-) Mandatory Amortization | K120: =-MIN($K$13*$M$13,K119) | L120: =-MIN($K$13*$M$13,L119) | M120: =-MIN($K$13*$M$13,M119) | N120: =-MIN($K$13*$M$13,N119) | O120: =-MIN($K$13*$M$13,O119) | P120: =-MIN($K$13*$M$13,P119) | Q120: =-MIN($K$13*$M$13,Q119) | R120: =-MIN($K$13*$M$13,R119) | ... T120: =-MIN($K$13*$M$13,T119)
C121: (-) Cash Sweep | K121: =K102 | L121: =L102 | M121: =M102 | N121: =N102 | O121: =O102 | P121: =P102 | Q121: =Q102 | R121: =R102 | ... T121: =T102
C122: Ending Balance | K122: =SUM(K119:K121) | L122: =SUM(L119:L121) | M122: =SUM(M119:M121) | N122: =SUM(N119:N121) | O122: =SUM(O119:O121) | P122: =SUM(P119:P121) | Q122: =SUM(Q119:Q121) | R122: =SUM(R119:R121) | ... T122: =SUM(T119:T121)
C123: =" "&C118&" Interest Expense" | K123: =AVERAGE(K119,K122)*$L$13 | L123: =AVERAGE(L119,L122)*$L$13 | M123: =AVERAGE(M119,M122)*$L$13 | N123: =AVERAGE(N119,N122)*$L$13 | O123: =AVERAGE(O119,O122)*$L$13 | P123: =AVERAGE(P119,P122)*$L$13 | Q123: =AVERAGE(Q119,Q122)*$L$13 | R123: =AVERAGE(R119,R122)*$L$13 | ... T123: =AVERAGE(T119,T122)*$L$13
C125: Total Beginning Debt | K125: =SUM(K119,K112,K106) | L125: =SUM(L119,L112,L106) | M125: =SUM(M119,M112,M106) | N125: =SUM(N119,N112,N106) | O125: =SUM(O119,O112,O106) | P125: =SUM(P119,P112,P106) | Q125: =SUM(Q119,Q112,Q106) | R125: =SUM(R119,R112,R106) | ... T125: =SUM(T119,T112,T106)
C126: Total Ending Debt | K126: =SUM(K122,K115,K108) | L126: =SUM(L122,L115,L108) | M126: =SUM(M122,M115,M108) | N126: =SUM(N122,N115,N108) | O126: =SUM(O122,O115,O108) | P126: =SUM(P122,P115,P108) | Q126: =SUM(Q122,Q115,Q108) | R126: =SUM(R122,R115,R108) | ... T126: =SUM(T122,T115,T108)
C128: Total Mandatory Amortization | K128: =SUM(K120,K113) | L128: =SUM(L120,L113) | M128: =SUM(M120,M113) | N128: =SUM(N120,N113) | O128: =SUM(O120,O113) | P128: =SUM(P120,P113) | Q128: =SUM(Q120,Q113) | R128: =SUM(R120,R113) | ... T128: =SUM(T120,T113)
C129: Total Interest Expense | K129: =SUM(K123,K116,K109) | L129: =SUM(L123,L116,L109) | M129: =SUM(M123,M116,M109) | N129: =SUM(N123,N116,N109) | O129: =SUM(O123,O116,O109) | P129: =SUM(P123,P116,P109) | Q129: =SUM(Q123,Q116,Q109) | R129: =SUM(R123,R116,R109) | ... T129: =SUM(T123,T116,T109)
C133: ='Financial Model'!C3
A134: X | C134: Covenant Compliance | J134: ='Financial Model'!J4
C135: ='Financial Model'!C5 | G135: ='Financial Model'!G5 | H135: ='Financial Model'!H5 | I135: ='Financial Model'!I5 | J135: ='Financial Model'!J5 | K135: ='Financial Model'!K5 | L135: ='Financial Model'!L5 | M135: ='Financial Model'!M5 | N135: ='Financial Model'!N5 | ... T135: ='Financial Model'!T5
C137: Net Leverage Ratio (Net Debt / EBITDA) | K137: =K126/K64 | L137: =L126/L64 | M137: =M126/M64 | N137: =N126/N64 | O137: =O126/O64 | P137: =P126/P64 | Q137: =Q126/Q64 | R137: =R126/R64 | ... T137: =T126/T64
C138: Maximum Net Leverage Covenant | K138: 5 | L138: 5 | M138: 5 | N138: 5 | O138: 5 | P138: 5 | Q138: 5 | R138: 5 | S138: 5 | T138: 5
C139: Compliance | K139: =IF(K137<=K138,"PASS","FAIL") | L139: =IF(L137<=L138,"PASS","FAIL") | M139: =IF(M137<=M138,"PASS","FAIL") | N139: =IF(N137<=N138,"PASS","FAIL") | O139: =IF(O137<=O138,"PASS","FAIL") | P139: =IF(P137<=P138,"PASS","FAIL") | Q139: =IF(Q137<=Q138,"PASS","FAIL") | R139: =IF(R137<=R138,"PASS","FAIL") | ... T139: =IF(T137<=T138,"PASS","FAIL")
C141: Interest Coverage (EBITDA / Interest) | K141: =K64/K129 | L141: =L64/L129 | M141: =M64/M129 | N141: =N64/N129 | O141: =O64/O129 | P141: =P64/P129 | Q141: =Q64/Q129 | R141: =R64/R129 | ... T141: =T64/T129
C142: Minimum Interest Coverage Covenant | K142: 5 | L142: 5 | M142: 5 | N142: 5 | O142: 5 | P142: 5 | Q142: 5 | R142: 5 | S142: 5 | T142: 5
...

Sheet Source Data ->

Sheet PASTE IN SOURCE DATA HERE

Sheet Support
B2: Copart, Inc. (CPRT) - Support: scenarios, bridges, cross-checks ($ in millions except per share)
B3: Valuation date and market data (September 30, 2026)
B4: Share price ($) | D4: 27.36 | J4: Memo / Yahoo Finance close 9/30/2026
B5: Market cap ($M) | D5: 25300 | J5: Memo: $25.3B on 9/30/2026
B6: Shares outstanding implied (M) | D6: =D5/D4 | J6: Derived = market cap / price. 10-K cover count not pulled; Q4 FY26 basic W.A. was 927.1M.
B7: Cash & securities, FY26 ($M) | D7: ='Financial Model'!J50 | J7: Cash, equivalents, restricted cash + HTM securities (memo $4.5B)
B8: Debt (revolver + term loan), FY26 | D8: =SUM('Financial Model'!J75:J76) | J8: No debt outstanding; finance leases not separately disclosed on the balance sheet (immaterial) and sit in lease liabilities
B9: Enterprise value ($M) | D9: =D5+D8-D7 | J9: Memo date EV
B10: Street FY27 EPS ($) - reference only, not a driver | D10: 1.75 | J10: Memo / Yahoo consensus 9/30/2026
B11: Later price print ($) | D11: 27.35 | J11: Motley Fool quote widget, retrieved 10/2/2026. Target downside is measured vs $27.36.
B12: ACV cash consideration ($M) - used in model | D12: 1900 | J12: 8-K Ex.99.1 9/10/2026: $10.50/sh, implied equity value ~$1.9B. Memo says ~$1.8B: filing wins. https://www.sec.gov/Archives/edgar/data/900075/000119312526388064/d138322dex991.htm
B13: ACV consideration per memo ($M) | D13: 1800 | J13: Memo (footnoted; not used)
B14: Published price target ($) | D14: 21.5 | J14: Memo headline. Memo Exhibit 2 prints $21.54; 15 x model EPS is in D36/E36.
B15: Exhibit 2 - FY27E scenarios (switch drives the three statements via Drivers)
B16: Scenario switch (1 = Bear, 2 = Base, 3 = Bull) | D16: 2 | J16: Base selected = printed case. Recommendation remains short at $21.50.
D18: Bear | E18: Base | F18: Bull | G18: Live
B19: Probability | D19: 0.25 | E19: 0.5 | F19: 0.25
B20: Units growth | D20: -0.06 | E20: -0.03 | F20: 0.02 | G20: =INDEX(D20:F20,1,$D$16)
B21: Revenue per unit growth | D21: 0.03 | E21: 0.04 | F21: 0.05 | G21: =INDEX(D21:F21,1,$D$16)
B22: Operating margin | D22: 0.31 | E22: 0.33 | F22: 0.365 | G22: =INDEX(D22:F22,1,$D$16)
B23: Other / interest income ($M) | D23: 110 | E23: 110 | F23: 110 | G23: =INDEX(D23:F23,1,$D$16)
B24: P/E multiple (x) | D24: 13 | E24: 15 | F24: 20 | G24: =INDEX(D24:F24,1,$D$16)
B25: Tax rate (FY24-FY26 average) | D25: =Drivers!$K$75 | E25: =Drivers!$K$75 | F25: =Drivers!$K$75
B26: Service revenue | D26: ='Financial Model'!$J$7*(1+D20)*(1+D21) | E26: ='Financial Model'!$J$7*(1+E20)*(1+E21) | F26: ='Financial Model'!$J$7*(1+F20)*(1+F21)
B27: Vehicle sales | D27: ='Financial Model'!$J$8*(1+D20)*(1+D21) | E27: ='Financial Model'!$J$8*(1+E20)*(1+E21) | F27: ='Financial Model'!$J$8*(1+F20)*(1+F21)
B28: Total revenue | D28: =D26+D27 | E28: =E26+E27 | F28: =F26+F27 | G28: ='Financial Model'!K9
B29: Operating income | D29: =D28*D22 | E29: =E28*E22 | F29: =F28*F22 | G29: ='Financial Model'!K32
B30: Pre-tax income | D30: =D29+D23 | E30: =E29+E23 | F30: =F29+F23
B31: Net income | D31: =D30*(1-D25) | E31: =E30*(1-E25) | F31: =F30*(1-F25) | G31: ='Financial Model'!K41
B32: Diluted W.A. shares (M), no FY27E buyback | D32: =Drivers!$J$214+0.5*Drivers!$J$162*D28/$D$4 | E32: =Drivers!$J$214+0.5*Drivers!$J$162*E28/$D$4 | F32: =Drivers!$J$214+0.5*Drivers!$J$162*F28/$D$4 | G32: ='Multiples & Ratios'!K57
B33: FY27E EPS ($) - computed | D33: =D31/D32 | E33: =E31/E32 | F33: =F31/F32 | G33: ='Multiples & Ratios'!K28 | J33: Live column = three-statement model output (Financial Model / Multiples & Ratios). D:F are a closed-form replica so all three scenarios print at once.
B34: FY27E EPS ($) - memo Exhibit 2 | D34: 1.3 | E34: 1.44 | F34: 1.7
B35: Computed less memo ($) | D35: =D33-D34 | E35: =E33-E34 | F35: =F33-F34
B36: Price target ($) = EPS x P/E | D36: =D33*D24 | E36: =E33*E24 | F36: =F33*F24 | G36: =G33*G24
B37: Price target ($) - memo Exhibit 2 | D37: 16.84 | E37: 21.54 | F37: 33.9
B38: Target vs $27.36 | D38: =D36/$D$4-1 | E38: =E36/$D$4-1 | F38: =F36/$D$4-1 | G38: =G36/$D$4-1
B39: EPS vs Street $1.75 | D39: =D33/$D$10-1 | E39: =E33/$D$10-1 | F39: =F33/$D$10-1 | G39: =G33/$D$10-1
B40: Check: live model EPS less scenario-block EPS (must be 0) | G40: =ROUND(G33-INDEX(D33:F33,1,D16),4)
B41: Probability-weighted target ($) - note only | D41: =SUMPRODUCT(D19:F19,D36:F36) | E41: 23.45 | J41: D = computed; E = memo. A note, not the recommendation.
B42: Published target vs $27.36 | D42: =D14/D4-1
B43: FY27E buybacks in live model ($M) | D43: =Drivers!K210 | J43: FY26 buybacks were $1,632.5M; ACV takes $1.9B of that cash.
B45: EPS bridge: FY26A to FY27E (live scenario)
B46: FY26A diluted EPS | D46: ='Multiples & Ratios'!J28
B47: Volume (units) | D47: ='Financial Model'!J9*Drivers!K192*(1-'Financial Model'!$J$39)/'Multiples & Ratios'!$J$57
B48: Price / mix (revenue per unit) | D48: ='Financial Model'!J9*(1+Drivers!K192)*Drivers!K203*(1-'Financial Model'!$J$39)/'Multiples & Ratios'!$J$57
B49: Cost of vehicle sales | D49: =-('Financial Model'!K13-'Financial Model'!J13)*(1-'Financial Model'!$J$39)/'Multiples & Ratios'!$J$57
B50: Facility cost (facility operations + D&A) | D50: =-(('Financial Model'!K12-'Financial Model'!J12)+SUM('Financial Model'!K30:K31)-SUM('Financial Model'!J30:J31))*(1-'Financial Model'!$J$39)/'Multiples & Ratios'!$J$57 | J50: Q4 FY26: revenue per car +5.4% vs US facility cost per car +14.2% (call).
B51: G&A | D51: =-('Financial Model'!K24-'Financial Model'!J24)*(1-'Financial Model'!$J$39)/'Multiples & Ratios'!$J$57
B52: ACV cash: lost interest on $1.9B | D52: =-D12*Drivers!J208*(1-'Financial Model'!$J$39)/'Multiples & Ratios'!$J$57 | J52: Memo: ~$0.06 of EPS before ACV's own losses.
B53: Other interest / other income | D53: =-(('Financial Model'!K34+'Financial Model'!K35)-('Financial Model'!J34+'Financial Model'!J35))*(1-'Financial Model'!$J$39)/'Multiples & Ratios'!$J$57-D52
B54: Tax rate | D54: ='Financial Model'!K36*('Financial Model'!J39-'Financial Model'!K39)/'Multiples & Ratios'!J57
B55: Share count | D55: ='Financial Model'!K41/'Multiples & Ratios'!K57-'Financial Model'!K41/'Multiples & Ratios'!J57
B56: FY27E diluted EPS (bridge) | D56: =SUM(D46:D55)
B57: FY27E diluted EPS (model) | D57: ='Multiples & Ratios'!K28
B58: Check (must be 0) | D58: =ROUND(D56-D57,4)
B61: Share-shift bridge (memo Exhibit 1B): Copart vs IAA, last 12 months
B62: Copart unit growth, FY26 | D62: -0.055 | J62: Q4 FY26 call: fiscal 2026 units sold declined 5.5%
B63: IAA unit growth, last 12 months | D63: 0.054 | J63: Memo (RB Global 10-Q/10-K filings)
B67: Copart share of pool, prior year | D67: 0.639 | J67: Memo Exhibit 1B
B68: Copart units, FY26 (M) | D68: 4 | J68: Memo base: Copart states >4 million units sold (release boilerplate). Floor, not an exact count.
B69: Copart units, prior year (M) | D69: =D68/(1+D62)
B70: Combined pool growth | D70: =(D68+D72)/(D69+D71)-1 | J70: Memo: -1.6%
B71: IAA units, prior year (M, implied) | D71: =D69*(1-D67)/D67 | J71: Implied by memo share
B72: IAA units, current (M, implied) | D72: =D71*(1+D63)
B74: Copart share of pool, current | D74: =D68/(D68+D72) | J74: Memo: 61.4%
B75: Share shift (pts) | D75: =(D74-D67)*100 | J75: Memo: -2.5 to -2.6 pts
B76: Cars lost to share shift (000s) | D76: =(D67*(D68+D72)-D68)*1000 | J76: Memo: ~167k
B77: Service revenue per unit, FY26 ($) | D77: =Drivers!J11 | J77: Service revenues / units
B78: Service revenue lost ($M) | D78: =D76*D77/1000 | J78: Memo: ~$166M, ~4% of service revenue
B79: Share shift at 4.5M Copart units, IAA units fixed (pts) | D79: =(4.5/(4.5+D72)-(4.5/(1+D62))/(4.5/(1+D62)+D71))*100 | J79: Memo: range -2.5 to -2.6 pts across 4.0-4.5M units
B80: Progressive share of salvage sent to IAA | D80: 0.9 | J80: Memo / industry press (~90%)
B82: Consensus comparison (reference only)
B83: Street FY27 EPS | D83: =D10
B84: Model FY27E EPS | D84: =G33
B85: Model vs Street | D85: =D84/D83-1 | J85: Memo: 18% below
B86: Street FY27 growth vs FY26 GAAP EPS | D86: =D83/'Multiples & Ratios'!J28-1 | J86: Memo says +11%; on reported FY26 EPS of $1.55 it is +12.8% (flag).
B87: DCF cross-check (not the price target)
B88: DCF enterprise value | D88: =DCF!P24
B89: Plus: cash & securities after ACV payment | D89: ='Financial Model'!J50+Drivers!K171 | J89: ACV carried at zero value in the DCF (no contribution underwritten)
B90: Less: debt | D90: =-D8
B91: Equity value | D91: =SUM(D88:D90)
B92: Per share ($) | D92: =D91/D6
B93: DCF per share vs $21.50 target | D93: =D92/D14-1 | J93: If beyond +/-15%, see Model Notes
B94: WACC | D94: =DCF!P61
B95: Implied exit EV/EBITDA on FY36E | D95: =DCF!P20/'Financial Model'!T27 | J95: Terminal value / terminal-year EBITDA
B96: Terminal value share of EV | D96: =DCF!P22/DCF!P24
B97: Per share with ACV at cost ($) | D97: =(D91+D12)/D6 | J97: Sensitivity only
B99: Football field ($ per share)
B100: Price, 9/30/2026 | D100: =D4
B101: Copart trailing P/E on memo date (x) | D101: =D4/'Multiples & Ratios'!J28 | J101: Memo 17.6x
B102: Copart EV/EBITDA on memo date (x) | D102: =D9/'Financial Model'!J27 | J102: Model 11.0x vs memo 11.1x (memo appears to use IS D&A captions; model uses CFS D&A per brief)
B103: Target: 15x FY27E EPS (primary) | D103: =E36 | J103: Published $21.50
B104: Bear: 13x | D104: =D36
B105: Bull: 20x | D105: =F36
B106: RBA multiple 16.8x on FY27E EPS | D106: =16.8*E33 | J106: Target is a discount to RBA (gaining the share Copart is losing)
B107: LKQ multiple 7.4x on FY27E EPS (floor) | D107: =7.4*E33 | J107: Floor reference only
B108: Trailing 17.6x on FY27E EPS | D108: =D101*E33 | J108: No de-rating case
B109: DCF per share (cross-check) | D109: =D92
B110: Target-implied EV/EBITDA on FY27E (x) | D110: =(D14*D6-D89+D8)/'Financial Model'!K27 | J110: Memo 9.7x
B111: P/E on model FY27E EPS at $27.36 (x) | D111: =D4/E33 | J111: Memo 19x
...

Sheet Sources
B2: Item / cell | C2: Value ($M unless noted) | D2: Period | E2: Filing / source | F2: Caption | G2: URL
B3: Support!D4, D5, D10 price / market cap / Street EPS | C3: 27.36 / 25,300 / 1.75 | D3: 9/30/2026 | E3: CPRT_short_memo_v2.docx (Yahoo Finance prices and consensus) | F3: Header line; Valuation section | G3: n/a (memo)
B4: Support D19:F24 scenario drivers | C4: see sheet | D4: FY27E | E4: Memo Exhibit 2 | F4: FY27 EPS scenarios and price targets | G4: n/a (memo)
B5: Other income $110M FY27E | C5: 110 | D5: FY27E | E5: Memo, Thesis 3 / Valuation | F5: Other income after the ACV payment | G5: n/a (memo)
B6: ACV consideration | C6: 1,900 | D6: 9/10/2026 | E6: Copart 8-K Ex.99.1 | F6: $10.50 per share, implied equity value ~$1.9B; accretive in fiscal 2028 | G6: https://www.sec.gov/Archives/edgar/data/900075/000119312526388064/d138322dex991.htm
B7: FY26 10-K (filed 9/28/2026) | C7: reference | D7: FY2026 | E7: Form 10-K | F7: Audited statements; release figures used for inputs | G7: https://www.sec.gov/Archives/edgar/data/900075/000119312526405731/cprt-20260731.htm
B8: Unit / per-car statistics | C8: see Drivers V192-V196, Support rows 119-126 | D8: Q4 FY26 | E8: Q4 FY26 earnings call transcript | F8: CEO / CFO prepared remarks | G8: https://www.fool.com/earnings/call-transcripts/2026/09/11/copart-cprt-q4-2026-earnings-call-transcript/
B9: Industry stats (CCC, J.D. Power, IIHS, NHTSA FMVSS 127, BLS CPI, FRED) | C9: as cited | D9: various | E9: Memo source list | F9: Cited as memo sources, not re-estimated | G9: n/a (memo)
B10: Ritchie Bros / IAA precedent | C10: 7,300 EV; 13.6x | D10: 11/7/2022 | E10: Ritchie Bros 8-K Ex.99.1 | F10: Transaction valued at ~$7.3B incl. $1.0B net debt; 13.6x LTM Adjusted EBITDA | G10: https://www.sec.gov/Archives/edgar/data/1046102/000110465922115108/tm2229848d1_ex99-1.htm
B11: Hist!G9 Service revenues | C11: 3198.128 | D11: FY2023 | E11: 8-K Ex.99.1 (Q4 FY23 release, 9/14/2023) / FY23 10-K | F11: Service revenues | G11: https://www.sec.gov/Archives/edgar/data/900075/000090007523000027/cprt07312023ex99-1.htm
B12: Hist!H9 Service revenues | C12: 3561.002 | D12: FY2024 | E12: 8-K Ex.99.1 (Q4 FY24 release, 9/4/2024) / FY24 10-K | F12: Service revenues | G12: https://www.sec.gov/Archives/edgar/data/900075/000090007524000019/cprt07312024ex99-1.htm
B13: Hist!I9 Service revenues | C13: 3968.662 | D13: FY2025 | E13: 8-K Ex.99.1 (Q4 FY26 release, 9/10/2026, prior-year column) / FY26 10-K | F13: Service revenues | G13: https://www.sec.gov/Archives/edgar/data/900075/000119312526387902/cprt-ex99_1.htm
B14: Hist!J9 Service revenues | C14: 3969.52 | D14: FY2026 | E14: 8-K Ex.99.1 (Q4 FY26 release, 9/10/2026) / FY26 10-K filed 9/28/2026 | F14: Service revenues | G14: https://www.sec.gov/Archives/edgar/data/900075/000119312526387902/cprt-ex99_1.htm
B15: Hist!G10 Vehicle sales | C15: 671.39 | D15: FY2023 | E15: 8-K Ex.99.1 (Q4 FY23 release, 9/14/2023) / FY23 10-K | F15: Vehicle sales | G15: https://www.sec.gov/Archives/edgar/data/900075/000090007523000027/cprt07312023ex99-1.htm
B16: Hist!H10 Vehicle sales | C16: 675.821 | D16: FY2024 | E16: 8-K Ex.99.1 (Q4 FY24 release, 9/4/2024) / FY24 10-K | F16: Vehicle sales | G16: https://www.sec.gov/Archives/edgar/data/900075/000090007524000019/cprt07312024ex99-1.htm
B17: Hist!I10 Vehicle sales | C17: 678.296 | D17: FY2025 | E17: 8-K Ex.99.1 (Q4 FY26 release, 9/10/2026, prior-year column) / FY26 10-K | F17: Vehicle sales | G17: https://www.sec.gov/Archives/edgar/data/900075/000119312526387902/cprt-ex99_1.htm
B18: Hist!J10 Vehicle sales | C18: 696.689 | D18: FY2026 | E18: 8-K Ex.99.1 (Q4 FY26 release, 9/10/2026) / FY26 10-K filed 9/28/2026 | F18: Vehicle sales | G18: https://www.sec.gov/Archives/edgar/data/900075/000119312526387902/cprt-ex99_1.htm
B19: Hist!G13 Facility operations (incl. facility SBC; ex-D&A) | C19: 1369.006+6.926-(159.684-142.097-17.381) | D19: FY2023 | E19: 8-K Ex.99.1 (Q4 FY23 release, 9/14/2023) / FY23 10-K | F19: Yard/Facility operations + Yard/Facility SBC - (CFS D&A - IS D&A captions) | G19: https://www.sec.gov/Archives/edgar/data/900075/000090007523000027/cprt07312023ex99-1.htm
B20: Hist!H13 Facility operations (incl. facility SBC; ex-D&A) | C20: 1532.484+6.95-(190.256-170.65-19.111) | D20: FY2024 | E20: 8-K Ex.99.1 (Q4 FY24 release, 9/4/2024) / FY24 10-K | F20: Yard/Facility operations + Yard/Facility SBC - (CFS D&A - IS D&A captions) | G20: https://www.sec.gov/Archives/edgar/data/900075/000090007524000019/cprt07312024ex99-1.htm
B21: Hist!I13 Facility operations (incl. facility SBC; ex-D&A) | C21: 1744.436+8.107-(217.784-191.775-24.074) | D21: FY2025 | E21: 8-K Ex.99.1 (Q4 FY26 release, 9/10/2026, prior-year column) / FY26 10-K | F21: Yard/Facility operations + Yard/Facility SBC - (CFS D&A - IS D&A captions) | G21: https://www.sec.gov/Archives/edgar/data/900075/000119312526387902/cprt-ex99_1.htm
B22: Hist!J13 Facility operations (incl. facility SBC; ex-D&A) | C22: 1755.747+8.472-(238.466-201.669-27.704) | D22: FY2026 | E22: 8-K Ex.99.1 (Q4 FY26 release, 9/10/2026) / FY26 10-K filed 9/28/2026 | F22: Yard/Facility operations + Yard/Facility SBC - (CFS D&A - IS D&A captions) | G22: https://www.sec.gov/Archives/edgar/data/900075/000119312526387902/cprt-ex99_1.htm
B23: Hist!G14 Cost of vehicle sales | C23: 614.498 | D23: FY2023 | E23: 8-K Ex.99.1 (Q4 FY23 release, 9/14/2023) / FY23 10-K | F23: Cost of vehicle sales | G23: https://www.sec.gov/Archives/edgar/data/900075/000090007523000027/cprt07312023ex99-1.htm
B24: Hist!H14 Cost of vehicle sales | C24: 619.487 | D24: FY2024 | E24: 8-K Ex.99.1 (Q4 FY24 release, 9/4/2024) / FY24 10-K | F24: Cost of vehicle sales | G24: https://www.sec.gov/Archives/edgar/data/900075/000090007524000019/cprt07312024ex99-1.htm
B25: Hist!I14 Cost of vehicle sales | C25: 602.997 | D25: FY2025 | E25: 8-K Ex.99.1 (Q4 FY26 release, 9/10/2026, prior-year column) / FY26 10-K | F25: Cost of vehicle sales | G25: https://www.sec.gov/Archives/edgar/data/900075/000119312526387902/cprt-ex99_1.htm
B26: Hist!J14 Cost of vehicle sales | C26: 616.463 | D26: FY2026 | E26: 8-K Ex.99.1 (Q4 FY26 release, 9/10/2026) / FY26 10-K filed 9/28/2026 | F26: Cost of vehicle sales | G26: https://www.sec.gov/Archives/edgar/data/900075/000119312526387902/cprt-ex99_1.htm
B27: Hist!G21 General & Administrative | C27: 200.294+32.747 | D27: FY2023 | E27: 8-K Ex.99.1 (Q4 FY23 release, 9/14/2023) / FY23 10-K | F27: General and administrative + G&A stock-based compensation | G27: https://www.sec.gov/Archives/edgar/data/900075/000090007523000027/cprt07312023ex99-1.htm
B28: Hist!H21 General & Administrative | C28: 287.834+28.284 | D28: FY2024 | E28: 8-K Ex.99.1 (Q4 FY24 release, 9/4/2024) / FY24 10-K | F28: General and administrative + G&A stock-based compensation | G28: https://www.sec.gov/Archives/edgar/data/900075/000090007524000019/cprt07312024ex99-1.htm
B29: Hist!I21 General & Administrative | C29: 348.958+29.897 | D29: FY2025 | E29: 8-K Ex.99.1 (Q4 FY26 release, 9/10/2026, prior-year column) / FY26 10-K | F29: General and administrative + G&A stock-based compensation | G29: https://www.sec.gov/Archives/edgar/data/900075/000119312526387902/cprt-ex99_1.htm
B30: Hist!J21 General & Administrative | C30: 373.218+30.346 | D30: FY2026 | E30: 8-K Ex.99.1 (Q4 FY26 release, 9/10/2026) / FY26 10-K filed 9/28/2026 | F30: General and administrative + G&A stock-based compensation | G30: https://www.sec.gov/Archives/edgar/data/900075/000119312526387902/cprt-ex99_1.htm
B31: Hist!G22 Sales & Marketing | C31: 0 | D31: FY2023 | E31: 8-K Ex.99.1 (Q4 FY23 release, 9/14/2023) / FY23 10-K | F31: Not broken out in 10-K | G31: https://www.sec.gov/Archives/edgar/data/900075/000090007523000027/cprt07312023ex99-1.htm
B32: Hist!H22 Sales & Marketing | C32: 0 | D32: FY2024 | E32: 8-K Ex.99.1 (Q4 FY24 release, 9/4/2024) / FY24 10-K | F32: Not broken out in 10-K | G32: https://www.sec.gov/Archives/edgar/data/900075/000090007524000019/cprt07312024ex99-1.htm
B33: Hist!I22 Sales & Marketing | C33: 0 | D33: FY2025 | E33: 8-K Ex.99.1 (Q4 FY26 release, 9/10/2026, prior-year column) / FY26 10-K | F33: Not broken out in 10-K | G33: https://www.sec.gov/Archives/edgar/data/900075/000119312526387902/cprt-ex99_1.htm
B34: Hist!J22 Sales & Marketing | C34: 0 | D34: FY2026 | E34: 8-K Ex.99.1 (Q4 FY26 release, 9/10/2026) / FY26 10-K filed 9/28/2026 | F34: Not broken out in 10-K | G34: https://www.sec.gov/Archives/edgar/data/900075/000119312526387902/cprt-ex99_1.htm
B35: Hist!G23 Research & Development | C35: 0 | D35: FY2023 | E35: 8-K Ex.99.1 (Q4 FY23 release, 9/14/2023) / FY23 10-K | F35: Not broken out in 10-K | G35: https://www.sec.gov/Archives/edgar/data/900075/000090007523000027/cprt07312023ex99-1.htm
B36: Hist!H23 Research & Development | C36: 0 | D36: FY2024 | E36: 8-K Ex.99.1 (Q4 FY24 release, 9/4/2024) / FY24 10-K | F36: Not broken out in 10-K | G36: https://www.sec.gov/Archives/edgar/data/900075/000090007524000019/cprt07312024ex99-1.htm
B37: Hist!I23 Research & Development | C37: 0 | D37: FY2025 | E37: 8-K Ex.99.1 (Q4 FY26 release, 9/10/2026, prior-year column) / FY26 10-K | F37: Not broken out in 10-K | G37: https://www.sec.gov/Archives/edgar/data/900075/000119312526387902/cprt-ex99_1.htm
B38: Hist!J23 Research & Development | C38: 0 | D38: FY2026 | E38: 8-K Ex.99.1 (Q4 FY26 release, 9/10/2026) / FY26 10-K filed 9/28/2026 | F38: Not broken out in 10-K | G38: https://www.sec.gov/Archives/edgar/data/900075/000119312526387902/cprt-ex99_1.htm
B39: Hist!G30 Depreciation | C39: 159.684 | D39: FY2023 | E39: 8-K Ex.99.1 (Q4 FY23 release, 9/14/2023) / FY23 10-K | F39: CFS: Depreciation and amortization, including debt cost (total D&A; amortization not split) | G39: https://www.sec.gov/Archives/edgar/data/900075/000090007523000027/cprt07312023ex99-1.htm
B40: Hist!H30 Depreciation | C40: 190.256 | D40: FY2024 | E40: 8-K Ex.99.1 (Q4 FY24 release, 9/4/2024) / FY24 10-K | F40: CFS: Depreciation and amortization, including debt cost (total D&A; amortization not split) | G40: https://www.sec.gov/Archives/edgar/data/900075/000090007524000019/cprt07312024ex99-1.htm
B41: Hist!I30 Depreciation | C41: 217.784 | D41: FY2025 | E41: 8-K Ex.99.1 (Q4 FY26 release, 9/10/2026, prior-year column) / FY26 10-K | F41: CFS: Depreciation and amortization, including debt cost (total D&A; amortization not split) | G41: https://www.sec.gov/Archives/edgar/data/900075/000119312526387902/cprt-ex99_1.htm
B42: Hist!J30 Depreciation | C42: 238.466 | D42: FY2026 | E42: 8-K Ex.99.1 (Q4 FY26 release, 9/10/2026) / FY26 10-K filed 9/28/2026 | F42: CFS: Depreciation and amortization, including debt cost (total D&A; amortization not split) | G42: https://www.sec.gov/Archives/edgar/data/900075/000119312526387902/cprt-ex99_1.htm
... B50: Hist!J36 Interest Expense | C50: 1.866 | D50: FY2026 | E50: 8-K Ex.99.1 (Q4 FY26 release, 9/10/2026) / FY26 10-K filed 9/28/2026 | F50: CFS supplemental: Interest paid (cash interest on debt) | G50: https://www.sec.gov/Archives/edgar/data/900075/000119312526387902/cprt-ex99_1.htm
B51: Hist!G38 Interest income, gross (= -(Interest income, net + interest paid)) | C51: -(65.928+2.614) | D51: FY2023 | E51: 8-K Ex.99.1 (Q4 FY23 release, 9/14/2023) / FY23 10-K | F51: Interest income (expense), net; Interest paid | G51: https://www.sec.gov/Archives/edgar/data/900075/000090007523000027/cprt07312023ex99-1.htm
B52: Hist!H38 Interest income, gross (= -(Interest income, net + interest paid)) | C52: -(145.673+3.127) | D52: FY2024 | E52: 8-K Ex.99.1 (Q4 FY24 release, 9/4/2024) / FY24 10-K | F52: Interest income (expense), net; Interest paid | G52: https://www.sec.gov/Archives/edgar/data/900075/000090007524000019/cprt07312024ex99-1.htm
B53: Hist!I38 Interest income, gross (= -(Interest income, net + interest paid)) | C53: -(178.909+2.019) | D53: FY2025 | E53: 8-K Ex.99.1 (Q4 FY26 release, 9/10/2026, prior-year column) / FY26 10-K | F53: Interest income (expense), net; Interest paid | G53: https://www.sec.gov/Archives/edgar/data/900075/000119312526387902/cprt-ex99_1.htm
B54: Hist!J38 Interest income, gross (= -(Interest income, net + interest paid)) | C54: -(181.923+1.866) | D54: FY2026 | E54: 8-K Ex.99.1 (Q4 FY26 release, 9/10/2026) / FY26 10-K filed 9/28/2026 | F54: Interest income (expense), net; Interest paid | G54: https://www.sec.gov/Archives/edgar/data/900075/000119312526387902/cprt-ex99_1.htm
B55: Hist!G39 Other (income) expense, net | C55: -1.831 | D55: FY2023 | E55: 8-K Ex.99.1 (Q4 FY23 release, 9/14/2023) / FY23 10-K | F55: Other income (expense), net (sign reversed) | G55: https://www.sec.gov/Archives/edgar/data/900075/000090007523000027/cprt07312023ex99-1.htm
B56: Hist!H39 Other (income) expense, net | C56: 3.095 | D56: FY2024 | E56: 8-K Ex.99.1 (Q4 FY24 release, 9/4/2024) / FY24 10-K | F56: Other income (expense), net (sign reversed) | G56: https://www.sec.gov/Archives/edgar/data/900075/000090007524000019/cprt07312024ex99-1.htm
B57: Hist!I39 Other (income) expense, net | C57: -19.958 | D57: FY2025 | E57: 8-K Ex.99.1 (Q4 FY26 release, 9/10/2026, prior-year column) / FY26 10-K | F57: Other income (expense), net (sign reversed) | G57: https://www.sec.gov/Archives/edgar/data/900075/000119312526387902/cprt-ex99_1.htm
B58: Hist!J39 Other (income) expense, net | C58: -0.464 | D58: FY2026 | E58: 8-K Ex.99.1 (Q4 FY26 release, 9/10/2026) / FY26 10-K filed 9/28/2026 | F58: Other income (expense), net (sign reversed) | G58: https://www.sec.gov/Archives/edgar/data/900075/000119312526387902/cprt-ex99_1.htm
B59: Hist!G40 Net loss attributable to noncontrolling interest | C59: 0 | D59: FY2023 | E59: 8-K Ex.99.1 (Q4 FY23 release, 9/14/2023) / FY23 10-K | F59: Less: Net loss attributable to noncontrolling interest (so NI = attributable to Copart) | G59: https://www.sec.gov/Archives/edgar/data/900075/000090007523000027/cprt07312023ex99-1.htm
B60: Hist!H40 Net loss attributable to noncontrolling interest | C60: -0.673 | D60: FY2024 | E60: 8-K Ex.99.1 (Q4 FY24 release, 9/4/2024) / FY24 10-K | F60: Less: Net loss attributable to noncontrolling interest (so NI = attributable to Copart) | G60: https://www.sec.gov/Archives/edgar/data/900075/000090007524000019/cprt07312024ex99-1.htm
B61: Hist!I40 Net loss attributable to noncontrolling interest | C61: -4.086 | D61: FY2025 | E61: 8-K Ex.99.1 (Q4 FY26 release, 9/10/2026, prior-year column) / FY26 10-K | F61: Less: Net loss attributable to noncontrolling interest (so NI = attributable to Copart) | G61: https://www.sec.gov/Archives/edgar/data/900075/000119312526387902/cprt-ex99_1.htm
B62: Hist!J40 Net loss attributable to noncontrolling interest | C62: -3.873 | D62: FY2026 | E62: 8-K Ex.99.1 (Q4 FY26 release, 9/10/2026) / FY26 10-K filed 9/28/2026 | F62: Less: Net loss attributable to noncontrolling interest (so NI = attributable to Copart) | G62: https://www.sec.gov/Archives/edgar/data/900075/000119312526387902/cprt-ex99_1.htm
B63: Hist!G47 Taxes | C63: 316.587 | D63: FY2023 | E63: 8-K Ex.99.1 (Q4 FY23 release, 9/14/2023) / FY23 10-K | F63: Income tax expense | G63: https://www.sec.gov/Archives/edgar/data/900075/000090007523000027/cprt07312023ex99-1.htm
B64: Hist!H47 Taxes | C64: 352.254 | D64: FY2024 | E64: 8-K Ex.99.1 (Q4 FY24 release, 9/4/2024) / FY24 10-K | F64: Income tax expense | G64: https://www.sec.gov/Archives/edgar/data/900075/000090007524000019/cprt07312024ex99-1.htm
B65: Hist!I47 Taxes | C65: 347.218 | D65: FY2025 | E65: 8-K Ex.99.1 (Q4 FY26 release, 9/10/2026, prior-year column) / FY26 10-K | F65: Income tax expense | G65: https://www.sec.gov/Archives/edgar/data/900075/000119312526387902/cprt-ex99_1.htm
B66: Hist!J47 Taxes | C66: 354.58 | D66: FY2026 | E66: 8-K Ex.99.1 (Q4 FY26 release, 9/10/2026) / FY26 10-K filed 9/28/2026 | F66: Income tax expense | G66: https://www.sec.gov/Archives/edgar/data/900075/000119312526387902/cprt-ex99_1.htm
... B70: Hist!J52 Company Reported Net Income | C70: 1484.27 | D70: FY2026 | E70: 8-K Ex.99.1 (Q4 FY26 release, 9/10/2026) / FY26 10-K filed 9/28/2026 | F70: Net income attributable to Copart, Inc. | G70: https://www.sec.gov/Archives/edgar/data/900075/000119312526387902/cprt-ex99_1.htm
B71: Hist!G59 Cash, equivalents, restricted cash + HTM securities | C71: 957.395+1406.589 | D71: FY2023 | E71: 8-K Ex.99.1 (Q4 FY23 release, 9/14/2023) / FY23 10-K | F71: Cash, cash equivalents, and restricted cash + Investment in held to maturity securities | G71: https://www.sec.gov/Archives/edgar/data/900075/000090007523000027/cprt07312023ex99-1.htm
B72: Hist!H59 Cash, equivalents, restricted cash + HTM securities | C72: 1514.111+1908.047 | D72: FY2024 | E72: 8-K Ex.99.1 (Q4 FY24 release, 9/4/2024) / FY24 10-K | F72: Cash, cash equivalents, and restricted cash + Investment in held to maturity securities | G72: https://www.sec.gov/Archives/edgar/data/900075/000090007524000019/cprt07312024ex99-1.htm
B73: Hist!I59 Cash, equivalents, restricted cash + HTM securities | C73: 2780.531+2008.539 | D73: FY2025 | E73: 8-K Ex.99.1 (Q4 FY26 release, 9/10/2026, prior-year column) / FY26 10-K | F73: Cash, cash equivalents, and restricted cash + Investment in held to maturity securities | G73: https://www.sec.gov/Archives/edgar/data/900075/000119312526387902/cprt-ex99_1.htm
B74: Hist!J59 Cash, equivalents, restricted cash + HTM securities | C74: 1907.901+2581.901 | D74: FY2026 | E74: 8-K Ex.99.1 (Q4 FY26 release, 9/10/2026) / FY26 10-K filed 9/28/2026 | F74: Cash, cash equivalents, and restricted cash + Investment in held to maturity securities | G74: https://www.sec.gov/Archives/edgar/data/900075/000119312526387902/cprt-ex99_1.htm
B75: Hist!G60 Accounts Receivable | C75: 702.038 | D75: FY2023 | E75: 8-K Ex.99.1 (Q4 FY23 release, 9/14/2023) / FY23 10-K | F75: Accounts receivable, net | G75: https://www.sec.gov/Archives/edgar/data/900075/000090007523000027/cprt07312023ex99-1.htm
B76: Hist!H60 Accounts Receivable | C76: 785.877 | D76: FY2024 | E76: 8-K Ex.99.1 (Q4 FY24 release, 9/4/2024) / FY24 10-K | F76: Accounts receivable, net | G76: https://www.sec.gov/Archives/edgar/data/900075/000090007524000019/cprt07312024ex99-1.htm
B77: Hist!I60 Accounts Receivable | C77: 762.811 | D77: FY2025 | E77: 8-K Ex.99.1 (Q4 FY26 release, 9/10/2026, prior-year column) / FY26 10-K | F77: Accounts receivable, net | G77: https://www.sec.gov/Archives/edgar/data/900075/000119312526387902/cprt-ex99_1.htm
B78: Hist!J60 Accounts Receivable | C78: 809.247 | D78: FY2026 | E78: 8-K Ex.99.1 (Q4 FY26 release, 9/10/2026) / FY26 10-K filed 9/28/2026 | F78: Accounts receivable, net | G78: https://www.sec.gov/Archives/edgar/data/900075/000119312526387902/cprt-ex99_1.htm
B79: Hist!G61 Prepaid Expenses | C79: 26.31 | D79: FY2023 | E79: 8-K Ex.99.1 (Q4 FY23 release, 9/14/2023) / FY23 10-K | F79: Prepaid expenses and other assets | G79: https://www.sec.gov/Archives/edgar/data/900075/000090007523000027/cprt07312023ex99-1.htm
B80: Hist!H61 Prepaid Expenses | C80: 33.872 | D80: FY2024 | E80: 8-K Ex.99.1 (Q4 FY24 release, 9/4/2024) / FY24 10-K | F80: Prepaid expenses and other assets | G80: https://www.sec.gov/Archives/edgar/data/900075/000090007524000019/cprt07312024ex99-1.htm
B81: Hist!I61 Prepaid Expenses | C81: 46.361 | D81: FY2025 | E81: 8-K Ex.99.1 (Q4 FY26 release, 9/10/2026, prior-year column) / FY26 10-K | F81: Prepaid expenses and other assets | G81: https://www.sec.gov/Archives/edgar/data/900075/000119312526387902/cprt-ex99_1.htm
B82: Hist!J61 Prepaid Expenses | C82: 44.959 | D82: FY2026 | E82: 8-K Ex.99.1 (Q4 FY26 release, 9/10/2026) / FY26 10-K filed 9/28/2026 | F82: Prepaid expenses and other assets | G82: https://www.sec.gov/Archives/edgar/data/900075/000119312526387902/cprt-ex99_1.htm
B83: Hist!G62 Inventories | C83: 39.973 | D83: FY2023 | E83: 8-K Ex.99.1 (Q4 FY23 release, 9/14/2023) / FY23 10-K | F83: Inventories | G83: https://www.sec.gov/Archives/edgar/data/900075/000090007523000027/cprt07312023ex99-1.htm
B84: Hist!H62 Inventories | C84: 43.639 | D84: FY2024 | E84: 8-K Ex.99.1 (Q4 FY24 release, 9/4/2024) / FY24 10-K | F84: Inventories | G84: https://www.sec.gov/Archives/edgar/data/900075/000090007524000019/cprt07312024ex99-1.htm
B85: Hist!I62 Inventories | C85: 39.661 | D85: FY2025 | E85: 8-K Ex.99.1 (Q4 FY26 release, 9/10/2026, prior-year column) / FY26 10-K | F85: Inventories | G85: https://www.sec.gov/Archives/edgar/data/900075/000119312526387902/cprt-ex99_1.htm
B86: Hist!J62 Inventories | C86: 51.382 | D86: FY2026 | E86: 8-K Ex.99.1 (Q4 FY26 release, 9/10/2026) / FY26 10-K filed 9/28/2026 | F86: Inventories | G86: https://www.sec.gov/Archives/edgar/data/900075/000119312526387902/cprt-ex99_1.htm
B87: Hist!G63 Vehicle pooling costs + income taxes receivable | C87: 123.725+6.574 | D87: FY2023 | E87: 8-K Ex.99.1 (Q4 FY23 release, 9/14/2023) / FY23 10-K | F87: Vehicle pooling costs + Income taxes receivable | G87: https://www.sec.gov/Archives/edgar/data/900075/000090007523000027/cprt07312023ex99-1.htm
B88: Hist!H63 Vehicle pooling costs + income taxes receivable | C88: 132.638+0 | D88: FY2024 | E88: 8-K Ex.99.1 (Q4 FY24 release, 9/4/2024) / FY24 10-K | F88: Vehicle pooling costs + Income taxes receivable | G88: https://www.sec.gov/Archives/edgar/data/900075/000090007524000019/cprt07312024ex99-1.htm
B89: Hist!I63 Vehicle pooling costs + income taxes receivable | C89: 116.145+0.58 | D89: FY2025 | E89: 8-K Ex.99.1 (Q4 FY26 release, 9/10/2026, prior-year column) / FY26 10-K | F89: Vehicle pooling costs + Income taxes receivable | G89: https://www.sec.gov/Archives/edgar/data/900075/000119312526387902/cprt-ex99_1.htm
B90: Hist!J63 Vehicle pooling costs + income taxes receivable | C90: 122.948+49.856 | D90: FY2026 | E90: 8-K Ex.99.1 (Q4 FY26 release, 9/10/2026) / FY26 10-K filed 9/28/2026 | F90: Vehicle pooling costs + Income taxes receivable | G90: https://www.sec.gov/Archives/edgar/data/900075/000119312526387902/cprt-ex99_1.htm
B91: Hist!G66 PP&E, net (gross/accumulated split not loaded) | C91: 2844.339 | D91: FY2023 | E91: 8-K Ex.99.1 (Q4 FY23 release, 9/14/2023) / FY23 10-K | F91: Property and equipment, net | G91: https://www.sec.gov/Archives/edgar/data/900075/000090007523000027/cprt07312023ex99-1.htm
B92: Hist!H66 PP&E, net (gross/accumulated split not loaded) | C92: 3175.838 | D92: FY2024 | E92: 8-K Ex.99.1 (Q4 FY24 release, 9/4/2024) / FY24 10-K | F92: Property and equipment, net | G92: https://www.sec.gov/Archives/edgar/data/900075/000090007524000019/cprt07312024ex99-1.htm
B93: Hist!I66 PP&E, net (gross/accumulated split not loaded) | C93: 3598.093 | D93: FY2025 | E93: 8-K Ex.99.1 (Q4 FY26 release, 9/10/2026, prior-year column) / FY26 10-K | F93: Property and equipment, net | G93: https://www.sec.gov/Archives/edgar/data/900075/000119312526387902/cprt-ex99_1.htm
B94: Hist!J66 PP&E, net (gross/accumulated split not loaded) | C94: 3733.22 | D94: FY2026 | E94: 8-K Ex.99.1 (Q4 FY26 release, 9/10/2026) / FY26 10-K filed 9/28/2026 | F94: Property and equipment, net | G94: https://www.sec.gov/Archives/edgar/data/900075/000119312526387902/cprt-ex99_1.htm
B95: Hist!G67 (Accumulated Depreciation) | C95: 0 | D95: FY2023 | E95: 8-K Ex.99.1 (Q4 FY23 release, 9/14/2023) / FY23 10-K | F95: Not loaded (net basis in row 66) | G95: https://www.sec.gov/Archives/edgar/data/900075/000090007523000027/cprt07312023ex99-1.htm
B96: Hist!H67 (Accumulated Depreciation) | C96: 0 | D96: FY2024 | E96: 8-K Ex.99.1 (Q4 FY24 release, 9/4/2024) / FY24 10-K | F96: Not loaded (net basis in row 66) | G96: https://www.sec.gov/Archives/edgar/data/900075/000090007524000019/cprt07312024ex99-1.htm
B97: Hist!I67 (Accumulated Depreciation) | C97: 0 | D97: FY2025 | E97: 8-K Ex.99.1 (Q4 FY26 release, 9/10/2026, prior-year column) / FY26 10-K | F97: Not loaded (net basis in row 66) | G97: https://www.sec.gov/Archives/edgar/data/900075/000119312526387902/cprt-ex99_1.htm
B98: Hist!J67 (Accumulated Depreciation) | C98: 0 | D98: FY2026 | E98: 8-K Ex.99.1 (Q4 FY26 release, 9/10/2026) / FY26 10-K filed 9/28/2026 | F98: Not loaded (net basis in row 66) | G98: https://www.sec.gov/Archives/edgar/data/900075/000119312526387902/cprt-ex99_1.htm
B99: Hist!G71 Goodwill + intangibles, net | C99: 394.289+62.702 | D99: FY2023 | E99: 8-K Ex.99.1 (Q4 FY23 release, 9/14/2023) / FY23 10-K | F99: Goodwill + Intangibles, net | G99: https://www.sec.gov/Archives/edgar/data/900075/000090007523000027/cprt07312023ex99-1.htm
B100: Hist!H71 Goodwill + intangibles, net | C100: 513.909+74.088 | D100: FY2024 | E100: 8-K Ex.99.1 (Q4 FY24 release, 9/4/2024) / FY24 10-K | F100: Goodwill + Intangibles, net | G100: https://www.sec.gov/Archives/edgar/data/900075/000090007524000019/cprt07312024ex99-1.htm
B101: Hist!I71 Goodwill + intangibles, net | C101: 517.779+62.832 | D101: FY2025 | E101: 8-K Ex.99.1 (Q4 FY26 release, 9/10/2026, prior-year column) / FY26 10-K | F101: Goodwill + Intangibles, net | G101: https://www.sec.gov/Archives/edgar/data/900075/000119312526387902/cprt-ex99_1.htm
B102: Hist!J71 Goodwill + intangibles, net | C102: 511.297+50.477 | D102: FY2026 | E102: 8-K Ex.99.1 (Q4 FY26 release, 9/10/2026) / FY26 10-K filed 9/28/2026 | F102: Goodwill + Intangibles, net | G102: https://www.sec.gov/Archives/edgar/data/900075/000119312526387902/cprt-ex99_1.htm
B103: Hist!G72 (Accumulated Amortization) | C103: 0 | D103: FY2023 | E103: 8-K Ex.99.1 (Q4 FY23 release, 9/14/2023) / FY23 10-K | F103: Not loaded (net basis in row 71) | G103: https://www.sec.gov/Archives/edgar/data/900075/000090007523000027/cprt07312023ex99-1.htm
B104: Hist!H72 (Accumulated Amortization) | C104: 0 | D104: FY2024 | E104: 8-K Ex.99.1 (Q4 FY24 release, 9/4/2024) / FY24 10-K | F104: Not loaded (net basis in row 71) | G104: https://www.sec.gov/Archives/edgar/data/900075/000090007524000019/cprt07312024ex99-1.htm
B105: Hist!I72 (Accumulated Amortization) | C105: 0 | D105: FY2025 | E105: 8-K Ex.99.1 (Q4 FY26 release, 9/10/2026, prior-year column) / FY26 10-K | F105: Not loaded (net basis in row 71) | G105: https://www.sec.gov/Archives/edgar/data/900075/000119312526387902/cprt-ex99_1.htm
B106: Hist!J72 (Accumulated Amortization) | C106: 0 | D106: FY2026 | E106: 8-K Ex.99.1 (Q4 FY26 release, 9/10/2026) / FY26 10-K filed 9/28/2026 | F106: Not loaded (net basis in row 71) | G106: https://www.sec.gov/Archives/edgar/data/900075/000119312526387902/cprt-ex99_1.htm
B107: Hist!G76 Operating lease ROU assets + other assets | C107: 108.139+65.806 | D107: FY2023 | E107: 8-K Ex.99.1 (Q4 FY23 release, 9/14/2023) / FY23 10-K | F107: Operating lease right-of-use assets + Other assets | G107: https://www.sec.gov/Archives/edgar/data/900075/000090007523000027/cprt07312023ex99-1.htm
B108: Hist!H76 Operating lease ROU assets + other assets | C108: 116.301+129.444 | D108: FY2024 | E108: 8-K Ex.99.1 (Q4 FY24 release, 9/4/2024) / FY24 10-K | F108: Operating lease right-of-use assets + Other assets | G108: https://www.sec.gov/Archives/edgar/data/900075/000090007524000019/cprt07312024ex99-1.htm
B109: Hist!I76 Operating lease ROU assets + other assets | C109: 99.708+57.862 | D109: FY2025 | E109: 8-K Ex.99.1 (Q4 FY26 release, 9/10/2026, prior-year column) / FY26 10-K | F109: Operating lease right-of-use assets + Other assets | G109: https://www.sec.gov/Archives/edgar/data/900075/000119312526387902/cprt-ex99_1.htm
B110: Hist!J76 Operating lease ROU assets + other assets | C110: 83.728+80.894 | D110: FY2026 | E110: 8-K Ex.99.1 (Q4 FY26 release, 9/10/2026) / FY26 10-K filed 9/28/2026 | F110: Operating lease right-of-use assets + Other assets | G110: https://www.sec.gov/Archives/edgar/data/900075/000119312526387902/cprt-ex99_1.htm
B111: Hist!G82 Accounts Payable | C111: 440.81 | D111: FY2023 | E111: 8-K Ex.99.1 (Q4 FY23 release, 9/14/2023) / FY23 10-K | F111: Accounts payable and accrued liabilities (reported combined) | G111: https://www.sec.gov/Archives/edgar/data/900075/000090007523000027/cprt07312023ex99-1.htm
...
